Workbook
Name Augusttotalinfracash: Calculations!#REF!
Name BalAug: Calculations!#REF!
Name Excessinfracash2023: final!$H$1
Name FL: [1]Calculations!$G$43
Name FL_Total: 'Loan Applicants'!#REF!
Name FLAUGUST2024: Calculations!$D$32
Name INFINVEST: [1]Shares!$B$4:$Z$41
Name INFINVEST: Summary!$B$4:$Z$26
Name INFINVEST: Shares!$B$4:$Z$28
Name INFMO: [1]Shares!$B$4:$Z$41
Name INFMONEYSHARES: [1]Shares!$B$4:$Z$42
Name infracashexcess2024: 'REDLIST ALERT'!$D$38
Name INFRACASHshares2025: Shares!$B$4:$Z$29
Name INFRCASHTOTALSHARE2023: Shares!$Y$31
Name INFSHARES: Shares!$B$4:$X$29
Name INFSHARES: Summary!$B$4:$X$33
Name INFSHARES: Shares!$B$4:$X$28
Name INFTOTAL: Shares!$Y$31
Name INFTOTAL: Summary!$Y$34
Name INFTOTAL: Shares!$Y$30
Name loan: 'New Repayment Schedule'!$H$6:$DD$30
Name LOANTOTAL: #REF!
Name LOANTOTAL: #REF!
Name TotalFL: Summary!$Y$36
Name TotalFL: Shares!$Y$32
Name Totalinfracash2024: Shares!$Y$30-Shares!$Y$29
Name TOTALLOAN: 'LOAN BALANCE'!$B$3:$M$33

Sheet Shares
B2: MEETING | C2: NOVEMBER | E2: DECEMBER | G2: JANUARY | I2: FEBUARY | K2: MARCH | M2: APRIL | O2: MAY | Q2: JUNE | S2: JULY | U2: AUGUST
A3: No | B3: FULL NAMES | C3: SHARES | D3: TOTAL | E3: SHARES | F3: TOTAL | G3: SHARES | H3: TOTAL | I3: SHARES | J3: TOTAL | K3: SHARES | L3: TOTAL | M3: SHARES | N3: TOTAL | O3: SHARES | P3: TOTAL | Q3: SHARES | R3: TOTAL | S3: SHARES | T3: TOTAL | U3: SHARES | V3: TOTAL | X3: GRAND SHARES | Y3: GRAND TOTAL INVESTED | Z3: LOAN ELIGIBILTY
A4: 1 | B4: Abigail Mundia | C4: =D4/200 -> 1 | D4: 200 | E4: =F4/200 -> 75 | F4: 15000 | G4: =H4/200 -> 1 | H4: 200 | I4: =J4/200 -> 1 | J4: 200 | K4: =L4/200 -> 50 | L4: 10000 | M4: =N4/200 -> 1 | N4: 200 | O4: =P4/200 -> 1 | P4: 200 | Q4: =R4/200 -> 1 | R4: 200 | S4: =T4/200 -> 1 | T4: 200 | U4: =V4/200 -> 5 | V4: 1000 | Y4: =D4+F4+H4+J4+L4+N4+P4+R4+T4+V4 -> 27400 | Z4: =Y4*3 -> 82200 | AA4: {=Y4/Totalinfracash2024} -> 0.063455303
A5: 2 | B5: Abel Kunda | C5: =D5/200 -> 0 | E5: =F5/200 -> 0 | G5: =H5/200 -> 0 | I5: =J5/200 -> 0 | K5: =L5/200 -> 240 | L5: 48000 | M5: =N5/200 -> 1 | N5: 200 | O5: =P5/200 -> 1 | P5: 200 | Q5: =R5/200 -> 1 | R5: 200 | S5: =T5/200 -> 1 | T5: 200 | U5: =V5/200 -> 1 | V5: 200 | Y5: =D5+F5+H5+J5+L5+N5+P5+R5+T5+V5 -> 49000 | Z5: =Y5*3 -> 147000 | AA5: {=Y5/Totalinfracash2024} -> 0.11347846
A6: 3 | B6: Andrew | C6: =D6/200 -> 6 | D6: 1200 | E6: =F6/200 -> 1 | F6: 200 | G6: =H6/200 -> 1 | H6: 200 | I6: =J6/200 -> 1 | J6: 200 | K6: =L6/200 -> 15 | L6: 3000 | M6: =N6/200 -> 1 | N6: 200 | O6: =P6/200 -> 1 | P6: 200 | Q6: =R6/200 -> 1 | R6: 200 | S6: =T6/200 -> 1 | T6: 200 | U6: =V6/200 -> 1 | V6: 200 | Y6: =D6+F6+H6+J6+L6+N6+P6+R6+T6+V6 -> 5800 | Z6: =Y6*3 -> 17400 | AA6: {=Y6/Totalinfracash2024} -> 0.013432145
A7: 4 | B7: Arthur | C7: =D7/200 -> 1 | D7: 200 | E7: =F7/200 -> 1 | F7: 200 | G7: =H7/200 -> 2 | H7: 400 | I7: =J7/200 -> 1 | J7: 200 | K7: =L7/200 -> 2 | L7: 400 | M7: =N7/200 -> 2 | N7: 400 | O7: =P7/200 -> 5 | P7: 1000 | Q7: =R7/200 -> 15 | R7: 3000 | S7: =T7/200 -> 1 | T7: 200 | U7: =V7/200 -> 1 | V7: 200 | Y7: =D7+F7+H7+J7+L7+N7+P7+R7+T7+V7 -> 6200 | Z7: =Y7*3 -> 18600 | AA7: {=Y7/Totalinfracash2024} -> 0.014358499
A8: 5 | B8: Evans | C8: =D8/200 -> 25 | D8: 5000 | E8: =F8/200 -> 1 | F8: 200 | G8: =H8/200 -> 10 | H8: 2000 | I8: =J8/200 -> 1 | J8: 200 | K8: =L8/200 -> 1 | L8: 200 | M8: =N8/200 -> 10 | N8: 2000 | O8: =P8/200 -> 1 | P8: 200 | Q8: =R8/200 -> 1 | R8: 200 | S8: =T8/200 -> 1 | T8: 200 | U8: =V8/200 -> 1 | V8: 200 | Y8: =D8+F8+H8+J8+L8+N8+P8+R8+T8+V8 -> 10400 | Z8: =Y8*3 -> 31200 | AA8: {=Y8/Totalinfracash2024} -> 0.024085225
A9: 6 | B9: Jesper | C9: =D9/200 -> 1 | D9: 200 | E9: =F9/200 -> 1 | F9: 200 | G9: =H9/200 -> 1 | H9: 200 | I9: =J9/200 -> 1 | J9: 200 | K9: =L9/200 -> 1 | L9: 200 | M9: =N9/200 -> 1 | N9: 200 | O9: =P9/200 -> 1 | P9: 200 | Q9: =R9/200 -> 2 | R9: 400 | S9: =T9/200 -> 1 | T9: 200 | U9: =V9/200 -> 1 | V9: 200 | Y9: =D9+F9+H9+J9+L9+N9+P9+R9+T9+V9 -> 2200 | Z9: =Y9*3 -> 6600 | AA9: {=Y9/Totalinfracash2024} -> 0.0050949514
A10: 7 | B10: Joshua | C10: =D10/200 -> 1 | D10: 200 | E10: =F10/200 -> 1 | F10: 200 | G10: =H10/200 -> 1 | H10: 200 | I10: =J10/200 -> 1 | J10: 200 | K10: =L10/200 -> 1 | L10: 200 | M10: =N10/200 -> 1 | N10: 200 | O10: =P10/200 -> 1 | P10: 200 | Q10: =R10/200 -> 50 | R10: 10000 | S10: =T10/200 -> 5 | T10: 1000 | U10: =V10/200 -> 5 | V10: 1000 | Y10: =D10+F10+H10+J10+L10+N10+P10+R10+T10+V10 -> 13400 | Z10: =Y10*3 -> 40200 | AA10: {=Y10/Totalinfracash2024} -> 0.031032886
A11: 8 | B11: Kampamba | C11: =D11/200 -> 2 | D11: 400 | E11: =F11/200 -> 2 | F11: 400 | G11: =H11/200 -> 6 | H11: 1200 | I11: =J11/200 -> 2 | J11: 400 | K11: =L11/200 -> 2 | L11: 400 | M11: =N11/200 -> 18 | N11: 3600 | O11: =P11/200 -> 1 | P11: 200 | Q11: =R11/200 -> 1 | R11: 200 | S11: =T11/200 -> 1 | T11: 200 | U11: =V11/200 -> 2 | V11: 400 | Y11: =D11+F11+H11+J11+L11+N11+P11+R11+T11+V11 -> 7400 | Z11: =Y11*3 -> 22200 | AA11: {=Y11/Totalinfracash2024} -> 0.017137564
A12: 9 | B12: Karen Mwinga | C12: =D12/200 -> 5 | D12: 1000 | E12: =F12/200 -> 1 | F12: 200 | G12: =H12/200 -> 1 | H12: 200 | I12: =J12/200 -> 1 | J12: 200 | K12: =L12/200 -> 5 | L12: 1000 | M12: =N12/200 -> 1 | N12: 200 | O12: =P12/200 -> 5 | P12: 1000 | Q12: =R12/200 -> 5 | R12: 1000 | S12: =T12/200 -> 1 | T12: 200 | U12: =V12/200 -> 1 | V12: 200 | Y12: =D12+F12+H12+J12+L12+N12+P12+R12+T12+V12 -> 5200 | Z12: =Y12*3 -> 15600 | AA12: {=Y12/Totalinfracash2024} -> 0.012042612
A13: 10 | B13: Keji | C13: =D13/200 -> 1 | D13: 200 | E13: =F13/200 -> 1 | F13: 200 | G13: =H13/200 -> 1 | H13: 200 | I13: =J13/200 -> 24 | J13: 4800 | K13: =L13/200 -> 1 | L13: 200 | M13: =N13/200 -> 1 | N13: 200 | O13: =P13/200 -> 1 | P13: 200 | Q13: =R13/200 -> 1 | R13: 200 | S13: =T13/200 -> 1 | T13: 200 | U13: =V13/200 -> 1 | V13: 200 | Y13: =D13+F13+H13+J13+L13+N13+P13+R13+T13+V13 -> 6600 | Z13: =Y13*3 -> 19800 | AA13: {=Y13/Totalinfracash2024} -> 0.015284854
A14: 11 | B14: Kombe | C14: =D14/200 -> 1 | D14: 200 | E14: =F14/200 -> 1 | F14: 200 | G14: =H14/200 -> 1 | H14: 200 | I14: =J14/200 -> 1 | J14: 200 | K14: =L14/200 -> 75 | L14: 15000 | M14: =N14/200 -> 1 | N14: 200 | O14: =P14/200 -> 75 | P14: 15000 | Q14: =R14/200 -> 2 | R14: 400 | S14: =T14/200 -> 1 | T14: 200 | U14: =V14/200 -> 1 | V14: 200 | Y14: =D14+F14+H14+J14+L14+N14+P14+R14+T14+V14 -> 31800 | Z14: =Y14*3 -> 95400 | AA14: {=Y14/Totalinfracash2024} -> 0.073645206
A15: 12 | B15: Khucwayo | C15: =D15/200 -> 1 | D15: 200 | E15: =F15/200 -> 2 | F15: 400 | G15: =H15/200 -> 1 | H15: 200 | I15: =J15/200 -> 1 | J15: 200 | K15: =L15/200 -> 1 | L15: 200 | M15: =N15/200 -> 1 | N15: 200 | O15: =P15/200 -> 1 | P15: 200 | Q15: =R15/200 -> 2 | R15: 400 | S15: =T15/200 -> 5 | T15: 1000 | U15: =V15/200 -> 1 | V15: 200 | Y15: =D15+F15+H15+J15+L15+N15+P15+R15+T15+V15 -> 3200 | Z15: =Y15*3 -> 9600 | AA15: {=Y15/Totalinfracash2024} -> 0.0074108384
A16: 13 | B16: Kwibisa | C16: =D16/200 -> 25 | D16: 5000 | E16: =F16/200 -> 1 | F16: 200 | G16: =H16/200 -> 1 | H16: 200 | I16: =J16/200 -> 1 | J16: 200 | K16: =L16/200 -> 1 | L16: 200 | M16: =N16/200 -> 1 | N16: 200 | O16: =P16/200 -> 5 | P16: 1000 | Q16: =R16/200 -> 1 | R16: 200 | S16: =T16/200 -> 1 | T16: 200 | U16: =V16/200 -> 1 | V16: 200 | Y16: =D16+F16+H16+J16+L16+N16+P16+R16+T16+V16 -> 7600 | Z16: =Y16*3 -> 22800 | AA16: {=Y16/Totalinfracash2024} -> 0.017600741
A17: 14 | B17: Michael | C17: =D17/200 -> 25 | D17: 5000 | E17: =F17/200 -> 25 | F17: 5000 | G17: =H17/200 -> 25 | H17: 5000 | I17: =J17/200 -> 25 | J17: 5000 | K17: =L17/200 -> 50 | L17: 10000 | M17: =N17/200 -> 25 | N17: 5000 | O17: =P17/200 -> 25 | P17: 5000 | Q17: =R17/200 -> 25 | R17: 5000 | S17: =T17/200 -> 18 | T17: 3600 | U17: =V17/200 -> 1 | V17: 200 | Y17: =D17+F17+H17+J17+L17+N17+P17+R17+T17+V17 -> 48800 | Z17: =Y17*3 -> 146400 | AA17: {=Y17/Totalinfracash2024} -> 0.11301528
... A25: 22 | B25: Schuller | C25: =D25/200 -> 25 | D25: 5000 | E25: =F25/200 -> 50 | F25: 10000 | G25: =H25/200 -> 5 | H25: 1000 | I25: =J25/200 -> 25 | J25: 5000 | K25: =L25/200 -> 25 | L25: 5000 | M25: =N25/200 -> 5 | N25: 1000 | O25: =P25/200 -> 5 | P25: 1000 | Q25: =R25/200 -> 10 | R25: 2000 | S25: =T25/200 -> 10 | T25: 2000 | U25: =V25/200 -> 1 | V25: 200 | Y25: =D25+F25+H25+J25+L25+N25+P25+R25+T25+V25 -> 32200 | Z25: =Y25*3 -> 96600 | AA25: {=Y25/Totalinfracash2024} -> 0.074571561
A26: 23 | B26: Shubart | C26: =D26/200 -> 25 | D26: 5000 | E26: =F26/200 -> 5 | F26: 1000 | G26: =H26/200 -> 5 | H26: 1000 | I26: =J26/200 -> 10 | J26: 2000 | K26: =L26/200 -> 5 | L26: 1000 | M26: =N26/200 -> 1 | N26: 200 | O26: =P26/200 -> 1 | P26: 200 | Q26: =R26/200 -> 0 | S26: =T26/200 -> 1 | T26: 200 | U26: =V26/200 -> 2 | V26: 400 | Y26: =D26+F26+H26+J26+L26+N26+P26+R26+T26+V26 -> 11000 | Z26: =Y26*3 -> 33000 | AA26: {=Y26/Totalinfracash2024} -> 0.025474757
A27: 24 | B27: Solomon | C27: =D27/200 -> 10 | D27: 2000 | E27: =F27/200 -> 20 | F27: 4000 | G27: =H27/200 -> 5 | H27: 1000 | I27: =J27/200 -> 1 | J27: 200 | K27: =L27/200 -> 1 | L27: 200 | M27: =N27/200 -> 2 | N27: 400 | O27: =P27/200 -> 3 | P27: 600 | Q27: =R27/200 -> 3 | R27: 600 | S27: =T27/200 -> 1 | T27: 200 | U27: =V27/200 -> 1 | V27: 200 | Y27: =D27+F27+H27+J27+L27+N27+P27+R27+T27+V27 -> 9400 | Z27: =Y27*3 -> 28200 | AA27: {=Y27/Totalinfracash2024} -> 0.021769338
A28: 25 | B28: Tumelo | C28: =D28/200 -> 1 | D28: 200 | E28: =F28/200 -> 0 | I28: =J28/200 -> 0 | K28: =L28/200 -> 0 | M28: =N28/200 -> 0 | O28: =P28/200 -> 0 | Q28: =R28/200 -> 0 | S28: =T28/200 -> 0 | U28: =V28/200 -> 0 | Y28: =D28+F28+H28+J28+L28+N28+P28+R28+T28+V28 -> 200 | Z28: =Y28*3 -> 600 | AA28: {=Y28/Totalinfracash2024} -> 0.0004631774
A29: 26 | B29: INSURANCE | C29: =D29/200 -> 23 | D29: 4600 | E29: =F29/200 -> 23 | F29: 4600 | H29: 4600 | I29: =J29/200 -> 23 | J29: 4600 | K29: =L29/200 -> 24 | L29: 4800 | M29: =N29/200 -> 23 | N29: 4600 | O29: =P29/200 -> 0 | Q29: =R29/200 -> 0 | S29: =T29/200 -> 0 | U29: =V29/200 -> 0 | Y29: =D29+F29+H29+J29+L29+N29+P29+R29+T29+V29 -> 27800 | Z29: =Y29*3 -> 83400
B30: TOTAL | C30: =SUM(C4:C29) -> 238 | D30: =SUM(D4:D29) -> 47600 | E30: =SUM(E4:E28) -> 279 | F30: =SUM(F4:F29) -> 60400 | G30: =SUM(G4:G28) -> 168 | H30: =SUM(H4:H29) -> 38200 | I30: =J30/200 -> 259 | J30: =SUM(J4:J29) -> 51800 | K30: =SUM(K4:K27) -> 729 | L30: =SUM(L4:L29) -> 150600 | M30: =SUM(M4:M28) -> 85 | N30: =SUM(N4:N29) -> 21600 | O30: =SUM(O4:O27) -> 166 | P30: =SUM(P4:P28) -> 33200 | Q30: =SUM(Q4:Q27) -> 151 | R30: =SUM(R4:R28) -> 30200 | S30: =SUM(S4:S28) -> 80 | T30: =SUM(T4:T28) -> 16000 | U30: =SUM(U4:U27) -> 50 | V30: =SUM(V4:V28) -> 10000 | X30: =SUM(X4:X27) -> 0 | Y30: =SUM(Y4:Y29) -> 459600 | AA30: =SUM(AA4:AA28) -> 1

Sheet final
B1: MEETING | H1: =34916.9337259358-8200 -> 26716.934 | J1: =111201.71-1700 -> 109501.71 | K1: =22545-1200 -> 21345 | L1: =41125.2272078665-1700 -> 39425.227 | M1: =24813.2726452535-1200 -> 23613.273 | N1: =74495.0870519596-1200 -> 73295.087 | O1: =35832.9524290763-1200 -> 34632.952
A2: No | B2: FULL NAMES | C2: SHARES OUT | D2: TOTAL | E2: SHARE-LOAN | F2: PEOPLE GET SHAREOUT | G2: REDLIST | H2: Excess | I2: Total SHARE+ EXCESS | J2: Nyanyiwe | K2: Mwenya | L2: Evans | M2: Karen Mwinga | N2: Pamela | O2: Kwibisa
A3: 1 | B3: Abigail Mundia | C3: =Shareout!C85 -> 41458.426 | D3: ='New Repayment Schedule'!DC6 -> 75216.482 | E3: =C3-D3 -> -33758.056 | H3: =Excessinfracash2023*Shares!AA4 -> 1695.3311 | I3: =F3+H3 -> 1695.3311 | J3: =I3 -> 1695.3311 | P3: =SUM(J3:O3)-I3 -> 0
A4: 2 | B4: Andrew | C4: =Shareout!K85 -> 8404.5446 | D4: ='New Repayment Schedule'!DC8 -> 1141.2562 | E4: =C4-D4 -> 7263.2884 | F4: =E4 -> 7263.2884 | H4: =Excessinfracash2023*Shares!AA6 -> 358.86571 | I4: =F4+H4 -> 7622.1541 | K4: =I4 -> 7622.1541 | P4: =SUM(J4:O4)-I4 -> 0
A5: 3 | B5: Arthur | C5: =Shareout!O85 -> 8039.3018 | D5: ='New Repayment Schedule'!DC9 -> 5351.8097 | E5: =C5-D5 -> 2687.4921 | H5: =Excessinfracash2023*Shares!AA7 -> 383.61507 | I5: =F5+H5 -> 383.61507 | O5: =I5 -> 383.61507 | P5: =SUM(J5:O5)-I5 -> 0
A6: 4 | B6: Benson | C6: =Shareout!#REF! -> #REF! | D6: ='New Repayment Schedule'!DC10 -> 10566.477 | E6: =C6-D6 -> #REF! | H6: =Excessinfracash2023*Shares!AA8 -> 643.48335 | I6: =F6+H6 -> 643.48335 | N6: =I6 -> 643.48335 | P6: =SUM(J6:O6)-I6 -> 0
A7: 5 | B7: Davies | C7: =Shareout!#REF! -> #REF! | D7: ='New Repayment Schedule'!DC11 -> -4.1813014 | E7: =C7-D7 -> #REF! | G7: =E7*-1 -> #REF! | H7: =Excessinfracash2023*Shares!AA9 -> 136.12148 | I7: =F7+H7 -> 136.12148 | J7: =I7 -> 136.12148 | P7: =SUM(J7:O7)-I7 -> 0
A8: 7 | B8: Evans | C8: =Shareout!S85 -> 16150.911 | D8: ='New Repayment Schedule'!DC12 -> 12127.5 | E8: =C8-D8 -> 4023.4106 | H8: =Excessinfracash2023*Shares!AA10 -> 829.10355 | I8: =F8+H8 -> 829.10355 | J8: 210.21719 | K8: 219.87296 | L8: =I8 -> 829.10355 | M8: 215.65521 | N8: 21.688566 | O8: 117.26163 | P8: =SUM(J8:O8)-I8 -> 784.69557
A9: 8 | B9: Gilbert | C9: =Shareout!#REF! -> #REF! | D9: ='New Repayment Schedule'!DC13 -> 13494.111 | E9: =C9-D9 -> #REF! | H9: =Excessinfracash2023*Shares!AA11 -> 457.86315 | I9: =F9+H9 -> 457.86315 | L9: =I9 -> 457.86315 | P9: =SUM(J9:O9)-I9 -> 0
A10: 9 | B10: Jesper Chola | C10: =Shareout!X85 -> 3009.6864 | D10: ='New Repayment Schedule'!DC14 -> 4847.7509 | E10: =C10-D10 -> -1838.0646 | F10: =E10 -> -1838.0646 | H10: =Excessinfracash2023*Shares!AA12 -> 321.74168 | I10: =F10+H10 -> -1516.3229 | J10: =I10 -> -1516.3229 | P10: =SUM(J10:O10)-I10 -> 0
A11: 10 | B11: Joshua | C11: =Shareout!AB85 -> 16456.086 | D11: ='New Repayment Schedule'!DC15 -> 10586.081 | E11: =C11-D11 -> 5870.0057 | F11: =E11 -> 5870.0057 | H11: =Excessinfracash2023*Shares!AA13 -> 408.36443 | I11: =F11+H11 -> 6278.3702 | K11: =I11 -> 6278.3702 | P11: =SUM(J11:O11)-I11 -> 0
A12: 11 | B12: Kampamba | C12: =Shareout!AF85 -> 10322.876 | D12: ='New Repayment Schedule'!DC16 -> 83718.175 | E12: =C12-D12 -> -73395.3 | H12: =Excessinfracash2023*Shares!AA14 -> 1967.5741 | I12: =F12+H12 -> 1967.5741 | J12: =I12 -> 1967.5741 | P12: =SUM(J12:O12)-I12 -> 0
A13: 12 | B13: Karen Mwinga | C13: =Shareout!AJ85 -> 7244.343 | D13: ='New Repayment Schedule'!DC17 -> -416.72233 | E13: =C13-D13 -> 7661.0653 | F13: =E13 -> 7661.0653 | H13: =Excessinfracash2023*Shares!AA15 -> 197.99488 | I13: =F13+H13 -> 7859.0602 | M13: =I13 -> 7859.0602 | P13: =SUM(J13:O13)-I13 -> 0
A14: 13 | B14: Karen S | C14: =Shareout!#REF! -> #REF! | D14: ='New Repayment Schedule'!DC18 -> 11425.696 | E14: =C14-D14 -> #REF! | G14: =E14*-1 -> #REF! | H14: =Excessinfracash2023*Shares!AA16 -> 470.23783 | I14: =F14+H14 -> 470.23783 | N14: =I14 -> 470.23783 | P14: =SUM(J14:O14)-I14 -> 0
A15: 14 | B15: Kebby | C15: =Shareout!#REF! -> #REF! | D15: ='New Repayment Schedule'!DC19 -> -121.55418 | E15: =C15-D15 -> #REF! | F15: =E15 -> #REF! | H15: =Excessinfracash2023*Shares!AA17 -> 3019.4219 | I15: =F15+H15 -> #REF! | N15: =I15 -> #REF! | P15: =SUM(J15:O15)-I15 -> #REF!
A16: 15 | B16: Keji | C16: =Shareout!AN85 -> 9548.0203 | D16: ='New Repayment Schedule'!DC21 -> 1003.2706 | E16: =C16-D16 -> 8544.7497 | F16: =E16 -> 8544.7497 | H16: =Excessinfracash2023*Shares!AA19 -> 1559.2097 | I16: =F16+H16 -> 10103.959 | O16: =I16 -> 10103.959 | P16: =SUM(J16:O16)-I16 -> 0
A17: 16 | B17: Khucwayo | C17: =Shareout!AR85 -> 4258.7266 | D17: ='New Repayment Schedule'!DC22 -> -0.00030205479 | E17: =C17-D17 -> 4258.7269 | F17: =E17 -> 4258.7269 | H17: =Excessinfracash2023*Shares!AA20 -> 1559.2097 | I17: =F17+H17 -> 5817.9365 | N17: =I17 -> 5817.9365 | P17: =SUM(J17:O17)-I17 -> 0
A18: 17 | B18: Kombe | C18: =Shareout!AV85 -> 42633.685 | D18: ='New Repayment Schedule'!DC23 -> 6491.2086 | E18: =C18-D18 -> 36142.477 | H18: =Excessinfracash2023*Shares!AA21 -> 1670.5818 | I18: =F18+H18 -> 1670.5818 | N18: =I18 -> 1670.5818 | P18: =SUM(J18:O18)-I18 -> 0
A19: 18 | B19: Kwibisa | C19: =Shareout!AZ85 -> 11976.859 | D19: ='New Repayment Schedule'!DC25 -> 2044.6104 | E19: =C19-D19 -> 9932.2489 | H19: =Excessinfracash2023*Shares!AA23 -> 1546.835 | I19: =F19+H19 -> 1546.835 | O19: =I19 -> 1546.835 | P19: =SUM(J19:O19)-I19 -> 0
A20: 19 | B20: Michael | C20: =Shareout!BD85 -> 69300.958 | D20: ='New Repayment Schedule'!DC26 -> 19210.884 | E20: =C20-D20 -> 50090.074 | F20: =E20 -> 50090.074 | H20: =Excessinfracash2023*Shares!AA24 -> 878.60227 | I20: =F20+H20 -> 50968.676 | O20: =I20 -> 50968.676 | P20: =SUM(J20:O20)-I20 -> 0
A21: 20 | B21: Mike | C21: =Shareout!#REF! -> #REF! | D21: ='New Repayment Schedule'!DC27 -> 29574.557 | E21: =C21-D21 -> #REF! | H21: =Excessinfracash2023*Shares!AA25 -> 1992.3235 | I21: =F21+H21 -> 1992.3235 | O21: =I21 -> 1992.3235 | P21: =SUM(J21:O21)-I21 -> 0
A22: 21 | B22: Millie | C22: =Shareout!BH85 -> 5100.8299 | D22: ='New Repayment Schedule'!DC28 -> 16577.725 | E22: =C22-D22 -> -11476.895 | F22: =E22 -> -11476.895 | H22: =Excessinfracash2023*Shares!AA26 -> 680.60739 | I22: =F22+H22 -> -10796.288 | N22: =I22 -> -10796.288 | P22: =SUM(J22:O22)-I22 -> 0
A23: 22 | B23: Mofya | C23: =Shareout!#REF! -> #REF! | D23: ='New Repayment Schedule'!DC29 -> 0 | E23: =C23-D23 -> #REF! | F23: =E23 -> #REF! | H23: =Excessinfracash2023*Shares!AA27 -> 581.60995 | I23: =F23+H23 -> #REF! | J23: =I23 -> #REF! | P23: =SUM(J23:O23)-I23 -> #REF!
A24: 23 | B24: Mukuma | C24: =Shareout!BL85 -> 35608.031 | D24: ='New Repayment Schedule'!#REF! -> #REF! | E24: =C24-D24 -> #REF! | F24: =E24 -> #REF! | H24: =Excessinfracash2023*Shares!#REF! -> #REF! | I24: =F24+H24 -> #REF! | N24: =I24 -> #REF! | P24: =SUM(J24:O24)-I24 -> #REF!
A25: 24 | B25: Mumba | C25: =Shareout!BP85 -> 35718.613 | D25: ='New Repayment Schedule'!DC30 -> 0 | E25: =C25-D25 -> 35718.613 | F25: =E25 -> 35718.613 | H25: =Excessinfracash2023*Shares!AA28 -> 12.37468 | I25: =F25+H25 -> 35730.987 | O25: =I25 -> 35730.987 | P25: =SUM(J25:O25)-I25 -> 0
A26: 25 | B26: Mwenya | C26: =Shareout!#REF! -> #REF! | D26: ='New Repayment Schedule'!#REF! -> #REF! | E26: =C26-D26 -> #REF! | F26: =E26 -> #REF! | H26: =Excessinfracash2023*Shares!#REF! -> #REF! | I26: =F26+H26 -> #REF! | K26: =I26 -> #REF! | P26: =SUM(J26:O26)-I26 -> #REF!
A27: 26 | B27: Nancy Mwila | C27: =Shareout!#REF! -> #REF! | D27: ='New Repayment Schedule'!#REF! -> #REF! | E27: =C27-D27 -> #REF! | G27: =E27*-1 -> #REF! | H27: =Excessinfracash2023*Shares!#REF! -> #REF! | I27: =F27+H27 -> #REF! | J27: =I27 -> #REF! | P27: =SUM(J27:O27)-I27 -> #REF!
A28: 27 | B28: Nyanyiwe | C28: =Shareout!CB85 -> 39135.116 | D28: ='New Repayment Schedule'!#REF! -> #REF! | E28: =C28-D28 -> #REF! | F28: =E28 -> #REF! | H28: =Excessinfracash2023*Shares!#REF! -> #REF! | I28: =F28+H28 -> #REF! | J28: =I28 -> #REF! | P28: =SUM(J28:O28)-I28 -> #REF!
A29: 28 | B29: Pamela | C29: =Shareout!CF85 -> 20082.571 | D29: ='New Repayment Schedule'!#REF! -> #REF! | E29: =C29-D29 -> #REF! | F29: =E29 -> #REF! | H29: =Excessinfracash2023*Shares!#REF! -> #REF! | I29: =F29+H29 -> #REF! | N29: =I29 -> #REF! | P29: =SUM(J29:O29)-I29 -> #REF!
A30: 29 | B30: Paul | C30: =Shareout!#REF! -> #REF! | D30: ='New Repayment Schedule'!#REF! -> #REF! | E30: =C30-D30 -> #REF! | H30: =Excessinfracash2023*Shares!#REF! -> #REF! | I30: =F30+H30 -> #REF! | L30: =I30 -> #REF! | P30: =SUM(J30:O30)-I30 -> #REF!
A31: 30 | B31: Schuller | C31: =Shareout!CJ85 -> 48288.145 | D31: ='New Repayment Schedule'!#REF! -> #REF! | E31: =C31-D31 -> #REF! | F31: =E31 -> #REF! | H31: =Excessinfracash2023*Shares!#REF! -> #REF! | I31: =F31+H31 -> #REF! | N31: =I31 -> #REF! | P31: =SUM(J31:O31)-I31 -> #REF!
A32: 31 | B32: Shubart | C32: =Shareout!CN85 -> 17250.526 | D32: ='New Repayment Schedule'!#REF! -> #REF! | E32: =C32-D32 -> #REF! | F32: =E32 -> #REF! | H32: =Excessinfracash2023*Shares!#REF! -> #REF! | I32: =F32+H32 -> #REF! | N32: =I32 -> #REF! | P32: =SUM(J32:O32)-I32 -> #REF!
A33: 32 | B33: Solomon | C33: =Shareout!CR85 -> 14514.645 | D33: ='New Repayment Schedule'!#REF! -> #REF! | E33: =C33-D33 -> #REF! | F33: =E33 -> #REF! | H33: =Excessinfracash2023*Shares!#REF! -> #REF! | I33: =F33+H33 -> #REF! | M33: =I33 -> #REF! | P33: =SUM(J33:O33)-I33 -> #REF!
A34: 33 | B34: Tumelo | C34: =Shareout!CV85 -> 341.29221 | D34: ='New Repayment Schedule'!#REF! -> #REF! | E34: =C34-D34 -> #REF! | F34: =E34 -> #REF! | H34: =Excessinfracash2023*Shares!#REF! -> #REF! | I34: =F34+H34 -> #REF! | M34: =I34 -> #REF! | P34: =SUM(J34:O34)-I34 -> #REF!
A35: 34 | B35: Zeko | C35: =Shareout!#REF! -> #REF! | D35: ='New Repayment Schedule'!#REF! -> #REF! | E35: =C35-D35 -> #REF! | F35: =E35 -> #REF! | H35: =Excessinfracash2023*Shares!#REF! -> #REF! | I35: =F35+H35 -> #REF! | J35: 6646.36 | L35: 38000 | P35: =SUM(J35:O35)-I35 -> #REF!
A36: 35 | B36: INSURANCE | C36: =Shareout!CZ85 -> 42115.686 | E36: =C36-D36 -> 42115.686 | F36: =E36 -> 42115.686 | P36: =SUM(J36:O36)-I36 -> 0
B37: TOTAL | C37: =SUM(C3:C36) -> #REF! | D37: =SUM(D3:D36) -> #REF! | E37: =SUM(E3:E36) -> #REF! | F37: =SUM(F3:F35) -> #REF! | G37: =SUM(G3:G36) -> #REF! | H37: =SUM(H3:H36) -> #REF! | I37: =SUM(I3:I36) -> #REF! | J37: =SUM(J3:J35) -> #REF! | K37: =SUM(K3:K35) -> #REF! | L37: =SUM(L3:L35) -> #REF! | M37: =SUM(M3:M35) -> #REF! | N37: =SUM(N3:N35) -> #REF! | O37: =SUM(O3:O35) -> 100843.66 | P37: =SUM(J37:O37) -> #REF!
F38: =F37-F36 -> #REF! | J38: =J1-J37 -> #REF! | K38: =K1-K37 -> #REF! | L38: =L1-L37 -> #REF! | M38: =M1-M37 -> #REF! | N38: =N1-N37 -> #REF! | O38: =O1-O37 -> -66210.705 | P38: =P1-P37 -> #REF!
H40: =C46-8200 -> #REF!
B42: PEOPLE GETTING SHAREOUT | C42: =F37-F36 -> #REF!
B43: REDLIST | C43: =G37 -> #REF! | E43: =C44-C42 -> #REF!
B44: ADMINS | C44: =Admins!#REF! -> #REF! | D44: =C44-C42 -> #REF! | E44: =D44+C43 -> #REF!
B45: REDLIST + ADMINS | C45: =C43+C44 -> #REF!
B46: Excess | C46: =C45-C42-F36 -> #REF! | D46: =C46+3605 -> #REF! | E46: 34917.72 | F46: =D46-E46 -> #REF!

Sheet Calculations
B4: MAY TRANSACTIONS
B5: Name | C5: Shares | D5: LR1 | E5: FLR | F5: Insurance | G5: LA | H5: Total | L5: Recipient > | M5: Nyanyiwe | N5: Karen Mwinga | O5: Kwibisa | P5: Pamela | Q5: Evans | R5: Total
A6: 1 | B6: Abigail Mundia | D6: 24000 | G6: =D6+E6 -> 24000 | H6: =SUM(C6:F6) -> 24000 | J6: ='New Repayment Schedule'!BV6 -> 105207.14 | K6: =Shares!Z156-J6 -> -105207.14 | M6: =M33 -> 52377.19 | N6: =N33 -> 0 | O6: =O33 -> 3345 | P6: =P33 -> 146573.59 | Q6: =Q33 -> 61138.561 | R6: =SUM(M6:Q6) -> 263434.34 | T6: =H30-R6 -> -9372.5092
A7: 2 | B7: Abel Kunda | D7: 15000 | E7: 806.44 | G7: =D7+E7 -> 15806.44 | H7: =SUM(C7:F7) -> 15806.44 | J7: ='New Repayment Schedule'!BV7 -> 15427.5 | K7: =Shares!Z157-J7 -> -15427.5 | R7: =SUM(M7:Q7) -> 0
A8: 3 | B8: Andrew | D8: 9560 | G8: =D8+E8 -> 9560 | H8: =SUM(C8:F8) -> 9560 | J8: ='New Repayment Schedule'!BV8 -> 22827.82 | K8: =Shares!Z158-J8 -> -22827.82 | L8: Sender | R8: =SUM(M8:Q8) -> 0 | S8: =H6-R8 -> 24000
A9: 4 | B9: Arthur | D9: 5000 | E9: 102.04 | G9: =D9+E9 -> 5102.04 | H9: =SUM(C9:F9) -> 5102.04 | J9: ='New Repayment Schedule'!BV9 -> 18700 | K9: =Shares!Z161-J9 -> -18700 | L9: Abigail Mundia | P9: 24000 | R9: =SUM(M9:Q9) -> 24000 | S9: =H6-R9 -> 0
A10: 5 | B10: Evans | D10: 46500 | G10: =D10+E10 -> 46500 | H10: =SUM(C10:F10) -> 46500 | J10: ='New Repayment Schedule'!BV10 -> 49431.042 | K10: =Shares!Z163-J10 -> -49431.042 | L10: Abel Kunda | P10: 15806.44 | R10: =SUM(M10:Q10) -> 15806.44 | S10: =H7-R10 -> 0 | V10: Nyanyiwe | W10: =O6 -> 3345 | X10: 18600 | Y10: 7400 | Z10: 6000 | AB10: 1200 | AC10: 200 | AD10: =W10-SUM(X10:AA10) -> -28655
A11: 6 | B11: Jesper | G11: =D11+E11 -> 0 | H11: =SUM(C11:F11) -> 0 | J11: ='New Repayment Schedule'!BV11 -> 0 | K11: =Shares!Z164-J11 -> 0 | L11: Andrew | M11: 9560 | R11: =SUM(M11:Q11) -> 9560 | S11: =H8-R11 -> 0 | V11: Kwibisa | W11: 22600 | Y11: 22600 | AD11: =W11-SUM(X11:AA11) -> 0
A12: 7 | B12: Joshua | D12: 1100 | G12: =D12+E12 -> 1100 | H12: =SUM(C12:F12) -> 1100 | J12: ='New Repayment Schedule'!BV12 -> 0 | K12: =Shares!Z165-J12 -> 0 | L12: Arthur | P12: 5103 | R12: =SUM(M12:Q12) -> 5103 | S12: =H9-R12 -> -0.96 | V12: Evans | W12: =Q6 -> 61138.561 | AA12: 2600 | AD12: =W12-SUM(X12:AA12) -> 58538.561
A13: 8 | B13: Kampamba | D13: 2500 | E13: 121.79 | G13: =D13+E13 -> 2621.79 | H13: =SUM(C13:F13) -> 2621.79 | J13: ='New Repayment Schedule'!BV13 -> 17845.404 | K13: =Shares!Z166-J13 -> -17845.404 | L13: Evans | Q13: 54482.281 | R13: =SUM(M13:Q13) -> 54482.281 | S13: =H10-R13 -> -7982.2809 | V13: Mwenya | W13: =#REF! -> #REF! | AA13: 7400 | AC13: 2300 | AD13: =W13-SUM(X13:AA13) -> #REF!
A14: 9 | B14: Karen Mwinga | D14: 44750 | G14: =D14+E14 -> 44750 | H14: =SUM(C14:F14) -> 44750 | J14: ='New Repayment Schedule'!BV14 -> 58024.011 | K14: =Shares!Z169-J14 -> -58024.011 | L14: Jesper | P14: 40 | R14: =SUM(M14:Q14) -> 40 | S14: =H11-R14 -> -40 | W14: =SUM(W10:W13) -> #REF! | X14: =SUM(X10:X13) -> 18600 | Y14: =SUM(Y10:Y13) -> 30000 | Z14: =SUM(Z10:Z13) -> 6000 | AA14: =SUM(AA10:AA13) -> 10000 | AB14: =SUM(AB10:AB13) -> 1200 | AC14: =SUM(AC10:AC13) -> 2500 | AD14: =W14-SUM(X14:AA14) -> #REF!
A15: 10 | B15: Keji | D15: 688.12 | E15: 108.62 | G15: =D15+E15 -> 796.74 | H15: =SUM(C15:F15) -> 796.74 | J15: ='New Repayment Schedule'!BV15 -> 16800.004 | L15: Joshua | Q15: 1100 | R15: =SUM(M15:Q15) -> 1100 | S15: =H12-R15 -> 0 | X15: =X14-48000 -> -29400 | Y15: =Y14-30000 -> 0 | Z15: =Z14-6000 -> 0 | AA15: =AA14-10000 -> 0 | AB15: =AB14-1200 -> 0 | AC15: =AC14-2500 -> 0
A16: 11 | B16: Kombe | D16: 40000 | G16: =D16+E16 -> 40000 | H16: =SUM(C16:F16) -> 40000 | J16: ='New Repayment Schedule'!BV16 -> 115443.53 | L16: Kampamba | P16: 2622 | R16: =SUM(M16:Q16) -> 2622 | S16: =H13-R16 -> -0.21
A17: 12 | B17: Khucwayo | G17: =D17+E17 -> 0 | H17: =SUM(C17:F17) -> 0 | J17: ='New Repayment Schedule'!BV17 -> -9.6551438 | K17: =Shares!Z173-J17 -> 9.6551438 | L17: Karen Mwinga | P17: 44750 | R17: =SUM(M17:Q17) -> 44750 | S17: =H14-R17 -> 0
A18: 13 | B18: Kwibisa | D18: 1500 | E18: 125 | G18: =D18+E18 -> 1625 | H18: =SUM(C18:F18) -> 1625 | J18: ='New Repayment Schedule'!BV18 -> 16117.562 | K18: =Shares!Z174-J18 -> -16117.562 | L18: Keji | M18: 796.74 | R18: =SUM(M18:Q18) -> 796.74 | S18: =H15-R18 -> 0
A19: 14 | B19: Michael | E19: 803.15 | G19: =D19+E19 -> 803.15 | H19: =SUM(C19:F19) -> 803.15 | J19: ='New Repayment Schedule'!BV19 -> 6300 | K19: =Shares!Z176-J19 -> -6300 | L19: Kombe | P19: 40000 | R19: =SUM(M19:Q19) -> 40000 | S19: =H16-R19 -> 0
A20: 15 | B20: Millie | D20: 2048 | E20: 60 | G20: =D20+E20 -> 2108 | H20: =SUM(C20:F20) -> 2108 | J20: ='New Repayment Schedule'!BV20 -> 10999.449 | K20: =Shares!Z177-J20 -> -10999.449 | L20: Khucwayo | R20: =SUM(M20:Q20) -> 0 | S20: =H17-R20 -> 0
A21: 16 | B21: Mukuma | D21: 2500 | G21: =D21+E21 -> 2500 | H21: =SUM(C21:F21) -> 2500 | J21: ='New Repayment Schedule'!BV21 -> 7402.5 | L21: Kwibisa | O21: 1625 | R21: =SUM(M21:Q21) -> 1625 | S21: =H18-R21 -> 0
A22: 17 | B22: Mumba | E22: 414.74 | G22: =D22+E22 -> 414.74 | H22: =SUM(C22:F22) -> 414.74 | J22: ='New Repayment Schedule'!BV22 -> 0 | K22: =Shares!Z180-J22 -> 0 | L22: Michael | P22: 803.15 | R22: =SUM(M22:Q22) -> 803.15 | S22: =H19-R22 -> 0
A23: 18 | B23: Mumbi | D23: 3000 | G23: =D23+E23 -> 3000 | H23: =SUM(C23:F23) -> 3000 | J23: ='New Repayment Schedule'!BV23 -> 11767.894 | K23: =Shares!Z181-J23 -> -11767.894 | L23: Millie | M23: 2108 | R23: =SUM(M23:Q23) -> 2108 | S23: =H20-R23 -> 0
A24: 19 | B24: Mwenya | D24: 5000 | E24: 556.28 | G24: =D24+E24 -> 5556.28 | H24: =SUM(C24:F24) -> 5556.28 | J24: ='New Repayment Schedule'!BV24 -> 0 | K24: =Shares!Z182-J24 -> 0 | L24: Mukuma | M24: 2500 | R24: =SUM(M24:Q24) -> 2500 | S24: =H21-R24 -> 0
A25: 20 | B25: Nyanyiwe | D25: 37000 | E25: 412.45 | G25: =D25+E25 -> 37412.45 | H25: =SUM(C25:F25) -> 37412.45 | J25: ='New Repayment Schedule'!BV25 -> 38195.486 | K25: =Shares!Z184-J25 -> -38195.486 | L25: Mumba | P25: 414.74 | R25: =SUM(M25:Q25) -> 414.74 | S25: =H22-R25 -> 0
A26: 21 | B26: Pamela | D26: 7155.2527 | G26: =D26+E26 -> 7155.2527 | H26: =SUM(C26:F26) -> 7155.2527 | J26: ='New Repayment Schedule'!BV26 -> 28163.625 | K26: =Shares!#REF!-J26 -> #REF! | L26: Mumbi | P26: 3000 | R26: =SUM(M26:Q26) -> 3000 | S26: =H23-R26 -> 0
A27: 22 | B27: Schuller | D27: 1000 | E27: 529.95 | G27: =D27+E27 -> 1529.95 | H27: =SUM(C27:F27) -> 1529.95 | J27: ='New Repayment Schedule'!BV27 -> 0 | K27: =Shares!#REF!-J27 -> #REF! | L27: Mwenya | Q27: 5556.28 | R27: =SUM(M27:Q27) -> 5556.28 | S27: =H24-R27 -> 0
A28: 23 | B28: Shubart | G28: =D28+E28 -> 0 | H28: =SUM(C28:F28) -> 0 | J28: ='New Repayment Schedule'!BV28 -> 15226.71 | K28: =Shares!#REF!-J28 -> #REF! | L28: Nyanyiwe | M28: 37412.45 | R28: =SUM(M28:Q28) -> 37412.45 | S28: =H25-R28 -> 0
A29: 24 | B29: Solomon | D29: 1720 | G29: =D29+E29 -> 1720 | H29: =SUM(C29:F29) -> 1720 | J29: ='New Repayment Schedule'!BV29 -> 0 | L29: Pamela | P29: 8504.261 | R29: =SUM(M29:Q29) -> 8504.261 | S29: =H26-R29 -> -1349.0083
B30: TOTAL LOAN | C30: =SUM(C6:C29) -> 0 | D30: =SUM(D6:D29) -> 250021.37 | E30: =SUM(E6:E29) -> 4040.46 | F30: =SUM(F6:F29) -> 0 | G30: =SUM(G6:G29) -> 254061.83 | H30: =SUM(C30:F30) -> 254061.83 | L30: Schuller | P30: 1530 | R30: =SUM(M30:Q30) -> 1530 | S30: =H27-R30 -> -0.05
H31: =H30-G30 -> 0 | J31: 57 | L31: Shubart | R31: =SUM(M31:Q31) -> 0 | S31: =H28-R31 -> 0
D32: =H31 -> 0 | L32: Solomon | O32: 1720 | R32: =SUM(M32:Q32) -> 1720 | S32: =H29-R32 -> 0
L33: TOTAL LOAN | M33: =SUM(M9:M32) -> 52377.19 | N33: =SUM(N9:N32) -> 0 | O33: =SUM(O9:O32) -> 3345 | P33: =SUM(P9:P32) -> 146573.59 | Q33: =SUM(Q9:Q32) -> 61138.561 | R33: =SUM(R9:R32) -> 263434.34 | S33: =H30-R33 -> -9372.5092
B34: Name | C34: FL | D34: FL Interest | E34: Total | M34: =M6-M33 -> 0 | N34: =N6-N33 -> 0 | O34: =O6-O33 -> 0 | P34: =P6-P33 -> 0 | Q34: =Q6-Q33 -> 0
B35: Abigail Mundia | C35: =FLAUGUST2024*G35 -> 0 | D35: =C35*0.1 -> 0 | E35: =C35+D35 -> 0 | F35: =Shares!Y4 -> 27400 | G35: =F35/F59 -> 0.06702544
B36: Abel Kunda | C36: =FLAUGUST2024*G36 -> 0 | D36: =C36*0.1 -> 0 | E36: =C36+D36 -> 0 | F36: =Shares!Y5 -> 49000 | G36: =F36/F59 -> 0.11986301
B37: Andrew | C37: =FLAUGUST2024*G37 -> 0 | D37: =C37*0.1 -> 0 | E37: =C37+D37 -> 0 | F37: =Shares!Y6 -> 5800 | G37: =F37/F59 -> 0.014187867
B38: Arthur | C38: =FLAUGUST2024*G38 -> 0 | D38: =C38*0.1 -> 0 | E38: =C38+D38 -> 0 | F38: =Shares!Y7 -> 6200 | G38: =F38/F59 -> 0.015166341
B39: Evans | C39: =FLAUGUST2024*G39 -> 0 | D39: =C39*0.1 -> 0 | E39: =C39+D39 -> 0 | F39: =Shares!Y8 -> 10400 | G39: =F39/F59 -> 0.025440313
B40: Jesper | C40: =FLAUGUST2024*G40 -> 0 | D40: =C40*0.1 -> 0 | E40: =C40+D40 -> 0 | F40: =Shares!Y9 -> 2200 | G40: =F40/F59 -> 0.0053816047
B41: Joshua | C41: 11000 | D41: =C41*0.1 -> 1100 | E41: =C41+D41 -> 12100
B42: Kampamba | C42: =FLAUGUST2024*G42 -> 0 | D42: =C42*0.1 -> 0 | E42: =C42+D42 -> 0 | F42: =Shares!Y11 -> 7400 | G42: =F42/F59 -> 0.018101761
B43: Karen Mwinga | C43: =FLAUGUST2024*G43 -> 0 | D43: =C43*0.1 -> 0 | E43: =C43+D43 -> 0 | F43: =Shares!Y12 -> 5200 | G43: =F43/F59 -> 0.012720157
B44: Keji | C44: =FLAUGUST2024*G44 -> 0 | D44: =C44*0.1 -> 0 | E44: =C44+D44 -> 0 | F44: =Shares!Y13 -> 6600 | G44: =F44/F59 -> 0.016144814
B45: Kombe | C45: =FLAUGUST2024*G45 -> 0 | D45: =C45*0.1 -> 0 | E45: =C45+D45 -> 0 | F45: =Shares!Y14 -> 31800 | G45: =F45/F59 -> 0.07778865
B46: Khucwayo | C46: =FLAUGUST2024*G46 -> 0 | D46: =C46*0.1 -> 0 | E46: =C46+D46 -> 0 | F46: =Shares!Y15 -> 3200 | G46: =F46/F59 -> 0.0078277886
B47: Kwibisa | C47: =FLAUGUST2024*G47 -> 0 | D47: =C47*0.1 -> 0 | E47: =C47+D47 -> 0 | F47: =Shares!Y16 -> 7600 | G47: =F47/F59 -> 0.018590998
B48: Michael | C48: =FLAUGUST2024*G48 -> 0 | D48: =C48*0.1 -> 0 | E48: =C48+D48 -> 0 | F48: =Shares!Y17 -> 48800 | G48: =F48/F59 -> 0.11937378
B49: Millie | C49: =FLAUGUST2024*G49 -> 0 | D49: =C49*0.1 -> 0 | E49: =C49+D49 -> 0 | F49: =Shares!Y18 -> 3600 | G49: =F49/F59 -> 0.0088062622
B50: Mukuma | C50: =FLAUGUST2024*G50 -> 0 | D50: =C50*0.1 -> 0 | E50: =C50+D50 -> 0 | F50: =Shares!Y19 -> 25200 | G50: =F50/F59 -> 0.061643836
B51: Mumba | C51: =FLAUGUST2024*G51 -> 0 | D51: =C51*0.1 -> 0 | E51: =C51+D51 -> 0 | F51: =Shares!Y20 -> 25200 | G51: =F51/F59 -> 0.061643836
B52: Mumbi | C52: =FLAUGUST2024*G52 -> 0 | D52: =C52*0.1 -> 0 | E52: =C52+D52 -> 0 | F52: =Shares!Y21 -> 27000 | G52: =F52/F59 -> 0.066046967
B53: Mwenya | C53: =FLAUGUST2024*G53 -> 0 | D53: =C53*0.1 -> 0 | E53: =C53+D53 -> 0 | F53: =Shares!Y22 -> 33800 | G53: =F53/F59 -> 0.082681018
B54: Nyanyiwe | C54: =FLAUGUST2024*G54 -> 0 | D54: =C54*0.1 -> 0 | E54: =C54+D54 -> 0 | F54: =Shares!Y23 -> 25000 | G54: =F54/F59 -> 0.061154599
B55: Pamela | C55: =FLAUGUST2024*G55 -> 0 | D55: =C55*0.1 -> 0 | E55: =C55+D55 -> 0 | F55: =Shares!Y24 -> 14200 | G55: =F55/F59 -> 0.034735812
B56: Schuller | C56: =FLAUGUST2024*G56 -> 0 | D56: =C56*0.1 -> 0 | E56: =C56+D56 -> 0 | F56: =Shares!Y25 -> 32200 | G56: =F56/F59 -> 0.078767123
B57: Shubart | C57: =FLAUGUST2024*G57 -> 0 | D57: =C57*0.1 -> 0 | E57: =C57+D57 -> 0 | F57: =Shares!Y26 -> 11000 | G57: =F57/F59 -> 0.026908023
B58: Solomon | C58: 15000 | D58: =C58*0.1 -> 1500 | E58: =C58+D58 -> 16500 | G58: =F58/F59 -> 0
B59: TOTAL LOAN | C59: =SUM(C35:C58) -> 26000 | D59: =SUM(D35:D58) -> 2600 | E59: =SUM(E35:E58) -> 28600 | F59: =SUM(F35:F58) -> 408800 | G59: =SUM(G35:G58) -> 1

Sheet Admins
A1: Recipient > | B1: Nyanyiwe | C1: Karen Mwinga | D1: Kwibisa | E1: Evans
B2: 25280 | C2: 20400 | D2: 9800 | E2: =E29 -> 23100 | F2: =SUM(B2:E2) -> 78580 | I2: August | J2: September | K2: October | L2: Total
H3: Nyanyiwe | I3: =36280-11000 -> 25280 | J3: 52156.28 | L3: =SUM(I3:K3) -> 77436.28
A4: Sender | H4: Evans | I4: 23100 | J4: 61138.561 | L4: =SUM(I4:K4) -> 84238.561
A5: Abigail Mundia | E5: 17500 | H5: Karen M | L5: =SUM(I5:K5) -> 0
A6: Abel Kunda | B6: 3700 | H6: Pamela | J6: =146573.591000908+20400 -> 166973.59 | L6: =SUM(I6:K6) -> 166973.59
A7: Andrew | B7: 1580 | H7: Kwibisa | I7: 9800 | J7: 3345 | L7: =SUM(I7:K7) -> 13145
A8: Arthur | B8: 5200 | H8: Total | I8: =SUM(I3:I7) -> 58180 | J8: =SUM(J3:J7) -> 283613.43 | L8: =SUM(L3:L7) -> 341793.43
A9: Evans | E9: 1300
A10: Jesper | D10: 200
A11: Joshua
A12: Kampamba | E12: 3100
A13: Karen Mwinga | C13: 10200
A14: Keji | B14: 5200
A15: Kombe | D15: 5200
A16: Khucwayo | B16: 700
A17: Kwibisa | D17: 3200
A18: Michael | D18: 200
A19: Millie | B19: 2700
A20: Mukuma | B20: 5000
A21: Mumba | D21: 1000
A22: Mumbi | C22: 4300
A23: Mwenya | E23: 1200
A24: Nyanyiwe | C24: 1200
A25: Pamela | C25: 3200
A26: Schuller | B26: 1200
A27: Shubart | C27: 1500
A28: Solomon
A29: TOTAL LOAN | B29: =SUM(B5:B28) -> 25280 | C29: =SUM(C5:C28) -> 20400 | D29: =SUM(D5:D28) -> 9800 | E29: =SUM(E5:E28) -> 23100
A30: Millie | B30: 1200
A31: Phyllis | B31: 7500 | D31: September
A32: Karen Mwinga | B32: =#REF! -> #REF! | D32: Chilombo | E32: 4000
D33: Evans | E33: 14000
A34: Total | B34: =SUM(B29:B33) -> #REF! | D34: Keji | E34: 164
D35: Mike | E35: 388
D36: Mukuma | E36: 754
A37: Grand Total | B37: =SUM(B6,B15,B25,B34) -> #REF! | D37: Mumba | E37: 395
D38: Mumbi | E38: 1000
D39: Solomon | E39: 223
E40: 10000
D41: Tumelo | E41: 62
D42: Total | E42: =SUM(E32:E41) -> 30986
D45: Grand Total | E45: =SUM(E9,E28,E42) -> 32286

Sheet New Repayment Schedule
H1: INFRACash 2025
H2: LOAN TRANSACTIONS
H3: 1 | I3: 2 | J3: 3 | K3: 4 | L3: 5 | M3: 6 | N3: 7 | O3: 8 | P3: 9 | Q3: 10 | R3: 11 | S3: 12 | T3: 13 | U3: 14 | V3: 15 | W3: 16 | X3: 17 | Y3: 18 | Z3: 19 | AA3: 20 | AB3: 21 | AC3: 22 | AD3: 23 | AE3: 24 | AF3: 25 | AG3: 26 | AH3: 27 | AI3: 28 | AJ3: 29 | AK3: 30 | AL3: 31 | AM3: 32 | AN3: 33 | AO3: 34 | AP3: 35 | AQ3: 36 | AR3: 37 | AS3: 38 | AT3: 39 | AU3: 40 | AV3: 41 | AW3: 42 | AX3: 43 | AY3: 44 | AZ3: 45 | BA3: 46 | BB3: 47 | BC3: 48 | BD3: 49 | BE3: 50 | BF3: 51 | BG3: 52 | BH3: 53 | BI3: 54 | BJ3: 55 | BK3: 56 | BL3: 57 | BM3: 58 | BN3: 59 | BO3: 60 | BP3: 61 | BQ3: 62 | BS3: 63 | BT3: 64 | BU3: 65 | BV3: 66 | BW3: 67 | BX3: 68 | BY3: 69 | BZ3: 70 | CB3: 71 | CC3: 72 | CD3: 73 | CE3: 74 | CF3: 75 | CG3: 76 | CI3: 77 | CJ3: 78 | CL3: 79 | CM3: 80 | CN3: 81 | CO3: 82 | CP3: 83 | CQ3: 84 | CR3: 85 | CS3: 86 | CU3: 87 | CV3: 88 | CW3: 89 | CX3: 90 | CY3: 91 | CZ3: 92 | DA3: 93 | DB3: 94 | DC3: 95
I4: NOVEMBER | Q4: DECEMBER | Y4: JANUARY | AG4: FEBRUARY | AO4: MARCH | AW4: APRIL | BE4: MAY | BM4: JUNE | BV4: JULY | CE4: AUGUST | CO4: SEPTEMBER | CX4: OCTOBER
B5: Saving | C5: Loan Application | D5: Loan Repayment | E5: Credit Limit | H5: Member ID | I5: Opening Loan Balance | J5: Loan repayment | K5: Loan Application | L5: Interest 5% | M5: Interest 10% | N5: Closing Loan Balance | O5: Credit Limit | Q5: Opening Loan Balance | R5: Loan repayment | S5: Loan Application | T5: Interest 5% | U5: Interest 10% | V5: Closing Loan Balance | W5: Credit Limit | Y5: Opening Loan Balance | Z5: Loan repayment | AA5: Loan Application | AB5: Interest 5% | AC5: Interest 10% | AD5: Closing Loan Balance | AE5: Credit Limit | AG5: Opening Loan Balance | AH5: Loan repayment | AI5: Loan Application | AJ5: Interest 5% | AK5: Interest 10% | AL5: Closing Loan Balance | AM5: Credit Limit | AO5: Opening Loan Balance | AP5: Loan repayment | AQ5: Loan Application | AR5: Interest 5% | AS5: Interest 10% | AT5: Closing Loan Balance | AU5: Credit Limit | AW5: Opening Loan Balance | AX5: Loan repayment | AY5: Loan Application | AZ5: Interest 5% | BA5: Interest 10% | BB5: Closing Loan Balance | BC5: Credit Limit | BE5: Opening Loan Balance | BF5: Loan repayment | BG5: Loan Application | BH5: Interest 5% | BI5: Interest 10% | BJ5: Closing Loan Balance | BK5: Credit Limit | BM5: Opening Loan Balance | BN5: Loan repayment | BO5: Loan Application | BP5: Interest 5% | BQ5: Interest 10% | BR5: Penalt | BS5: Closing Loan Balance | BT5: Credit Limit | BV5: Opening Loan Balance | BW5: Loan repayment | BX5: Loan Application | BY5: Interest 5% | BZ5: Interest 10% | CA5: Penalt | CB5: Closing Loan Balance | CC5: Credit Limit | CE5: Opening Loan Balance | CF5: Loan repayment | CG5: Loan Application | CH5: Forced Loan | CI5: Interest 5% | CJ5: Interest 10% | CK5: Penalt | CL5: Closing Loan Balance | CM5: Credit Limit | CO5: Opening Loan Balance | CP5: Loan repayment | CQ5: Loan Application | CR5: Interest 5% | CS5: Interest 10% | CT5: Penalty | CU5: Closing Loan Balance | CV5: Credit Limit | CX5: Opening Loan Balance | CY5: Loan repayment | CZ5: Loan Application | DA5: Interest 5% | DB5: Interest 10% | DC5: Closing Loan Balance | DD5: Credit Limit
B6: Saving | C6: Loan Application | D6: Loan Repayment | E6: Fines/Penalties | G6: 1 | H6: Abigail Mundia | L6: =IF(J6>0,(I6-J6)*0.05,0) -> 0 | M6: =IF(K6>0,K6*0.1,0) -> 0 | N6: =I6-J6+K6+L6+M6 -> 0 | O6: =(VLOOKUP(H6,INFRACASHshares2025,25,0)-N6) -> 82200 | Q6: =N6 -> 0 | S6: 44800 | T6: =IF(R6>0,(Q6-R6)*0.05,0) -> 0 | U6: =IF(S6>0,S6*0.1,0) -> 4480 | V6: =(Q6-R6+S6+T6+U6) -> 49280 | W6: =(VLOOKUP(H6,INFRACASHshares2025,25,0)-V6) -> 32920 | Y6: =V6 -> 49280 | Z6: 2500 | AB6: =IF(Z6>0,(Y6-Z6)*0.05,0) -> 2339 | AC6: =IF(AA6>0,AA6*0.1,0) -> 0 | AD6: =(Y6-Z6+AA6+AB6+AC6) -> 49119 | AE6: =(VLOOKUP(H6,INFRACASHshares2025,25,0)-AD6) -> 33081 | AG6: =AD6 -> 49119 | AH6: 5000 | AJ6: =((AG6-AH6)*0.05) -> 2205.95 | AK6: =IF(AI6>0,AI6*0.1,0) -> 0 | AL6: =(AG6-AH6+AI6+AJ6+AK6) -> 46324.95 | AM6: =(VLOOKUP(H6,INFRACASHshares2025,25,0)-AL6) -> 35875.05 | AO6: =AL6 -> 46324.95 | AP6: 3000 | AQ6: 50000 | AR6: =((AO6-AP6)*0.05) -> 2166.2475 | AS6: =IF(AQ6>0,AQ6*0.1,0) -> 5000 | AT6: =(AO6-AP6+AQ6+AR6+AS6) -> 100491.2 | AU6: =(VLOOKUP(H6,INFRACASHshares2025,25,0)-AT6) -> -18291.197 | AW6: =AT6 -> 100491.2 | AX6: 5000 | AZ6: =((AW6-AX6)*0.05) -> 4774.5599 | BA6: =IF(AY6>0,AY6*0.1,0) -> 0 | BB6: =(AW6-AX6+AY6+AZ6+BA6) -> 100265.76 | BC6: =(VLOOKUP(H6,INFRACASHshares2025,25,0)-BB6) -> -18065.757 | BE6: =BB6 -> 100265.76 | BF6: 3500 | BG6: =3429+1019.39 -> 4448.39 | BH6: =(BE6-BF6)*0.05 -> 4838.2879 | BI6: =IF(BG6>0,BG6*0.1,0) -> 444.839 | BJ6: =(BE6-BF6+BG6+BH6+BI6) -> 106497.27 | BK6: =(VLOOKUP(H6,INFRACASHshares2025,25,0)-BJ6) -> -24297.274 | BM6: =BJ6 -> 106497.27 | BN6: 6300 | BP6: =(BM6-BN6)*0.05 -> 5009.8637 | BQ6: =IF(BO6>0,BO6*0.1,0) -> 0 | BS6: =(BM6-BN6+BO6+BP6+BQ6+BR6) -> 105207.14 | BT6: =(VLOOKUP(H6,INFRACASHshares2025,25,0)-BS6) -> -23007.138 | BV6: =BS6 -> 105207.14 | BW6: 5300 | BY6: =(BV6-BW6)*0.05 -> 4995.3569 | BZ6: =IF(BX6>0,BX6*0.1,0) -> 0 | CB6: =(BV6-BW6+BX6+BY6+BZ6) -> 104902.49 | CC6: =(VLOOKUP(H6,INFRACASHshares2025,25,0)-CB6) -> -22702.495 | CE6: =CB6 -> 104902.49 | CF6: 17500 | CH6: 4509.4716 | CI6: =(CE6-CF6)*0.05 -> 4370.1247 | CJ6: =IF((CG6+CH6)>0,((CG6+CH6)*0.1),0) -> 450.94716 | CL6: =(CE6-CF6+CG6+CI6+CJ6) -> 92223.567 | CM6: =(VLOOKUP(H6,INFRACASHshares2025,25,0)-CL6) -> -10023.567 | CO6: =CL6 -> 92223.567 | CP6: 24000 | CR6: =((CO6-CP6)*0.05) -> 3411.1783 | CS6: =IF(CQ6>0,CQ6*0.1,0) -> 0 | CU6: =(CO6-CP6+CQ6+CR6+CS6) -> 71634.745 | CV6: =(VLOOKUP(H6,INFRACASHshares2025,25,0)-CU6) -> 10565.255 | CX6: =CU6 -> 71634.745 | DA6: =((CX6-CY8)*0.05) -> 3581.7373 | DB6: =IF(CZ6>0,CZ6*0.1,0) -> 0 | DC6: =(CX6-CY6+CZ6+DA6+DB6) -> 75216.482 | DD6: =(VLOOKUP(H6,INFRACASHshares2025,25,0)-DC6) -> 6983.5176
B7: Saving | C7: Loan Application | D7: Loan Repayment | E7: Fines/Penalties | G7: 2 | H7: Abel Kunda | L7: =IF(J7>0,(I7-J7)*0.05,0) -> 0 | M7: =IF(K7>0,K7*0.1,0) -> 0 | N7: =I7-J7+K7+L7+M7 -> 0 | O7: =(VLOOKUP(H7,INFRACASHshares2025,25,0)-N7) -> 147000 | Q7: =N7 -> 0 | T7: =IF(R7>0,(Q7-R7)*0.05,0) -> 0 | U7: =IF(S7>0,S7*0.1,0) -> 0 | V7: =(Q7-R7+S7+T7+U7) -> 0 | W7: =(VLOOKUP(H7,INFRACASHshares2025,25,0)-V7) -> 147000 | Y7: =V7 -> 0 | AB7: =IF(Z7>0,(Y7-Z7)*0.05,0) -> 0 | AC7: =IF(AA7>0,AA7*0.1,0) -> 0 | AD7: =(Y7-Z7+AA7+AB7+AC7) -> 0 | AE7: =(VLOOKUP(H7,INFRACASHshares2025,25,0)-AD7) -> 147000 | AG7: =AD7 -> 0 | AJ7: =((AG7-AH7)*0.05) -> 0 | AK7: =IF(AI7>0,AI7*0.1,0) -> 0 | AL7: =(AG7-AH7+AI7+AJ7+AK7) -> 0 | AM7: =(VLOOKUP(H7,INFRACASHshares2025,25,0)-AL7) -> 147000 | AO7: =AL7 -> 0 | AR7: =((AO7-AP7)*0.05) -> 0 | AS7: =IF(AQ7>0,AQ7*0.1,0) -> 0 | AT7: =(AO7-AP7+AQ7+AR7+AS7) -> 0 | AU7: =(VLOOKUP(H7,INFRACASHshares2025,25,0)-AT7) -> 147000 | AW7: =AT7 -> 0 | AZ7: =((AW7-AX7)*0.05) -> 0 | BA7: =IF(AY7>0,AY7*0.1,0) -> 0 | BB7: =(AW7-AX7+AY7+AZ7+BA7) -> 0 | BC7: =(VLOOKUP(H7,INFRACASHshares2025,25,0)-BB7) -> 147000 | BE7: =BB7 -> 0 | BH7: =(BE7-BF7)*0.05 -> 0 | BI7: =IF(BG7>0,BG7*0.1,0) -> 0 | BJ7: =(BE7-BF7+BG7+BH7+BI7) -> 0 | BK7: =(VLOOKUP(H7,INFRACASHshares2025,25,0)-BJ7) -> 147000 | BM7: =BJ7 -> 0 | BO7: 14025 | BP7: =(BM7-BN7)*0.05 -> 0 | BQ7: =IF(BO7>0,BO7*0.1,0) -> 1402.5 | BS7: =(BM7-BN7+BO7+BP7+BQ7+BR7) -> 15427.5 | BT7: =(VLOOKUP(H7,INFRACASHshares2025,25,0)-BS7) -> 131572.5 | BV7: =BS7 -> 15427.5 | BW7: 3000 | BX7: 26090 | BY7: =(BV7-BW7)*0.05 -> 621.375 | BZ7: =IF(BX7>0,BX7*0.1,0) -> 2609 | CB7: =(BV7-BW7+BX7+BY7+BZ7) -> 41747.875 | CC7: =(VLOOKUP(H7,INFRACASHshares2025,25,0)-CB7) -> 105252.12 | CE7: =CB7 -> 41747.875 | CF7: 13500 | CH7: 8064.3836 | CI7: =(CE7-CF7)*0.05 -> 1412.3938 | CJ7: =IF((CG7+CH7)>0,((CG7+CH7)*0.1),0) -> 806.43836 | CL7: =(CE7-CF7+CG7+CI7+CJ7) -> 30466.707 | CM7: =(VLOOKUP(H7,INFRACASHshares2025,25,0)-CL7) -> 116533.29 | CO7: =CL7 -> 30466.707 | CP7: 15806.44 | CR7: =((CO7-CP7)*0.05) -> 733.01336 | CS7: =IF(CQ7>0,CQ7*0.1,0) -> 0 | CU7: =(CO7-CP7+CQ7+CR7+CS7) -> 15393.28 | CV7: =(VLOOKUP(H7,INFRACASHshares2025,25,0)-CU7) -> 131606.72 | CX7: =CU7 -> 15393.28 | DA7: =((CX7-CY8)*0.05) -> 769.66402 | DB7: =IF(CZ7>0,CZ7*0.1,0) -> 0 | DC7: =(CX7-CY7+CZ7+DA7+DB7) -> 16162.944 | DD7: =(VLOOKUP(H7,INFRACASHshares2025,25,0)-DC7) -> 130837.06
B8: Saving | C8: Loan Application | D8: Loan Repayment | E8: Fines/Penalties | G8: 3 | H8: Andrew | K8: 6400 | L8: =IF(J8>0,(I8-J8)*0.05,0) -> 0 | M8: =IF(K8>0,K8*0.1,0) -> 640 | N8: =I8-J8+K8+L8+M8 -> 7040 | O8: =(VLOOKUP(H8,INFRACASHshares2025,25,0)-N8) -> 10360 | Q8: =N8 -> 7040 | R8: 640 | T8: =IF(R8>0,(Q8-R8)*0.05,0) -> 320 | U8: =IF(S8>0,S8*0.1,0) -> 0 | V8: =(Q8-R8+S8+T8+U8) -> 6720 | W8: =(VLOOKUP(H8,INFRACASHshares2025,25,0)-V8) -> 10680 | Y8: =V8 -> 6720 | Z8: 1250 | AB8: =IF(Z8>0,(Y8-Z8)*0.05,0) -> 273.5 | AC8: =IF(AA8>0,AA8*0.1,0) -> 0 | AD8: =(Y8-Z8+AA8+AB8+AC8) -> 5743.5 | AE8: =(VLOOKUP(H8,INFRACASHshares2025,25,0)-AD8) -> 11656.5 | AG8: =AD8 -> 5743.5 | AH8: 3000 | AJ8: =((AG8-AH8)*0.05) -> 137.175 | AK8: =IF(AI8>0,AI8*0.1,0) -> 0 | AL8: =(AG8-AH8+AI8+AJ8+AK8) -> 2880.675 | AM8: =(VLOOKUP(H8,INFRACASHshares2025,25,0)-AL8) -> 14519.325 | AO8: =AL8 -> 2880.675 | AP8: 200 | AQ8: 24000 | AR8: =((AO8-AP8)*0.05) -> 134.03375 | AS8: =IF(AQ8>0,AQ8*0.1,0) -> 2400 | AT8: =(AO8-AP8+AQ8+AR8+AS8) -> 29214.709 | AU8: =(VLOOKUP(H8,INFRACASHshares2025,25,0)-AT8) -> -11814.709 | AW8: =AT8 -> 29214.709 | AX8: 5214 | AZ8: =((AW8-AX8)*0.05) -> 1200.0354 | BA8: =IF(AY8>0,AY8*0.1,0) -> 0 | BB8: =(AW8-AX8+AY8+AZ8+BA8) -> 25200.744 | BC8: =(VLOOKUP(H8,INFRACASHshares2025,25,0)-BB8) -> -7800.7442 | BE8: =BB8 -> 25200.744 | BF8: 2400 | BG8: 8000 | BH8: =(BE8-BF8)*0.05 -> 1140.0372 | BI8: =IF(BG8>0,BG8*0.1,0) -> 800 | BJ8: =(BE8-BF8+BG8+BH8+BI8) -> 32740.781 | BK8: =(VLOOKUP(H8,INFRACASHshares2025,25,0)-BJ8) -> -15340.781 | BM8: =BJ8 -> 32740.781 | BN8: 11000 | BP8: =(BM8-BN8)*0.05 -> 1087.0391 | BQ8: =IF(BO8>0,BO8*0.1,0) -> 0 | BS8: =(BM8-BN8+BO8+BP8+BQ8+BR8) -> 22827.82 | BT8: =(VLOOKUP(H8,INFRACASHshares2025,25,0)-BS8) -> -5427.8205 | BV8: =BS8 -> 22827.82 | BW8: 11990 | BY8: =(BV8-BW8)*0.05 -> 541.89102 | BZ8: =IF(BX8>0,BX8*0.1,0) -> 0 | CB8: =(BV8-BW8+BX8+BY8+BZ8) -> 11379.711 | CC8: =(VLOOKUP(H8,INFRACASHshares2025,25,0)-CB8) -> 6020.2885 | CE8: =CB8 -> 11379.711 | CF8: 1380 | CH8: 954.55969 | CI8: =(CE8-CF8)*0.05 -> 499.98557 | CJ8: =IF((CG8+CH8)>0,((CG8+CH8)*0.1),0) -> 95.455969 | CL8: =(CE8-CF8+CG8+CI8+CJ8) -> 10595.153 | CM8: =(VLOOKUP(H8,INFRACASHshares2025,25,0)-CL8) -> 6804.847 | CO8: =CL8 -> 10595.153 | CP8: 9560 | CR8: =((CO8-CP8)*0.05) -> 51.757652 | CS8: =IF(CQ8>0,CQ8*0.1,0) -> 0 | CU8: =(CO8-CP8+CQ8+CR8+CS8) -> 1086.9107 | CV8: =(VLOOKUP(H8,INFRACASHshares2025,25,0)-CU8) -> 16313.089 | CX8: =CU8 -> 1086.9107 | DA8: =((CX8-CY9)*0.05) -> 54.345534 | DB8: =IF(CZ8>0,CZ8*0.1,0) -> 0 | DC8: =(CX8-CY8+CZ8+DA8+DB8) -> 1141.2562 | DD8: =(VLOOKUP(H8,INFRACASHshares2025,25,0)-DC8) -> 16258.744
B9: Saving | C9: Loan Application | D9: Loan Repayment | E9: Fines/Penalties | G9: 4 | H9: Arthur | L9: =IF(J9>0,(I9-J9)*0.05,0) -> 0 | M9: =IF(K9>0,K9*0.1,0) -> 0 | N9: =I9-J9+K9+L9+M9 -> 0 | O9: =(VLOOKUP(H9,INFRACASHshares2025,25,0)-N9) -> 18600 | Q9: =N9 -> 0 | T9: =IF(R9>0,(Q9-R9)*0.05,0) -> 0 | U9: =IF(S9>0,S9*0.1,0) -> 0 | V9: =(Q9-R9+S9+T9+U9) -> 0 | W9: =(VLOOKUP(H9,INFRACASHshares2025,25,0)-V9) -> 18600 | Y9: =V9 -> 0 | AB9: =IF(Z9>0,(Y9-Z9)*0.05,0) -> 0 | AC9: =IF(AA9>0,AA9*0.1,0) -> 0 | AD9: =(Y9-Z9+AA9+AB9+AC9) -> 0 | AE9: =(VLOOKUP(H9,INFRACASHshares2025,25,0)-AD9) -> 18600 | AG9: =AD9 -> 0 | AJ9: =((AG9-AH9)*0.05) -> 0 | AK9: =IF(AI9>0,AI9*0.1,0) -> 0 | AL9: =(AG9-AH9+AI9+AJ9+AK9) -> 0 | AM9: =(VLOOKUP(H9,INFRACASHshares2025,25,0)-AL9) -> 18600 | AO9: =AL9 -> 0 | AR9: =((AO9-AP9)*0.05) -> 0 | AS9: =IF(AQ9>0,AQ9*0.1,0) -> 0 | AT9: =(AO9-AP9+AQ9+AR9+AS9) -> 0 | AU9: =(VLOOKUP(H9,INFRACASHshares2025,25,0)-AT9) -> 18600 | AW9: =AT9 -> 0 | AZ9: =((AW9-AX9)*0.05) -> 0 | BA9: =IF(AY9>0,AY9*0.1,0) -> 0 | BB9: =(AW9-AX9+AY9+AZ9+BA9) -> 0 | BC9: =(VLOOKUP(H9,INFRACASHshares2025,25,0)-BB9) -> 18600 | BE9: =BB9 -> 0 | BH9: =(BE9-BF9)*0.05 -> 0 | BI9: =IF(BG9>0,BG9*0.1,0) -> 0 | BJ9: =(BE9-BF9+BG9+BH9+BI9) -> 0 | BK9: =(VLOOKUP(H9,INFRACASHshares2025,25,0)-BJ9) -> 18600 | BM9: =BJ9 -> 0 | BO9: 17000 | BP9: =(BM9-BN9)*0.05 -> 0 | BQ9: =IF(BO9>0,BO9*0.1,0) -> 1700 | BS9: =(BM9-BN9+BO9+BP9+BQ9+BR9) -> 18700 | BT9: =(VLOOKUP(H9,INFRACASHshares2025,25,0)-BS9) -> -100 | BV9: =BS9 -> 18700 | BW9: 5000 | BY9: =(BV9-BW9)*0.05 -> 685 | BZ9: =IF(BX9>0,BX9*0.1,0) -> 0 | CB9: =(BV9-BW9+BX9+BY9+BZ9) -> 14385 | CC9: =(VLOOKUP(H9,INFRACASHshares2025,25,0)-CB9) -> 4215 | CE9: =CB9 -> 14385 | CF9: 5000 | CH9: 1020.3914 | CI9: =(CE9-CF9)*0.05 -> 469.25 | CJ9: =IF((CG9+CH9)>0,((CG9+CH9)*0.1),0) -> 102.03914 | CL9: =(CE9-CF9+CG9+CI9+CJ9) -> 9956.2891 | CM9: =(VLOOKUP(H9,INFRACASHshares2025,25,0)-CL9) -> 8643.7109 | CO9: =CL9 -> 9956.2891 | CP9: 5102.04 | CR9: =((CO9-CP9)*0.05) -> 242.71246 | CS9: =IF(CQ9>0,CQ9*0.1,0) -> 0 | CU9: =(CO9-CP9+CQ9+CR9+CS9) -> 5096.9616 | CV9: =(VLOOKUP(H9,INFRACASHshares2025,25,0)-CU9) -> 13503.038 | CX9: =CU9 -> 5096.9616 | DA9: =((CX9-CY10)*0.05) -> 254.84808 | DB9: =IF(CZ9>0,CZ9*0.1,0) -> 0 | DC9: =(CX9-CY9+CZ9+DA9+DB9) -> 5351.8097 | DD9: =(VLOOKUP(H9,INFRACASHshares2025,25,0)-DC9) -> 13248.19
B10: Saving | C10: Loan Application | D10: Loan Repayment | E10: Fines/Penalties | G10: 5 | H10: Evans | K10: 20000 | L10: =IF(J10>0,(I10-J10)*0.05,0) -> 0 | M10: =IF(K10>0,K10*0.1,0) -> 2000 | N10: =I10-J10+K10+L10+M10 -> 22000 | O10: =(VLOOKUP(H10,INFRACASHshares2025,25,0)-N10) -> 9200 | Q10: =N10 -> 22000 | R10: 1000 | S10: 11340 | T10: =IF(R10>0,(Q10-R10)*0.05,0) -> 1050 | U10: =IF(S10>0,S10*0.1,0) -> 1134 | V10: =(Q10-R10+S10+T10+U10) -> 34524 | W10: =(VLOOKUP(H10,INFRACASHshares2025,25,0)-V10) -> -3324 | Y10: =V10 -> 34524 | Z10: 2000 | AB10: =IF(Z10>0,(Y10-Z10)*0.05,0) -> 1626.2 | AC10: =IF(AA10>0,AA10*0.1,0) -> 0 | AD10: =(Y10-Z10+AA10+AC10) -> 32524 | AE10: =(VLOOKUP(H10,INFRACASHshares2025,25,0)-AD10) -> -1324 | AG10: =AD10 -> 32524 | AH10: 2000 | AJ10: =((AG10-AH10)*0.05) -> 1526.2 | AK10: =IF(AI10>0,AI10*0.1,0) -> 0 | AL10: =(AG10-AH10+AI10+AJ10+AK10) -> 32050.2 | AM10: =(VLOOKUP(H10,INFRACASHshares2025,25,0)-AL10) -> -850.2 | AO10: =AL10 -> 32050.2 | AP10: 2000 | AR10: =((AO10-AP10)*0.05) -> 1502.51 | AS10: =IF(AQ10>0,AQ10*0.1,0) -> 0 | AT10: =(AO10-AP10+AQ10+AR10+AS10) -> 31552.71 | AU10: =(VLOOKUP(H10,INFRACASHshares2025,25,0)-AT10) -> -352.71 | AW10: =AT10 -> 31552.71 | AX10: 1000 | AY10: 9967.81 | AZ10: =((AW10-AX10)*0.05) -> 1527.6355 | BA10: =IF(AY10>0,AY10*0.1,0) -> 996.781 | BB10: =(AW10-AX10+AY10+AZ10+BA10) -> 43044.936 | BC10: =(VLOOKUP(H10,INFRACASHshares2025,25,0)-BB10) -> -11844.936 | BE10: =BB10 -> 43044.936 | BF10: 3000 | BG10: 5300 | BH10: =(BE10-BF10)*0.05 -> 2002.2468 | BI10: =IF(BG10>0,BG10*0.1,0) -> 530 | BJ10: =(BE10-BF10+BG10+BH10+BI10) -> 47877.183 | BK10: =(VLOOKUP(H10,INFRACASHshares2025,25,0)-BJ10) -> -16677.183 | BM10: =BJ10 -> 47877.183 | BN10: 800 | BP10: =(BM10-BN10)*0.05 -> 2353.8592 | BQ10: =IF(BO10>0,BO10*0.1,0) -> 0 | BS10: =(BM10-BN10+BO10+BP10+BQ10+BR10) -> 49431.042 | BT10: =(VLOOKUP(H10,INFRACASHshares2025,25,0)-BS10) -> -18231.042 | BV10: =BS10 -> 49431.042 | BW10: 1000 | BX10: 10000 | BY10: =(BV10-BW10)*0.05 -> 2421.5521 | BZ10: =IF(BX10>0,BX10*0.1,0) -> 1000 | CB10: =(BV10-BW10+BX10+BY10+BZ10) -> 61852.595 | CC10: =(VLOOKUP(H10,INFRACASHshares2025,25,0)-CB10) -> -30652.595 | CE10: =CB10 -> 61852.595 | CF10: 1000 | CH10: 1711.6243 | CI10: =(CE10-CF10)*0.05 -> 3042.6297 | CJ10: =IF((CG10+CH10)>0,((CG10+CH10)*0.1),0) -> 171.16243 | CL10: =(CE10-CF10+CG10+CI10+CJ10) -> 64066.387 | CM10: =(VLOOKUP(H10,INFRACASHshares2025,25,0)-CL10) -> -32866.387 | CO10: =CL10 -> 64066.387 | CP10: 54482.281 | CR10: =((CO10-CP10)*0.05) -> 479.2053 | CS10: =IF(CQ10>0,CQ10*0.1,0) -> 0 | CU10: =(CO10-CP10+CQ10+CR10+CS10) -> 10063.311 | CV10: =(VLOOKUP(H10,INFRACASHshares2025,25,0)-CU10) -> 21136.689 | CX10: =CU10 -> 10063.311 | DA10: =((CX10-CY11)*0.05) -> 503.16556 | DB10: =IF(CZ10>0,CZ10*0.1,0) -> 0 | DC10: =(CX10-CY10+CZ10+DA10+DB10) -> 10566.477 | DD10: =(VLOOKUP(H10,INFRACASHshares2025,25,0)-DC10) -> 20633.523
B11: Saving | C11: Loan Application | D11: Loan Repayment | E11: Fines/Penalties | G11: 6 | H11: Jesper | L11: =IF(J11>0,(I11-J11)*0.05,0) -> 0 | M11: =IF(K11>0,K11*0.1,0) -> 0 | N11: =I11-J11+K11+L11+M11 -> 0 | O11: =(VLOOKUP(H11,INFRACASHshares2025,25,0)-N11) -> 6600 | Q11: =N11 -> 0 | T11: =IF(R11>0,(Q11-R11)*0.05,0) -> 0 | U11: =IF(S11>0,S11*0.1,0) -> 0 | V11: =(Q11-R11+S11+T11+U11) -> 0 | W11: =(VLOOKUP(H11,INFRACASHshares2025,25,0)-V11) -> 6600 | Y11: =V11 -> 0 | AB11: =IF(Z11>0,(Y11-Z11)*0.05,0) -> 0 | AC11: =IF(AA11>0,AA11*0.1,0) -> 0 | AD11: =(Y11-Z11+AA11+AB11+AC11) -> 0 | AE11: =(VLOOKUP(H11,INFRACASHshares2025,25,0)-AD11) -> 6600 | AG11: =AD11 -> 0 | AJ11: =((AG11-AH11)*0.05) -> 0 | AK11: =IF(AI11>0,AI11*0.1,0) -> 0 | AL11: =(AG11-AH11+AI11+AJ11+AK11) -> 0 | AM11: =(VLOOKUP(H11,INFRACASHshares2025,25,0)-AL11) -> 6600 | AO11: =AL11 -> 0 | AR11: =((AO11-AP11)*0.05) -> 0 | AS11: =IF(AQ11>0,AQ11*0.1,0) -> 0 | AT11: =(AO11-AP11+AQ11+AR11+AS11) -> 0 | AU11: =(VLOOKUP(H11,INFRACASHshares2025,25,0)-AT11) -> 6600 | AW11: =AT11 -> 0 | AZ11: =((AW11-AX11)*0.05) -> 0 | BA11: =IF(AY11>0,AY11*0.1,0) -> 0 | BB11: =(AW11-AX11+AY11+AZ11+BA11) -> 0 | BC11: =(VLOOKUP(H11,INFRACASHshares2025,25,0)-BB11) -> 6600 | BE11: =BB11 -> 0 | BH11: =(BE11-BF11)*0.05 -> 0 | BI11: =IF(BG11>0,BG11*0.1,0) -> 0 | BJ11: =(BE11-BF11+BG11+BH11+BI11) -> 0 | BK11: =(VLOOKUP(H11,INFRACASHshares2025,25,0)-BJ11) -> 6600 | BM11: =BJ11 -> 0 | BP11: =(BM11-BN11)*0.05 -> 0 | BQ11: =IF(BO11>0,BO11*0.1,0) -> 0 | BS11: =(BM11-BN11+BO11+BP11+BQ11+BR11) -> 0 | BT11: =(VLOOKUP(H11,INFRACASHshares2025,25,0)-BS11) -> 6600 | BV11: =BS11 -> 0 | BY11: =(BV11-BW11)*0.05 -> 0 | BZ11: =IF(BX11>0,BX11*0.1,0) -> 0 | CA11: =0.15*BX11 -> 0 | CB11: =(BV11-BW11+BX11+BY11+BZ11+CA11) -> 0 | CC11: =(VLOOKUP(H11,INFRACASHshares2025,25,0)-CB11) -> 6600 | CE11: =CB11 -> 0 | CH11: 362.07436 | CI11: =(CE11-CF11)*0.05 -> 0 | CJ11: =IF((CG11+CH11)>0,((CG11+CH11)*0.1),0) -> 36.207436 | CL11: =(CE11-CF11+CG11+CI11+CJ11) -> 36.207436 | CM11: =(VLOOKUP(H11,INFRACASHshares2025,25,0)-CL11) -> 6563.7926 | CO11: =CL11 -> 36.207436 | CP11: 40 | CR11: =((CO11-CP11)*0.05) -> -0.18962818 | CS11: =IF(CQ11>0,CQ11*0.1,0) -> 0 | CU11: =(CO11-CP11+CQ11+CR11+CS11) -> -3.9821918 | CV11: =(VLOOKUP(H11,INFRACASHshares2025,25,0)-CU11) -> 6603.9822 | CX11: =CU11 -> -3.9821918 | DA11: =((CX11-CY12)*0.05) -> -0.19910959 | DB11: =IF(CZ11>0,CZ11*0.1,0) -> 0 | DC11: =(CX11-CY11+CZ11+DA11+DB11) -> -4.1813014 | DD11: =(VLOOKUP(H11,INFRACASHshares2025,25,0)-DC11) -> 6604.1813
B12: Saving | C12: Loan Application | D12: Loan Repayment | E12: Fines/Penalties | G12: 7 | H12: Joshua | L12: =IF(J12>0,(I12-J12)*0.05,0) -> 0 | M12: =IF(K12>0,K12*0.1,0) -> 0 | N12: =I12-J12+K12+L12+M12 -> 0 | O12: =(VLOOKUP(H12,INFRACASHshares2025,25,0)-N12) -> 40200 | Q12: =N12 -> 0 | T12: =IF(R12>0,(Q12-R12)*0.05,0) -> 0 | U12: =IF(S12>0,S12*0.1,0) -> 0 | V12: =(Q12-R12+S12+T12+U12) -> 0 | W12: =(VLOOKUP(H12,INFRACASHshares2025,25,0)-V12) -> 40200 | Y12: =V12 -> 0 | AA12: 3400 | AB12: =IF(Z12>0,(Y12-Z12)*0.05,0) -> 0 | AC12: =IF(AA12>0,AA12*0.1,0) -> 340 | AD12: =(Y12-Z12+AA12+AB12+AC12) -> 3740 | AE12: =(VLOOKUP(H12,INFRACASHshares2025,25,0)-AD12) -> 36460 | AG12: =AD12 -> 3740 | AH12: 1000 | AJ12: =((AG12-AH12)*0.05) -> 137 | AK12: =IF(AI12>0,AI12*0.1,0) -> 0 | AL12: =(AG12-AH12+AI12+AJ12+AK12) -> 2877 | AM12: =(VLOOKUP(H12,INFRACASHshares2025,25,0)-AL12) -> 37323 | AO12: =AL12 -> 2877 | AP12: 1000 | AR12: =((AO12-AP12)*0.05) -> 93.85 | AS12: =IF(AQ12>0,AQ12*0.1,0) -> 0 | AT12: =(AO12-AP12+AQ12+AR12+AS12) -> 1970.85 | AU12: =(VLOOKUP(H12,INFRACASHshares2025,25,0)-AT12) -> 38229.15 | AW12: =AT12 -> 1970.85 | AX12: 1000 | AZ12: =((AW12-AX12)*0.05) -> 48.5425 | BA12: =IF(AY12>0,AY12*0.1,0) -> 0 | BB12: =(AW12-AX12+AY12+AZ12+BA12) -> 1019.3925 | BC12: =(VLOOKUP(H12,INFRACASHshares2025,25,0)-BB12) -> 39180.607 | BE12: =BB12 -> 1019.3925 | BF12: 1019.3925 | BH12: =(BE12-BF12)*0.05 -> 0 | BI12: =IF(BG12>0,BG12*0.1,0) -> 0 | BJ12: =(BE12-BF12+BG12+BH12+BI12) -> 0 | BK12: =(VLOOKUP(H12,INFRACASHshares2025,25,0)-BJ12) -> 40200 | BM12: =BJ12 -> 0 | BP12: =(BM12-BN12)*0.05 -> 0 | BQ12: =IF(BO12>0,BO12*0.1,0) -> 0 | BS12: =(BM12-BN12+BO12+BP12+BQ12+BR12) -> 0 | BT12: =(VLOOKUP(H12,INFRACASHshares2025,25,0)-BS12) -> 40200 | BV12: =BS12 -> 0 | BY12: =(BV12-BW12)*0.05 -> 0 | BZ12: =IF(BX12>0,BX12*0.1,0) -> 0 | CB12: =(BV12-BW12+BX12+BY12+BZ12) -> 0 | CC12: =(VLOOKUP(H12,INFRACASHshares2025,25,0)-CB12) -> 40200 | CE12: =CB12 -> 0 | CG12: 11000 | CI12: =(CE12-CF12)*0.05 -> 0 | CJ12: =IF((CG12+CH12)>0,((CG12+CH12)*0.1),0) -> 1100 | CL12: =(CE12-CF12+CG12+CI12+CJ12) -> 12100 | CM12: =(VLOOKUP(H12,INFRACASHshares2025,25,0)-CL12) -> 28100 | CO12: =CL12 -> 12100 | CP12: 1100 | CR12: =((CO12-CP12)*0.05) -> 550 | CS12: =IF(CQ12>0,CQ12*0.1,0) -> 0 | CU12: =(CO12-CP12+CQ12+CR12+CS12) -> 11550 | CV12: =(VLOOKUP(H12,INFRACASHshares2025,25,0)-CU12) -> 28650 | CX12: =CU12 -> 11550 | DA12: =((CX12-CY13)*0.05) -> 577.5 | DB12: =IF(CZ12>0,CZ12*0.1,0) -> 0 | DC12: =(CX12-CY12+CZ12+DA12+DB12) -> 12127.5 | DD12: =(VLOOKUP(H12,INFRACASHshares2025,25,0)-DC12) -> 28072.5
B13: Saving | C13: Loan Application | D13: Loan Repayment | E13: Fines/Penalties | G13: 8 | H13: Kampamba | K13: 600 | L13: =IF(J13>0,(I13-J13)*0.05,0) -> 0 | M13: =IF(K13>0,K13*0.1,0) -> 60 | N13: =I13-J13+K13+L13+M13 -> 660 | O13: =(VLOOKUP(H13,INFRACASHshares2025,25,0)-N13) -> 21540 | Q13: =N13 -> 660 | R13: 1 | T13: =IF(R13>0,(Q13-R13)*0.05,0) -> 32.95 | U13: =IF(S13>0,S13*0.1,0) -> 0 | V13: =(Q13-R13+S13+T13+U13) -> 691.95 | W13: =(VLOOKUP(H13,INFRACASHshares2025,25,0)-V13) -> 21508.05 | Y13: =V13 -> 691.95 | AB13: =((Y13-Z13)*0.05) -> 34.5975 | AC13: =IF(AA13>0,AA13*0.1,0) -> 0 | AD13: =(Y13-Z13+AA13+AB13+AC13) -> 726.5475 | AE13: =(VLOOKUP(H13,INFRACASHshares2025,25,0)-AD13) -> 21473.452 | AG13: =AD13 -> 726.5475 | AJ13: =((AG13-AH13)*0.05) -> 36.327375 | AK13: =IF(AI13>0,AI13*0.1,0) -> 0 | AL13: =(AG13-AH13+AI13+AJ13+AK13) -> 762.87487 | AM13: =(VLOOKUP(H13,INFRACASHshares2025,25,0)-AL13) -> 21437.125 | AO13: =AL13 -> 762.87487 | AR13: =((AO13-AP13)*0.05) -> 38.143744 | AS13: =IF(AQ13>0,AQ13*0.1,0) -> 0 | AT13: =(AO13-AP13+AQ13+AR13+AS13) -> 801.01862 | AU13: =(VLOOKUP(H13,INFRACASHshares2025,25,0)-AT13) -> 21398.981 | AW13: =AT13 -> 801.01862 | AY13: 17500 | AZ13: =((AW13-AX13)*0.05) -> 40.050931 | BA13: =IF(AY13>0,AY13*0.1,0) -> 1750 | BB13: =(AW13-AX13+AY13+AZ13+BA13) -> 20091.07 | BC13: =(VLOOKUP(H13,INFRACASHshares2025,25,0)-BB13) -> 2108.9305 | BE13: =BB13 -> 20091.07 | BF13: 2000 | BH13: =(BE13-BF13)*0.05 -> 904.55348 | BI13: =IF(BG13>0,BG13*0.1,0) -> 0 | BJ13: =(BE13-BF13+BG13+BH13+BI13) -> 18995.623 | BK13: =(VLOOKUP(H13,INFRACASHshares2025,25,0)-BJ13) -> 3204.377 | BM13: =BJ13 -> 18995.623 | BN13: 2000 | BP13: =(BM13-BN13)*0.05 -> 849.78115 | BQ13: =IF(BO13>0,BO13*0.1,0) -> 0 | BS13: =(BM13-BN13+BO13+BP13+BQ13+BR13) -> 17845.404 | BT13: =(VLOOKUP(H13,INFRACASHshares2025,25,0)-BS13) -> 4354.5958 | BV13: =BS13 -> 17845.404 | BW13: 2000 | BY13: =(BV13-BW13)*0.05 -> 792.27021 | BZ13: =IF(BX13>0,BX13*0.1,0) -> 0 | CB13: =(BV13-BW13+BX13+BY13+BZ13) -> 16637.674 | CC13: =(VLOOKUP(H13,INFRACASHshares2025,25,0)-CB13) -> 5562.3256 | CE13: =CB13 -> 16637.674 | CF13: 2600 | CH13: 1217.8865 | CI13: =(CE13-CF13)*0.05 -> 701.88372 | CJ13: =IF((CG13+CH13)>0,((CG13+CH13)*0.1),0) -> 121.78865 | CL13: =(CE13-CF13+CG13+CI13+CJ13) -> 14861.347 | CM13: =(VLOOKUP(H13,INFRACASHshares2025,25,0)-CL13) -> 7338.6532 | CO13: =CL13 -> 14861.347 | CP13: 2621.79 | CR13: =((CO13-CP13)*0.05) -> 611.97784 | CS13: =IF(CQ13>0,CQ13*0.1,0) -> 0 | CU13: =(CO13-CP13+CQ13+CR13+CS13) -> 12851.535 | CV13: =(VLOOKUP(H13,INFRACASHshares2025,25,0)-CU13) -> 9348.4654 | CX13: =CU13 -> 12851.535 | DA13: =((CX13-CY14)*0.05) -> 642.57673 | DB13: =IF(CZ13>0,CZ13*0.1,0) -> 0 | DC13: =(CX13-CY13+CZ13+DA13+DB13) -> 13494.111 | DD13: =(VLOOKUP(H13,INFRACASHshares2025,25,0)-DC13) -> 8705.8887
B14: Saving | C14: Loan Application | D14: Loan Repayment | E14: Fines/Penalties | G14: 9 | H14: Karen Mwinga | L14: =IF(J14>0,(I14-J14)*0.05,0) -> 0 | M14: =IF(K14>0,K14*0.1,0) -> 0 | N14: =I14-J14+K14+L14+M14 -> 0 | O14: =(VLOOKUP(H14,INFRACASHshares2025,25,0)-N14) -> 15600 | Q14: =N14 -> 0 | T14: =IF(R14>0,(Q14-R14)*0.05,0) -> 0 | U14: =IF(S14>0,S14*0.1,0) -> 0 | V14: =(Q14-R14+S14+T14+U14) -> 0 | W14: =(VLOOKUP(H14,INFRACASHshares2025,25,0)-V14) -> 15600 | Y14: =V14 -> 0 | AA14: 11300 | AB14: =IF(Z14>0,(Y14-Z14)*0.05,0) -> 0 | AC14: =IF(AA14>0,AA14*0.1,0) -> 1130 | AD14: =(Y14-Z14+AA14+AB14+AC14) -> 12430 | AE14: =(VLOOKUP(H14,INFRACASHshares2025,25,0)-AD14) -> 3170 | AG14: =AD14 -> 12430 | AH14: 1200 | AJ14: =((AG14-AH14)*0.05) -> 561.5 | AK14: =IF(AI14>0,AI14*0.1,0) -> 0 | AL14: =(AG14-AH14+AI14+AJ14+AK14) -> 11791.5 | AM14: =(VLOOKUP(H14,INFRACASHshares2025,25,0)-AL14) -> 3808.5 | AO14: =AL14 -> 11791.5 | AP14: 1000 | AR14: =((AO14-AP14)*0.05) -> 539.575 | AS14: =IF(AQ14>0,AQ14*0.1,0) -> 0 | AT14: =(AO14-AP14+AQ14+AR14+AS14) -> 11331.075 | AU14: =(VLOOKUP(H14,INFRACASHshares2025,25,0)-AT14) -> 4268.925 | AW14: =AT14 -> 11331.075 | AX14: 5000 | AZ14: =((AW14-AX14)*0.05) -> 316.55375 | BA14: =IF(AY14>0,AY14*0.1,0) -> 0 | BB14: =(AW14-AX14+AY14+AZ14+BA14) -> 6647.6288 | BC14: =(VLOOKUP(H14,INFRACASHshares2025,25,0)-BB14) -> 8952.3713 | BE14: =BB14 -> 6647.6288 | BF14: 2000 | BH14: =(BE14-BF14)*0.05 -> 232.38144 | BI14: =IF(BG14>0,BG14*0.1,0) -> 0 | BJ14: =(BE14-BF14+BG14+BH14+BI14) -> 4880.0102 | BK14: =(VLOOKUP(H14,INFRACASHshares2025,25,0)-BJ14) -> 10719.99 | BM14: =BJ14 -> 4880.0102 | BN14: 2000 | BO14: 50000 | BP14: =(BM14-BN14)*0.05 -> 144.00051 | BQ14: =IF(BO14>0,BO14*0.1,0) -> 5000 | BS14: =(BM14-BN14+BO14+BP14+BQ14+BR14) -> 58024.011 | BT14: =(VLOOKUP(H14,INFRACASHshares2025,25,0)-BS14) -> -42424.011 | BV14: =BS14 -> 58024.011 | BW14: 4000 | BY14: =(BV14-BW14)*0.05 -> 2701.2005 | BZ14: =IF(BX14>0,BX14*0.1,0) -> 0 | CB14: =(BV14-BW14+BX14+BY14+BZ14) -> 56725.211 | CC14: =(VLOOKUP(H14,INFRACASHshares2025,25,0)-CB14) -> -41125.211 | CE14: =CB14 -> 56725.211 | CF14: 10000 | CH14: 855.81213 | CI14: =(CE14-CF14)*0.05 -> 2336.2606 | CJ14: =IF((CG14+CH14)>0,((CG14+CH14)*0.1),0) -> 85.581213 | CL14: =(CE14-CF14+CG14+CI14+CJ14) -> 49147.053 | CM14: =(VLOOKUP(H14,INFRACASHshares2025,25,0)-CL14) -> -33547.053 | CO14: =CL14 -> 49147.053 | CP14: 44750 | CR14: =((CO14-CP14)*0.05) -> 219.85265 | CS14: =IF(CQ14>0,CQ14*0.1,0) -> 0 | CU14: =(CO14-CP14+CQ14+CR14+CS14) -> 4616.9057 | CV14: =(VLOOKUP(H14,INFRACASHshares2025,25,0)-CU14) -> 10983.094 | CX14: =CU14 -> 4616.9057 | DA14: =((CX14-CY15)*0.05) -> 230.84528 | DB14: =IF(CZ14>0,CZ14*0.1,0) -> 0 | DC14: =(CX14-CY14+CZ14+DA14+DB14) -> 4847.7509 | DD14: =(VLOOKUP(H14,INFRACASHshares2025,25,0)-DC14) -> 10752.249
B15: Saving | C15: Loan Application | D15: Loan Repayment | E15: Fines/Penalties | G15: 10 | H15: Keji | K15: 6100 | L15: =IF(J15>0,(I15-J15)*0.05,0) -> 0 | M15: =IF(K15>0,K15*0.1,0) -> 610 | N15: =I15-J15+K15+L15+M15 -> 6710 | O15: =(VLOOKUP(H15,INFRACASHshares2025,25,0)-N15) -> 13090 | Q15: =N15 -> 6710 | R15: 1300 | T15: =IF(R15>0,(Q15-R15)*0.05,0) -> 270.5 | U15: =IF(S15>0,S15*0.1,0) -> 0 | V15: =(Q15-R15+S15+T15+U15) -> 5680.5 | W15: =(VLOOKUP(H15,INFRACASHshares2025,25,0)-V15) -> 14119.5 | Y15: =V15 -> 5680.5 | Z15: 600 | AB15: =IF(Z15>0,(Y15-Z15)*0.05,0) -> 254.025 | AC15: =IF(AA15>0,AA15*0.1,0) -> 0 | AD15: =(Y15-Z15+AA15+AB15+AC15) -> 5334.525 | AE15: =(VLOOKUP(H15,INFRACASHshares2025,25,0)-AD15) -> 14465.475 | AG15: =AD15 -> 5334.525 | AH15: 1000 | AI15: 21000 | AJ15: =((AG15-AH15)*0.05) -> 216.72625 | AK15: =IF(AI15>0,AI15*0.1,0) -> 2100 | AL15: =(AG15-AH15+AI15+AJ15+AK15) -> 27651.251 | AM15: =(VLOOKUP(H15,INFRACASHshares2025,25,0)-AL15) -> -7851.2513 | AO15: =AL15 -> 27651.251 | AP15: 9600 | AR15: =((AO15-AP15)*0.05) -> 902.56256 | AS15: =IF(AQ15>0,AQ15*0.1,0) -> 0 | AT15: =(AO15-AP15+AQ15+AR15+AS15) -> 18953.814 | AU15: =(VLOOKUP(H15,INFRACASHshares2025,25,0)-AT15) -> 846.18619 | AW15: =AT15 -> 18953.814 | AX15: 953.81 | AZ15: =((AW15-AX15)*0.05) -> 900.00019 | BA15: =IF(AY15>0,AY15*0.1,0) -> 0 | BB15: =(AW15-AX15+AY15+AZ15+BA15) -> 18900.004 | BC15: =(VLOOKUP(H15,INFRACASHshares2025,25,0)-BB15) -> 899.996 | BE15: =BB15 -> 18900.004 | BF15: 900 | BH15: =(BE15-BF15)*0.05 -> 900.0002 | BI15: =IF(BG15>0,BG15*0.1,0) -> 0 | BJ15: =(BE15-BF15+BG15+BH15+BI15) -> 18900.004 | BK15: =(VLOOKUP(H15,INFRACASHshares2025,25,0)-BJ15) -> 899.9958 | BM15: =BJ15 -> 18900.004 | BN15: 2900 | BP15: =(BM15-BN15)*0.05 -> 800.00021 | BQ15: =IF(BO15>0,BO15*0.1,0) -> 0 | BS15: =(BM15-BN15+BO15+BP15+BQ15+BR15) -> 16800.004 | BT15: =(VLOOKUP(H15,INFRACASHshares2025,25,0)-BS15) -> 2999.9956 | BV15: =BS15 -> 16800.004 | BW15: 2800 | BY15: =(BV15-BW15)*0.05 -> 700.00022 | BZ15: =IF(BX15>0,BX15*0.1,0) -> 0 | CB15: =(BV15-BW15+BX15+BY15+BZ15) -> 14700.005 | CC15: =(VLOOKUP(H15,INFRACASHshares2025,25,0)-CB15) -> 5099.9954 | CE15: =CB15 -> 14700.005 | CF15: 4900 | CH15: 1086.2231 | CI15: =(CE15-CF15)*0.05 -> 490.00023 | CJ15: =IF((CG15+CH15)>0,((CG15+CH15)*0.1),0) -> 108.62231 | CL15: =(CE15-CF15+CG15+CI15+CJ15) -> 10398.627 | CM15: =(VLOOKUP(H15,INFRACASHshares2025,25,0)-CL15) -> 9401.3728 | CO15: =CL15 -> 10398.627 | CP15: 796.74 | CR15: =((CO15-CP15)*0.05) -> 480.09436 | CS15: =IF(CQ15>0,CQ15*0.1,0) -> 0 | CU15: =(CO15-CP15+CQ15+CR15+CS15) -> 10081.982 | CV15: =(VLOOKUP(H15,INFRACASHshares2025,25,0)-CU15) -> 9718.0185 | CX15: =CU15 -> 10081.982 | DA15: =((CX15-CY16)*0.05) -> 504.09908 | DB15: =IF(CZ15>0,CZ15*0.1,0) -> 0 | DC15: =(CX15-CY15+CZ15+DA15+DB15) -> 10586.081 | DD15: =(VLOOKUP(H15,INFRACASHshares2025,25,0)-DC15) -> 9213.9194
B16: Saving | C16: Loan Application | D16: Loan Repayment | E16: Fines/Penalties | G16: 11 | H16: Kombe | L16: =IF(J16>0,(I16-J16)*0.05,0) -> 0 | M16: =IF(K16>0,K16*0.1,0) -> 0 | N16: =I16-J16+K16+L16+M16 -> 0 | O16: =(VLOOKUP(H16,INFRACASHshares2025,25,0)-N16) -> 95400 | Q16: =N16 -> 0 | S16: 6000 | T16: =IF(R16>0,(Q16-R16)*0.05,0) -> 0 | U16: =IF(S16>0,S16*0.1,0) -> 600 | V16: =(Q16-R16+S16+T16+U16) -> 6600 | W16: =(VLOOKUP(H16,INFRACASHshares2025,25,0)-V16) -> 88800 | Y16: =V16 -> 6600 | Z16: 1000 | AA16: 8750 | AB16: =IF(Z16>0,(Y16-Z16)*0.05,0) -> 280 | AC16: =IF(AA16>0,AA16*0.1,0) -> 875 | AD16: =(Y16-Z16+AA16+AB16+AC16) -> 15505 | AE16: =(VLOOKUP(H16,INFRACASHshares2025,25,0)-AD16) -> 79895 | AG16: =AD16 -> 15505 | AH16: 1000 | AJ16: =((AG16-AH16)*0.05) -> 725.25 | AK16: =IF(AI16>0,AI16*0.1,0) -> 0 | AL16: =(AG16-AH16+AI16+AJ16+AK16) -> 15230.25 | AM16: =(VLOOKUP(H16,INFRACASHshares2025,25,0)-AL16) -> 80169.75 | AO16: =AL16 -> 15230.25 | AP16: 1600 | AQ16: 50000 | AR16: =((AO16-AP16)*0.05) -> 681.5125 | AS16: =IF(AQ16>0,AQ16*0.1,0) -> 5000 | AT16: =(AO16-AP16+AQ16+AR16+AS16) -> 69311.762 | AU16: =(VLOOKUP(H16,INFRACASHshares2025,25,0)-AT16) -> 26088.238 | AW16: =AT16 -> 69311.762 | AX16: 8000 | AZ16: =((AW16-AX16)*0.05) -> 3065.5881 | BA16: =IF(AY16>0,AY16*0.1,0) -> 0 | BB16: =(AW16-AX16+AY16+AZ16+BA16) -> 64377.351 | BC16: =(VLOOKUP(H16,INFRACASHshares2025,25,0)-BB16) -> 31022.649 | BE16: =BB16 -> 64377.351 | BF16: 3000 | BG16: 55000 | BH16: =(BE16-BF16)*0.05 -> 3068.8675 | BI16: =IF(BG16>0,BG16*0.1,0) -> 5500 | BJ16: =(BE16-BF16+BG16+BH16+BI16) -> 124946.22 | BK16: =(VLOOKUP(H16,INFRACASHshares2025,25,0)-BJ16) -> -29546.218 | BM16: =BJ16 -> 124946.22 | BN16: 15000 | BP16: =(BM16-BN16)*0.05 -> 5497.3109 | BQ16: =IF(BO16>0,BO16*0.1,0) -> 0 | BS16: =(BM16-BN16+BO16+BP16+BQ16+BR16) -> 115443.53 | BT16: =(VLOOKUP(H16,INFRACASHshares2025,25,0)-BS16) -> -20043.529 | BV16: =BS16 -> 115443.53 | BW16: 6000 | BY16: =(BV16-BW16)*0.05 -> 5472.1765 | BZ16: =IF(BX16>0,BX16*0.1,0) -> 0 | CB16: =(BV16-BW16+BX16+BY16+BZ16) -> 114915.71 | CC16: =(VLOOKUP(H16,INFRACASHshares2025,25,0)-CB16) -> -19515.706 | CE16: =CB16 -> 114915.71 | CF16: 5000 | CH16: 5233.6204 | CI16: =(CE16-CF16)*0.05 -> 5495.7853 | CJ16: =IF((CG16+CH16)>0,((CG16+CH16)*0.1),0) -> 523.36204 | CL16: =(CE16-CF16+CG16+CI16+CJ16) -> 115934.85 | CM16: =(VLOOKUP(H16,INFRACASHshares2025,25,0)-CL16) -> -20534.853 | CO16: =CL16 -> 115934.85 | CP16: 40000 | CR16: =((CO16-CP16)*0.05) -> 3796.7426 | CS16: =IF(CQ16>0,CQ16*0.1,0) -> 0 | CU16: =(CO16-CP16+CQ16+CR16+CS16) -> 79731.595 | CV16: =(VLOOKUP(H16,INFRACASHshares2025,25,0)-CU16) -> 15668.405 | CX16: =CU16 -> 79731.595 | DA16: =((CX16-CY17)*0.05) -> 3986.5798 | DB16: =IF(CZ16>0,CZ16*0.1,0) -> 0 | DC16: =(CX16-CY16+CZ16+DA16+DB16) -> 83718.175 | DD16: =(VLOOKUP(H16,INFRACASHshares2025,25,0)-DC16) -> 11681.825
G17: 12 | H17: Khucwayo | L17: =IF(J17>0,(I17-J17)*0.05,0) -> 0 | M17: =IF(K17>0,K17*0.1,0) -> 0 | N17: =I17-J17+K17+L17+M17 -> 0 | O17: =(VLOOKUP(H17,INFRACASHshares2025,25,0)-N17) -> 9600 | Q17: =N17 -> 0 | T17: =IF(R17>0,(Q17-R17)*0.05,0) -> 0 | U17: =IF(S17>0,S17*0.1,0) -> 0 | V17: =(Q17-R17+S17+T17+U17) -> 0 | W17: =(VLOOKUP(H17,INFRACASHshares2025,25,0)-V17) -> 9600 | Y17: =V17 -> 0 | AA17: 1400 | AB17: =IF(Z17>0,(Y17-Z17)*0.05,0) -> 0 | AC17: =IF(AA17>0,AA17*0.1,0) -> 140 | AD17: =(Y17-Z17+AA17+AB17+AC17) -> 1540 | AE17: =(VLOOKUP(H17,INFRACASHshares2025,25,0)-AD17) -> 8060 | AG17: =AD17 -> 1540 | AJ17: =((AG17-AH17)*0.05) -> 77 | AK17: =IF(AI17>0,AI17*0.1,0) -> 0 | AL17: =(AG17-AH17+AI17+AJ17+AK17) -> 1617 | AM17: =(VLOOKUP(H17,INFRACASHshares2025,25,0)-AL17) -> 7983 | AO17: =AL17 -> 1617 | AP17: 600 | AR17: =((AO17-AP17)*0.05) -> 50.85 | AS17: =IF(AQ17>0,AQ17*0.1,0) -> 0 | AT17: =(AO17-AP17+AQ17+AR17+AS17) -> 1067.85 | AU17: =(VLOOKUP(H17,INFRACASHshares2025,25,0)-AT17) -> 8532.15 | AW17: =AT17 -> 1067.85 | AX17: 600 | AZ17: =((AW17-AX17)*0.05) -> 23.3925 | BA17: =IF(AY17>0,AY17*0.1,0) -> 0 | BB17: =(AW17-AX17+AY17+AZ17+BA17) -> 491.2425 | BC17: =(VLOOKUP(H17,INFRACASHshares2025,25,0)-BB17) -> 9108.7575 | BE17: =BB17 -> 491.2425 | BF17: 500 | BH17: =(BE17-BF17)*0.05 -> -0.437875 | BI17: =IF(BG17>0,BG17*0.1,0) -> 0 | BJ17: =(BE17-BF17+BG17+BH17+BI17) -> -9.195375 | BK17: =(VLOOKUP(H17,INFRACASHshares2025,25,0)-BJ17) -> 9609.1954 | BM17: =BJ17 -> -9.195375 | BP17: =(BM17-BN17)*0.05 -> -0.45976875 | BQ17: =IF(BO17>0,BO17*0.1,0) -> 0 | BS17: =(BM17-BN17+BO17+BP17+BQ17+BR17) -> -9.6551438 | BT17: =(VLOOKUP(H17,INFRACASHshares2025,25,0)-BS17) -> 9609.6551 | BV17: =BS17 -> -9.6551438 | BY17: =(BV17-BW17)*0.05 -> -0.48275719 | BZ17: =IF(BX17>0,BX17*0.1,0) -> 0 | CB17: =(BV17-BW17+BX17+BY17+BZ17) -> -10.137901 | CC17: =(VLOOKUP(H17,INFRACASHshares2025,25,0)-CB17) -> 9610.1379 | CE17: =CB17 -> -10.137901 | CF17: 400 | CH17: 526.65362 | CI17: =(CE17-CF17)*0.05 -> -20.506895 | CJ17: =IF((CG17+CH17)>0,((CG17+CH17)*0.1),0) -> 52.665362 | CL17: =(CE17-CF17+CG17+CI17+CJ17) -> -377.97943 | CM17: =(VLOOKUP(H17,INFRACASHshares2025,25,0)-CL17) -> 9977.9794 | CO17: =CL17 -> -377.97943 | CP17: 0 | CR17: =((CO17-CP17)*0.05) -> -18.898972 | CS17: =IF(CQ17>0,CQ17*0.1,0) -> 0 | CU17: =(CO17-CP17+CQ17+CR17+CS17) -> -396.87841 | CV17: =(VLOOKUP(H17,INFRACASHshares2025,25,0)-CU17) -> 9996.8784 | CX17: =CU17 -> -396.87841 | DA17: =((CX17-CY18)*0.05) -> -19.84392 | DB17: =IF(CZ17>0,CZ17*0.1,0) -> 0 | DC17: =(CX17-CY17+CZ17+DA17+DB17) -> -416.72233 | DD17: =(VLOOKUP(H17,INFRACASHshares2025,25,0)-DC17) -> 10016.722
B18: Saving | C18: Loan Application | D18: Loan Repayment | E18: Fines/Penalties | G18: 13 | H18: Kwibisa | K18: 15000 | N18: =I18-J18+K18+L18+M18 -> 15000 | O18: =(VLOOKUP(H18,INFRACASHshares2025,25,0)-N18) -> 7800 | Q18: =N18 -> 15000 | R18: 5000 | S18: 3500 | V18: =(Q18-R18+S18+T18+U18) -> 13500 | W18: =(VLOOKUP(H18,INFRACASHshares2025,25,0)-V18) -> 9300 | Y18: =V18 -> 13500 | Z18: 1000 | AA18: 2800 | AD18: =(Y18-Z18+AA18+AB18+AC18) -> 15300 | AG18: =AD18 -> 15300 | AH18: 1800 | AJ18: =((AG18-AH18)*0.05) -> 675 | AK18: =IF(AI18>0,AI18*0.1,0) -> 0 | AL18: =(AG18-AH18+AI18+AJ18+AK18) -> 14175 | AO18: =AL18 -> 14175 | AP18: 2200 | AR18: =((AO18-AP18)*0.05) -> 598.75 | AS18: =IF(AQ18>0,AQ18*0.1,0) -> 0 | AT18: =(AO18-AP18+AQ18+AR18+AS18) -> 12573.75 | AU18: =(VLOOKUP(H18,INFRACASHshares2025,25,0)-AT18) -> 10226.25 | AW18: =AT18 -> 12573.75 | AX18: 1000 | AY18: 8000 | AZ18: =((AW18-AX18)*0.05) -> 578.6875 | BA18: =IF(AY18>0,AY18*0.1,0) -> 800 | BB18: =(AW18-AX18+AY18+AZ18+BA18) -> 20952.438 | BC18: =(VLOOKUP(H18,INFRACASHshares2025,25,0)-BB18) -> 1847.5625 | BE18: =BB18 -> 20952.438 | BF18: 3000 | BH18: =(BE18-BF18)*0.05 -> 897.62188 | BI18: =IF(BG18>0,BG18*0.1,0) -> 0 | BJ18: =(BE18-BF18+BG18+BH18+BI18) -> 18850.059 | BK18: =(VLOOKUP(H18,INFRACASHshares2025,25,0)-BJ18) -> 3949.9406 | BM18: =BJ18 -> 18850.059 | BN18: 3500 | BP18: =(BM18-BN18)*0.05 -> 767.50297 | BS18: =(BM18-BN18+BO18+BP18+BQ18+BR18) -> 16117.562 | BV18: =BS18 -> 16117.562 | BW18: 2500 | BY18: =(BV18-BW18)*0.05 -> 680.87812 | CB18: =(BV18-BW18+BX18+BY18+BZ18) -> 14298.44 | CE18: =CB18 -> 14298.44 | CF18: 3000 | CH18: 1250.8023 | CI18: =(CE18-CF18)*0.05 -> 564.92202 | CJ18: =IF((CG18+CH18)>0,((CG18+CH18)*0.1),0) -> 125.08023 | CL18: =(CE18-CF18+CG18+CI18+CJ18) -> 11988.443 | CO18: =CL18 -> 11988.443 | CP18: 1625 | CR18: =((CO18-CP18)*0.05) -> 518.17214 | CS18: =IF(CQ18>0,CQ18*0.1,0) -> 0 | CU18: =(CO18-CP18+CQ18+CR18+CS18) -> 10881.615 | CX18: =CU18 -> 10881.615 | DA18: =((CX18-CY19)*0.05) -> 544.08074 | DC18: =(CX18-CY18+CZ18+DA18+DB18) -> 11425.696 | DD18: =(VLOOKUP(H18,INFRACASHshares2025,25,0)-DC18) -> 11374.304
B19: Saving | C19: Loan Application | D19: Loan Repayment | E19: Fines/Penalties | G19: 14 | H19: Michael | L19: =IF(J19>0,(I19-J19)*0.05,0) -> 0 | M19: =IF(K19>0,K19*0.1,0) -> 0 | N19: =I19-J19+K19+L19+M19 -> 0 | O19: =(VLOOKUP(H19,INFRACASHshares2025,25,0)-N19) -> 146400 | Q19: =N19 -> 0 | T19: =IF(R19>0,(Q19-R19)*0.05,0) -> 0 | U19: =IF(S19>0,S19*0.1,0) -> 0 | V19: =(Q19-R19+S19+T19+U19) -> 0 | W19: =(VLOOKUP(H19,INFRACASHshares2025,25,0)-V19) -> 146400 | Y19: =V19 -> 0 | AB19: =IF(Z19>0,(Y19-Z19)*0.05,0) -> 0 | AC19: =IF(AA19>0,AA19*0.1,0) -> 0 | AD19: =(Y19-Z19+AA19+AB19+AC19) -> 0 | AE19: =(VLOOKUP(H19,INFRACASHshares2025,25,0)-AD19) -> 146400 | AG19: =AD19 -> 0 | AJ19: =((AG19-AH19)*0.05) -> 0 | AK19: =IF(AI19>0,AI19*0.1,0) -> 0 | AL19: =(AG19-AH19+AI19+AJ19+AK19) -> 0 | AM19: =(VLOOKUP(H19,INFRACASHshares2025,25,0)-AL19) -> 146400 | AO19: =AL19 -> 0 | AR19: =((AO19-AP19)*0.05) -> 0 | AS19: =IF(AQ19>0,AQ19*0.1,0) -> 0 | AT19: =(AO19-AP19+AQ19+AR19+AS19) -> 0 | AU19: =(VLOOKUP(H19,INFRACASHshares2025,25,0)-AT19) -> 146400 | AW19: =AT19 -> 0 | AY19: 15000 | AZ19: =((AW19-AX19)*0.05) -> 0 | BA19: =IF(AY19>0,AY19*0.1,0) -> 1500 | BB19: =(AW19-AX19+AY19+AZ19+BA19) -> 16500 | BC19: =(VLOOKUP(H19,INFRACASHshares2025,25,0)-BB19) -> 129900 | BE19: =BB19 -> 16500 | BF19: 5000 | BH19: =(BE19-BF19)*0.05 -> 575 | BI19: =IF(BG19>0,BG19*0.1,0) -> 0 | BJ19: =(BE19-BF19+BG19+BH19+BI19) -> 12075 | BK19: =(VLOOKUP(H19,INFRACASHshares2025,25,0)-BJ19) -> 134325 | BM19: =BJ19 -> 12075 | BN19: 6075 | BP19: =(BM19-BN19)*0.05 -> 300 | BQ19: =IF(BO19>0,BO19*0.1,0) -> 0 | BS19: =(BM19-BN19+BO19+BP19+BQ19+BR19) -> 6300 | BT19: =(VLOOKUP(H19,INFRACASHshares2025,25,0)-BS19) -> 140100 | BV19: =BS19 -> 6300 | BW19: 6400 | BY19: =(BV19-BW19)*0.05 -> -5 | BZ19: =IF(BX19>0,BX19*0.1,0) -> 0 | CB19: =(BV19-BW19+BX19+BY19+BZ19) -> -105 | CC19: =(VLOOKUP(H19,INFRACASHshares2025,25,0)-CB19) -> 146505 | CE19: =CB19 -> -105 | CH19: 8031.4677 | CI19: =(CE19-CF19)*0.05 -> -5.25 | CJ19: =IF((CG19+CH19)>0,((CG19+CH19)*0.1),0) -> 803.14677 | CL19: =(CE19-CF19+CG19+CI19+CJ19) -> 692.89677 | CM19: =(VLOOKUP(H19,INFRACASHshares2025,25,0)-CL19) -> 145707.1 | CO19: =CL19 -> 692.89677 | CP19: 803.15 | CR19: =((CO19-CP19)*0.05) -> -5.5126614 | CS19: =IF(CQ19>0,CQ19*0.1,0) -> 0 | CU19: =(CO19-CP19+CQ19+CR19+CS19) -> -115.76589 | CV19: =(VLOOKUP(H19,INFRACASHshares2025,25,0)-CU19) -> 146515.77 | CX19: =CU19 -> -115.76589 | DA19: =((CX19-CY20)*0.05) -> -5.7882945 | DB19: =IF(CZ19>0,CZ19*0.1,0) -> 0 | DC19: =(CX19-CY19+CZ19+DA19+DB19) -> -121.55418 | DD19: =(VLOOKUP(H19,INFRACASHshares2025,25,0)-DC19) -> 146521.55
B20: Saving | C20: Loan Application | D20: Loan Repayment | E20: Fines/Penalties | G20: 15 | H20: Millie | L20: =IF(J20>0,(I20-J20)*0.05,0) -> 0 | M20: =IF(K20>0,K20*0.1,0) -> 0 | N20: =I20-J20+K20+L20+M20 -> 0 | O20: =(VLOOKUP(H20,INFRACASHshares2025,25,0)-N20) -> 10800 | Q20: =N20 -> 0 | T20: =IF(R20>0,(Q20-R20)*0.05,0) -> 0 | U20: =IF(S20>0,S20*0.1,0) -> 0 | V20: =(Q20-R20+S20+T20+U20) -> 0 | W20: =(VLOOKUP(H20,INFRACASHshares2025,25,0)-V20) -> 10800 | Y20: =V20 -> 0 | AA20: 10000 | AB20: =IF(Z20>0,(Y20-Z20)*0.05,0) -> 0 | AC20: =IF(AA20>0,AA20*0.1,0) -> 1000 | AD20: =(Y20-Z20+AA20+AB20+AC20) -> 11000 | AE20: =(VLOOKUP(H20,INFRACASHshares2025,25,0)-AD20) -> -200 | AG20: =AD20 -> 11000 | AH20: 3000 | AJ20: =((AG20-AH20)*0.05) -> 400 | AK20: =IF(AI20>0,AI20*0.1,0) -> 0 | AL20: =(AG20-AH20+AI20+AJ20+AK20) -> 8400 | AM20: =(VLOOKUP(H20,INFRACASHshares2025,25,0)-AL20) -> 2400 | AO20: =AL20 -> 8400 | AP20: 3000 | AR20: =((AO20-AP20)*0.05) -> 270 | AS20: =IF(AQ20>0,AQ20*0.1,0) -> 0 | AT20: =(AO20-AP20+AQ20+AR20+AS20) -> 5670 | AU20: =(VLOOKUP(H20,INFRACASHshares2025,25,0)-AT20) -> 5130 | AW20: =AT20 -> 5670 | AX20: 2500 | AZ20: =((AW20-AX20)*0.05) -> 158.5 | BA20: =IF(AY20>0,AY20*0.1,0) -> 0 | BB20: =(AW20-AX20+AY20+AZ20+BA20) -> 3328.5 | BC20: =(VLOOKUP(H20,INFRACASHshares2025,25,0)-BB20) -> 7471.5 | BE20: =BB20 -> 3328.5 | BF20: 3329 | BH20: =(BE20-BF20)*0.05 -> -0.025 | BI20: =IF(BG20>0,BG20*0.1,0) -> 0 | BJ20: =(BE20-BF20+BG20+BH20+BI20) -> -0.525 | BK20: =(VLOOKUP(H20,INFRACASHshares2025,25,0)-BJ20) -> 10800.525 | BM20: =BJ20 -> -0.525 | BO20: 10000 | BP20: =(BM20-BN20)*0.05 -> -0.02625 | BQ20: =IF(BO20>0,BO20*0.1,0) -> 1000 | BS20: =(BM20-BN20+BO20+BP20+BQ20+BR20) -> 10999.449 | BT20: =(VLOOKUP(H20,INFRACASHshares2025,25,0)-BS20) -> -199.44875 | BV20: =BS20 -> 10999.449 | BW20: 2500 | BY20: =(BV20-BW20)*0.05 -> 424.97244 | BZ20: =IF(BX20>0,BX20*0.1,0) -> 0 | CB20: =(BV20-BW20+BX20+BY20+BZ20) -> 8924.4212 | CC20: =(VLOOKUP(H20,INFRACASHshares2025,25,0)-CB20) -> 1875.5788 | CE20: =CB20 -> 8924.4212 | CF20: 2500 | CH20: 592.48532 | CI20: =(CE20-CF20)*0.05 -> 321.22106 | CJ20: =IF((CG20+CH20)>0,((CG20+CH20)*0.1),0) -> 59.248532 | CL20: =(CE20-CF20+CG20+CI20+CJ20) -> 6804.8908 | CM20: =(VLOOKUP(H20,INFRACASHshares2025,25,0)-CL20) -> 3995.1092 | CO20: =CL20 -> 6804.8908 | CP20: 2108 | CR20: =((CO20-CP20)*0.05) -> 234.84454 | CS20: =IF(CQ20>0,CQ20*0.1,0) -> 0 | CU20: =(CO20-CP20+CQ20+CR20+CS20) -> 4931.7353 | CV20: =(VLOOKUP(H20,INFRACASHshares2025,25,0)-CU20) -> 5868.2647 | CX20: =CU20 -> 4931.7353 | DA20: =((CX20-CY21)*0.05) -> 246.58677 | DB20: =IF(CZ20>0,CZ20*0.1,0) -> 0 | DC20: =(CX20-CY20+CZ20+DA20+DB20) -> 5178.3221 | DD20: =(VLOOKUP(H20,INFRACASHshares2025,25,0)-DC20) -> 5621.6779
B21: Saving | C21: Loan Application | D21: Loan Repayment | E21: Fines/Penalties | G21: 16 | H21: Mukuma | L21: =IF(J21>0,(I21-J21)*0.05,0) -> 0 | M21: =IF(K21>0,K21*0.1,0) -> 0 | N21: =I21-J21+K21+L21+M21 -> 0 | O21: =(VLOOKUP(H21,INFRACASHshares2025,25,0)-N21) -> 75600 | Q21: =N21 -> 0 | T21: =IF(R21>0,(Q21-R21)*0.05,0) -> 0 | U21: =IF(S21>0,S21*0.1,0) -> 0 | V21: =(Q21-R21+S21+T21+U21) -> 0 | W21: =(VLOOKUP(H21,INFRACASHshares2025,25,0)-V21) -> 75600 | Y21: =V21 -> 0 | AA21: 3000 | AB21: =IF(Z21>0,(Y21-Z21)*0.05,0) -> 0 | AC21: =IF(AA21>0,AA21*0.1,0) -> 300 | AD21: =(Y21-Z21+AA21+AB21+AC21) -> 3300 | AE21: =(VLOOKUP(H21,INFRACASHshares2025,25,0)-AD21) -> 72300 | AG21: =AD21 -> 3300 | AH21: 2000 | AJ21: =((AG21-AH21)*0.05) -> 65 | AK21: =IF(AI21>0,AI21*0.1,0) -> 0 | AL21: =(AG21-AH21+AI21+AJ21+AK21) -> 1365 | AM21: =(VLOOKUP(H21,INFRACASHshares2025,25,0)-AL21) -> 74235 | AO21: =AL21 -> 1365 | AP21: 1365 | AR21: =((AO21-AP21)*0.05) -> 0 | AS21: =IF(AQ21>0,AQ21*0.1,0) -> 0 | AT21: =(AO21-AP21+AQ21+AR21+AS21) -> 0 | AU21: =(VLOOKUP(H21,INFRACASHshares2025,25,0)-AT21) -> 75600 | AW21: =AT21 -> 0 | AY21: 10000 | AZ21: =((AW21-AX21)*0.05) -> 0 | BA21: =IF(AY21>0,AY21*0.1,0) -> 1000 | BB21: =(AW21-AX21+AY21+AZ21+BA21) -> 11000 | BC21: =(VLOOKUP(H21,INFRACASHshares2025,25,0)-BB21) -> 64600 | BE21: =BB21 -> 11000 | BF21: 2000 | BH21: =(BE21-BF21)*0.05 -> 450 | BI21: =IF(BG21>0,BG21*0.1,0) -> 0 | BJ21: =(BE21-BF21+BG21+BH21+BI21) -> 9450 | BK21: =(VLOOKUP(H21,INFRACASHshares2025,25,0)-BJ21) -> 66150 | BM21: =BJ21 -> 9450 | BN21: 2400 | BP21: =(BM21-BN21)*0.05 -> 352.5 | BQ21: =IF(BO21>0,BO21*0.1,0) -> 0 | BS21: =(BM21-BN21+BO21+BP21+BQ21+BR21) -> 7402.5 | BT21: =(VLOOKUP(H21,INFRACASHshares2025,25,0)-BS21) -> 68197.5 | BV21: =BS21 -> 7402.5 | BW21: 2400 | BY21: =(BV21-BW21)*0.05 -> 250.125 | BZ21: =IF(BX21>0,BX21*0.1,0) -> 0 | CB21: =(BV21-BW21+BX21+BY21+BZ21) -> 5252.625 | CC21: =(VLOOKUP(H21,INFRACASHshares2025,25,0)-CB21) -> 70347.375 | CE21: =CB21 -> 5252.625 | CF21: 2400 | CH21: 4147.3973 | CI21: =(CE21-CF21)*0.05 -> 142.63125 | CJ21: =IF((CG21+CH21)>0,((CG21+CH21)*0.1),0) -> 414.73973 | CL21: =(CE21-CF21+CG21+CI21+CJ21) -> 3409.996 | CM21: =(VLOOKUP(H21,INFRACASHshares2025,25,0)-CL21) -> 72190.004 | CO21: =CL21 -> 3409.996 | CP21: 2500 | CR21: =((CO21-CP21)*0.05) -> 45.499799 | CS21: =IF(CQ21>0,CQ21*0.1,0) -> 0 | CU21: =(CO21-CP21+CQ21+CR21+CS21) -> 955.49577 | CV21: =(VLOOKUP(H21,INFRACASHshares2025,25,0)-CU21) -> 74644.504 | CX21: =CU21 -> 955.49577 | DA21: =((CX21-CY22)*0.05) -> 47.774789 | DB21: =IF(CZ21>0,CZ21*0.1,0) -> 0 | DC21: =(CX21-CY21+CZ21+DA21+DB21) -> 1003.2706 | DD21: =(VLOOKUP(H21,INFRACASHshares2025,25,0)-DC21) -> 74596.729
B22: Saving | C22: Loan Application | D22: Loan Repayment | E22: Fines/Penalties | G22: 17 | H22: Mumba | L22: =IF(J22>0,(I22-J22)*0.05,0) -> 0 | M22: =IF(K22>0,K22*0.1,0) -> 0 | N22: =I22-J22+K22+L22+M22 -> 0 | O22: =(VLOOKUP(H22,INFRACASHshares2025,25,0)-N22) -> 75600 | Q22: =N22 -> 0 | T22: =IF(R22>0,(Q22-R22)*0.05,0) -> 0 | U22: =IF(S22>0,S22*0.1,0) -> 0 | V22: =(Q22-R22+S22+T22+U22) -> 0 | W22: =(VLOOKUP(H22,INFRACASHshares2025,25,0)-V22) -> 75600 | Y22: =V22 -> 0 | AB22: =IF(Z22>0,(Y22-Z22)*0.05,0) -> 0 | AC22: =IF(AA22>0,AA22*0.1,0) -> 0 | AD22: =(Y22-Z22+AA22+AB22+AC22) -> 0 | AE22: =(VLOOKUP(H22,INFRACASHshares2025,25,0)-AD22) -> 75600 | AG22: =AD22 -> 0 | AJ22: =((AG22-AH22)*0.05) -> 0 | AK22: =IF(AI22>0,AI22*0.1,0) -> 0 | AL22: =(AG22-AH22+AI22+AJ22+AK22) -> 0 | AM22: =(VLOOKUP(H22,INFRACASHshares2025,25,0)-AL22) -> 75600 | AO22: =AL22 -> 0 | AQ22: 10000 | AR22: =((AO22-AP22)*0.05) -> 0 | AS22: =IF(AQ22>0,AQ22*0.1,0) -> 1000 | AT22: =(AO22-AP22+AQ22+AR22+AS22) -> 11000 | AU22: =(VLOOKUP(H22,INFRACASHshares2025,25,0)-AT22) -> 64600 | AW22: =AT22 -> 11000 | AX22: 1000 | AZ22: =((AW22-AX22)*0.05) -> 500 | BA22: =IF(AY22>0,AY22*0.1,0) -> 0 | BB22: =(AW22-AX22+AY22+AZ22+BA22) -> 10500 | BC22: =(VLOOKUP(H22,INFRACASHshares2025,25,0)-BB22) -> 65100 | BE22: =BB22 -> 10500 | BF22: 5500 | BH22: =(BE22-BF22)*0.05 -> 250 | BI22: =IF(BG22>0,BG22*0.1,0) -> 0 | BJ22: =(BE22-BF22+BG22+BH22+BI22) -> 5250 | BK22: =(VLOOKUP(H22,INFRACASHshares2025,25,0)-BJ22) -> 70350 | BM22: =BJ22 -> 5250 | BN22: 5250 | BP22: =(BM22-BN22)*0.05 -> 0 | BQ22: =IF(BO22>0,BO22*0.1,0) -> 0 | BS22: =(BM22-BN22+BO22+BP22+BQ22+BR22) -> 0 | BT22: =(VLOOKUP(H22,INFRACASHshares2025,25,0)-BS22) -> 75600 | BV22: =BS22 -> 0 | BY22: =(BV22-BW22)*0.05 -> 0 | BZ22: =IF(BX22>0,BX22*0.1,0) -> 0 | CB22: =(BV22-BW22+BX22+BY22+BZ22) -> 0 | CC22: =(VLOOKUP(H22,INFRACASHshares2025,25,0)-CB22) -> 75600 | CE22: =CB22 -> 0 | CH22: 4147.3973 | CI22: =(CE22-CF22)*0.05 -> 0 | CJ22: =IF((CG22+CH22)>0,((CG22+CH22)*0.1),0) -> 414.73973 | CL22: =(CE22-CF22+CG22+CI22+CJ22) -> 414.73973 | CM22: =(VLOOKUP(H22,INFRACASHshares2025,25,0)-CL22) -> 75185.26 | CO22: =CL22 -> 414.73973 | CP22: 414.74 | CR22: =((CO22-CP22)*0.05) -> -1.369863e-05 | CS22: =IF(CQ22>0,CQ22*0.1,0) -> 0 | CU22: =(CO22-CP22+CQ22+CR22+CS22) -> -0.00028767123 | CV22: =(VLOOKUP(H22,INFRACASHshares2025,25,0)-CU22) -> 75600 | CX22: =CU22 -> -0.00028767123 | DA22: =((CX22-CY23)*0.05) -> -1.4383562e-05 | DB22: =IF(CZ22>0,CZ22*0.1,0) -> 0 | DC22: =(CX22-CY22+CZ22+DA22+DB22) -> -0.00030205479 | DD22: =(VLOOKUP(H22,INFRACASHshares2025,25,0)-DC22) -> 75600
G23: 18 | H23: Mumbi | L23: =IF(J23>0,(I23-J23)*0.05,0) -> 0 | M23: =IF(K23>0,K23*0.1,0) -> 0 | N23: =I23-J23+K23+L23+M23 -> 0 | O23: =(VLOOKUP(H23,INFRACASHshares2025,25,0)-N23) -> 81000 | Q23: =N23 -> 0 | S23: 3000 | T23: =IF(R23>0,(Q23-R23)*0.05,0) -> 0 | U23: =IF(S23>0,S23*0.1,0) -> 300 | V23: =(Q23-R23+S23+T23+U23) -> 3300 | W23: =(VLOOKUP(H23,INFRACASHshares2025,25,0)-V23) -> 77700 | Y23: =V23 -> 3300 | Z23: 200 | AA23: 3000 | AB23: =IF(Z23>0,(Y23-Z23)*0.05,0) -> 155 | AC23: =IF(AA23>0,AA23*0.1,0) -> 300 | AD23: =(Y23-Z23+AA23+AB23+AC23) -> 6555 | AE23: =(VLOOKUP(H23,INFRACASHshares2025,25,0)-AD23) -> 74445 | AG23: =AD23 -> 6555 | AJ23: =((AG23-AH23)*0.05) -> 327.75 | AK23: =IF(AI23>0,AI23*0.1,0) -> 0 | AL23: =(AG23-AH23+AI23+AJ23+AK23) -> 6882.75 | AM23: =(VLOOKUP(H23,INFRACASHshares2025,25,0)-AL23) -> 74117.25 | AO23: =AL23 -> 6882.75 | AP23: 1000 | AR23: =((AO23-AP23)*0.05) -> 294.1375 | AS23: =IF(AQ23>0,AQ23*0.1,0) -> 0 | AT23: =(AO23-AP23+AQ23+AR23+AS23) -> 6176.8875 | AU23: =(VLOOKUP(H23,INFRACASHshares2025,25,0)-AT23) -> 74823.113 | AW23: =AT23 -> 6176.8875 | AX23: 1000 | AZ23: =((AW23-AX23)*0.05) -> 258.84438 | BA23: =IF(AY23>0,AY23*0.1,0) -> 0 | BB23: =(AW23-AX23+AY23+AZ23+BA23) -> 5435.7319 | BC23: =(VLOOKUP(H23,INFRACASHshares2025,25,0)-BB23) -> 75564.268 | BE23: =BB23 -> 5435.7319 | BG23: 5000 | BH23: =(BE23-BF23)*0.05 -> 271.78659 | BI23: =IF(BG23>0,BG23*0.1,0) -> 500 | BJ23: =(BE23-BF23+BG23+BH23+BI23) -> 11207.518 | BK23: =(VLOOKUP(H23,INFRACASHshares2025,25,0)-BJ23) -> 69792.482 | BM23: =BJ23 -> 11207.518 | BP23: =(BM23-BN23)*0.05 -> 560.37592 | BQ23: =IF(BO23>0,BO23*0.1,0) -> 0 | BS23: =(BM23-BN23+BO23+BP23+BQ23+BR23) -> 11767.894 | BT23: =(VLOOKUP(H23,INFRACASHshares2025,25,0)-BS23) -> 69232.106 | BV23: =BS23 -> 11767.894 | BW23: 300 | BY23: =(BV23-BW23)*0.05 -> 573.39472 | BZ23: =IF(BX23>0,BX23*0.1,0) -> 0 | CB23: =(BV23-BW23+BX23+BY23+BZ23) -> 12041.289 | CC23: =(VLOOKUP(H23,INFRACASHshares2025,25,0)-CB23) -> 68958.711 | CE23: =CB23 -> 12041.289 | CF23: 4000 | CH23: 4443.6399 | CI23: =(CE23-CF23)*0.05 -> 402.06446 | CJ23: =IF((CG23+CH23)>0,((CG23+CH23)*0.1),0) -> 444.36399 | CL23: =(CE23-CF23+CG23+CI23+CJ23) -> 8887.7176 | CM23: =(VLOOKUP(H23,INFRACASHshares2025,25,0)-CL23) -> 72112.282 | CO23: =CL23 -> 8887.7176 | CP23: 3000 | CR23: =((CO23-CP23)*0.05) -> 294.38588 | CS23: =IF(CQ23>0,CQ23*0.1,0) -> 0 | CU23: =(CO23-CP23+CQ23+CR23+CS23) -> 6182.1034 | CV23: =(VLOOKUP(H23,INFRACASHshares2025,25,0)-CU23) -> 74817.897 | CX23: =CU23 -> 6182.1034 | DA23: =((CX23-CY25)*0.05) -> 309.10517 | DB23: =IF(CZ23>0,CZ23*0.1,0) -> 0 | DC23: =(CX23-CY23+CZ23+DA23+DB23) -> 6491.2086 | DD23: =(VLOOKUP(H23,INFRACASHshares2025,25,0)-DC23) -> 74508.791
B24: Saving | C24: Loan Application | D24: Loan Repayment | E24: Fines/Penalties | G24: 19 | H24: Mwenya | O24: =(VLOOKUP(H24,INFRACASHshares2025,25,0)-N24) -> 101400 | Q24: =N24 -> 0 | T24: =IF(R24>0,(Q24-R24)*0.05,0) -> 0 | U24: =IF(S24>0,S24*0.1,0) -> 0 | V24: =(Q24-R24+S24+T24+U24) -> 0 | W24: =(VLOOKUP(H24,INFRACASHshares2025,25,0)-V24) -> 101400 | AD24: =(Y24-Z24+AA24+AB24+AC24) -> 0 | AJ24: =((AG24-AH24)*0.05) -> 0 | AR24: =((AO24-AP24)*0.05) -> 0 | AZ24: =((AW24-AX24)*0.05) -> 0 | BA24: =IF(AY24>0,AY24*0.1,0) -> 0 | BB24: =(AW24-AX24+AY24+AZ24+BA24) -> 0 | BC24: =(VLOOKUP(H24,INFRACASHshares2025,25,0)-BB24) -> 101400 | BE24: =BB24 -> 0 | BH24: =(BE24-BF24)*0.05 -> 0 | BI24: =IF(BG24>0,BG24*0.1,0) -> 0 | BJ24: =(BE24-BF24+BG24+BH24+BI24) -> 0 | BK24: =(VLOOKUP(H24,INFRACASHshares2025,25,0)-BJ24) -> 101400 | BM24: =BJ24 -> 0 | BP24: =(BM24-BN24)*0.05 -> 0 | BT24: =(VLOOKUP(H24,INFRACASHshares2025,25,0)-BS24) -> 101400 | BV24: =BS24 -> 0 | BX24: 15000 | CB24: =(BV24-BW24+BX24+BY24+BZ24) -> 15000 | CC24: =(VLOOKUP(H24,INFRACASHshares2025,25,0)-CB24) -> 86400 | CE24: =CB24 -> 15000 | CF24: 1000 | CH24: 5562.7789 | CI24: =(CE24-CF24)*0.05 -> 700 | CL24: =(CE24-CF24+CG24+CI24+CJ24) -> 14700 | CM24: =(VLOOKUP(H24,INFRACASHshares2025,25,0)-CL24) -> 86700 | CO24: =CL24 -> 14700 | CP24: 5556.28 | CU24: =(CO24-CP24+CQ24+CR24+CS24) -> 9143.72 | CV24: =(VLOOKUP(H24,INFRACASHshares2025,25,0)-CU24) -> 92256.28 | CX24: =CU24 -> 9143.72 | DB24: =IF(CZ24>0,CZ24*0.1,0) -> 0 | DC24: =(CX24-CY24+CZ24+DA24+DB24) -> 9143.72
B25: Saving | C25: Loan Application | D25: Loan Repayment | E25: Fines/Penalties | G25: 20 | H25: Nyanyiwe | L25: =IF(J25>0,(I25-J25)*0.05,0) -> 0 | M25: =IF(K25>0,K25*0.1,0) -> 0 | N25: =I25-J25+K25+L25+M25 -> 0 | O25: =(VLOOKUP(H25,INFRACASHshares2025,25,0)-N25) -> 75000 | Q25: =N25 -> 0 | T25: =IF(R25>0,(Q25-R25)*0.05,0) -> 0 | U25: =IF(S25>0,S25*0.1,0) -> 0 | V25: =(Q25-R25+S25+T25+U25) -> 0 | W25: =(VLOOKUP(H25,INFRACASHshares2025,25,0)-V25) -> 75000 | Y25: =V25 -> 0 | AB25: =IF(Z25>0,(Y25-Z25)*0.05,0) -> 0 | AC25: =IF(AA25>0,AA25*0.1,0) -> 0 | AD25: =(Y25-Z25+AA25+AB25+AC25) -> 0 | AE25: =(VLOOKUP(H25,INFRACASHshares2025,25,0)-AD25) -> 75000 | AG25: =AD25 -> 0 | AI25: 51300 | AJ25: =((AG25-AH25)*0.05) -> 0 | AK25: =IF(AI25>0,AI25*0.1,0) -> 5130 | AL25: =(AG25-AH25+AI25+AJ25+AK25) -> 56430 | AM25: =(VLOOKUP(H25,INFRACASHshares2025,25,0)-AL25) -> 18570 | AO25: =AL25 -> 56430 | AP25: 5000 | AR25: =((AO25-AP25)*0.05) -> 2571.5 | AS25: =IF(AQ25>0,AQ25*0.1,0) -> 0 | AT25: =(AO25-AP25+AQ25+AR25+AS25) -> 54001.5 | AU25: =(VLOOKUP(H25,INFRACASHshares2025,25,0)-AT25) -> 20998.5 | AW25: =AT25 -> 54001.5 | AX25: 4000 | AZ25: =((AW25-AX25)*0.05) -> 2500.075 | BA25: =IF(AY25>0,AY25*0.1,0) -> 0 | BB25: =(AW25-AX25+AY25+AZ25+BA25) -> 52501.575 | BC25: =(VLOOKUP(H25,INFRACASHshares2025,25,0)-BB25) -> 22498.425 | BE25: =BB25 -> 52501.575 | BF25: 5000 | BH25: =(BE25-BF25)*0.05 -> 2375.0788 | BI25: =IF(BG25>0,BG25*0.1,0) -> 0 | BJ25: =(BE25-BF25+BG25+BH25+BI25) -> 49876.654 | BK25: =(VLOOKUP(H25,INFRACASHshares2025,25,0)-BJ25) -> 25123.346 | BM25: =BJ25 -> 49876.654 | BN25: 13500 | BP25: =(BM25-BN25)*0.05 -> 1818.8327 | BQ25: =IF(BO25>0,BO25*0.1,0) -> 0 | BS25: =(BM25-BN25+BO25+BP25+BQ25+BR25) -> 38195.486 | BT25: =(VLOOKUP(H25,INFRACASHshares2025,25,0)-BS25) -> 36804.514 | BV25: =BS25 -> 38195.486 | BW25: 2000 | BY25: =IF(BW25>0,(BV25-BW25)*0.05,0) -> 1809.7743 | BZ25: =IF(BX25>0,BX25*0.1,0) -> 0 | CB25: =(BV25-BW25+BX25+BY25+BZ25) -> 38005.261 | CC25: =(VLOOKUP(H25,INFRACASHshares2025,25,0)-CB25) -> 36994.739 | CE25: =CB25 -> 38005.261 | CF25: 1000 | CH25: 4114.4814 | CI25: =(CE25-CF25)*0.05 -> 1850.263 | CJ25: =IF((CG25+CH25)>0,((CG25+CH25)*0.1),0) -> 411.44814 | CL25: =(CE25-CF25+CG25+CI25+CJ25) -> 39266.972 | CM25: =(VLOOKUP(H25,INFRACASHshares2025,25,0)-CL25) -> 35733.028 | CO25: =CL25 -> 39266.972 | CP25: 37412.45 | CR25: =((CO25-CP25)*0.05) -> 92.726097 | CS25: =IF(CQ25>0,CQ25*0.1,0) -> 0 | CU25: =(CO25-CP25+CQ25+CR25+CS25) -> 1947.248 | CV25: =(VLOOKUP(H25,INFRACASHshares2025,25,0)-CU25) -> 73052.752 | CX25: =CU25 -> 1947.248 | DA25: =((CX25-CY26)*0.05) -> 97.362402 | DB25: =IF(CZ25>0,CZ25*0.1,0) -> 0 | DC25: =(CX25-CY25+CZ25+DA25+DB25) -> 2044.6104 | DD25: =(VLOOKUP(H25,INFRACASHshares2025,25,0)-DC25) -> 72955.39
B26: Saving | C26: Loan Application | D26: Loan Repayment | E26: Fines/Penalties | G26: 21 | H26: Pamela | L26: =IF(J26>0,(I26-J26)*0.05,0) -> 0 | M26: =IF(K26>0,K26*0.1,0) -> 0 | N26: =I26-J26+K26+L26+M26 -> 0 | O26: =(VLOOKUP(H26,INFRACASHshares2025,25,0)-N26) -> 42600 | Q26: =N26 -> 0 | T26: =IF(R26>0,(Q26-R26)*0.05,0) -> 0 | U26: =IF(S26>0,S26*0.1,0) -> 0 | V26: =(Q26-R26+S26+T26+U26) -> 0 | W26: =(VLOOKUP(H26,INFRACASHshares2025,25,0)-V26) -> 42600 | Y26: =V26 -> 0 | AB26: =IF(Z26>0,(Y26-Z26)*0.05,0) -> 0 | AC26: =IF(AA26>0,AA26*0.1,0) -> 0 | AD26: =(Y26-Z26+AA26+AB26+AC26) -> 0 | AE26: =(VLOOKUP(H26,INFRACASHshares2025,25,0)-AD26) -> 42600 | AG26: =AD26 -> 0 | AJ26: =((AG26-AH26)*0.05) -> 0 | AK26: =IF(AI26>0,AI26*0.1,0) -> 0 | AL26: =(AG26-AH26+AI26+AJ26+AK26) -> 0 | AM26: =(VLOOKUP(H26,INFRACASHshares2025,25,0)-AL26) -> 42600 | AO26: =AL26 -> 0 | AQ26: 30000 | AR26: =((AO26-AP26)*0.05) -> 0 | AS26: =IF(AQ26>0,AQ26*0.1,0) -> 3000 | AT26: =(AO26-AP26+AQ26+AR26+AS26) -> 33000 | AU26: =(VLOOKUP(H26,INFRACASHshares2025,25,0)-AT26) -> 9600 | AW26: =AT26 -> 33000 | AX26: 4000 | AZ26: =((AW26-AX26)*0.05) -> 1450 | BA26: =IF(AY26>0,AY26*0.1,0) -> 0 | BB26: =(AW26-AX26+AY26+AZ26+BA26) -> 30450 | BC26: =(VLOOKUP(H26,INFRACASHshares2025,25,0)-BB26) -> 12150 | BE26: =BB26 -> 30450 | BF26: 3000 | BH26: =(BE26-BF26)*0.05 -> 1372.5 | BI26: =IF(BG26>0,BG26*0.1,0) -> 0 | BJ26: =(BE26-BF26+BG26+BH26+BI26) -> 28822.5 | BK26: =(VLOOKUP(H26,INFRACASHshares2025,25,0)-BJ26) -> 13777.5 | BM26: =BJ26 -> 28822.5 | BN26: 2000 | BP26: =(BM26-BN26)*0.05 -> 1341.125 | BQ26: =IF(BO26>0,BO26*0.1,0) -> 0 | BS26: =(BM26-BN26+BO26+BP26+BQ26+BR26) -> 28163.625 | BT26: =(VLOOKUP(H26,INFRACASHshares2025,25,0)-BS26) -> 14436.375 | BV26: =BS26 -> 28163.625 | BW26: 2000 | BY26: =IF(BW26>0,(BV26-BW26)*0.05,0) -> 1308.1813 | BZ26: =IF(BX26>0,BX26*0.1,0) -> 0 | CB26: =(BV26-BW26+BX26+BY26+BZ26) -> 27471.806 | CC26: =(VLOOKUP(H26,INFRACASHshares2025,25,0)-CB26) -> 15128.194 | CE26: =CB26 -> 27471.806 | CF26: 3000 | CH26: 2337.0254 | CI26: =(CE26-CF26)*0.05 -> 1223.5903 | CJ26: =IF((CG26+CH26)>0,((CG26+CH26)*0.1),0) -> 233.70254 | CL26: =(CE26-CF26+CG26+CI26+CJ26) -> 25929.099 | CM26: =(VLOOKUP(H26,INFRACASHshares2025,25,0)-CL26) -> 16670.901 | CO26: =CL26 -> 25929.099 | CP26: 8504.261 | CR26: =((CO26-CP26)*0.05) -> 871.24191 | CS26: =IF(CQ26>0,CQ26*0.1,0) -> 0 | CU26: =(CO26-CP26+CQ26+CR26+CS26) -> 18296.08 | CV26: =(VLOOKUP(H26,INFRACASHshares2025,25,0)-CU26) -> 24303.92 | CX26: =CU26 -> 18296.08 | DA26: =((CX26-CY27)*0.05) -> 914.804 | DB26: =IF(CZ26>0,CZ26*0.1,0) -> 0 | DC26: =(CX26-CY26+CZ26+DA26+DB26) -> 19210.884 | DD26: =(VLOOKUP(H26,INFRACASHshares2025,25,0)-DC26) -> 23389.116
B27: Saving | C27: Loan Application | D27: Loan Repayment | E27: Fines/Penalties | G27: 22 | H27: Schuller | L27: =IF(J27>0,(I27-J27)*0.05,0) -> 0 | M27: =IF(K27>0,K27*0.1,0) -> 0 | N27: =I27-J27+K27+L27+M27 -> 0 | O27: =(VLOOKUP(H27,INFRACASHshares2025,25,0)-N27) -> 96600 | Q27: =N27 -> 0 | T27: =IF(R27>0,(Q27-R27)*0.05,0) -> 0 | U27: =IF(S27>0,S27*0.1,0) -> 0 | V27: =(Q27-R27+S27+T27+U27) -> 0 | W27: =(VLOOKUP(H27,INFRACASHshares2025,25,0)-V27) -> 96600 | Y27: =V27 -> 0 | AB27: =IF(Z27>0,(Y27-Z27)*0.05,0) -> 0 | AC27: =IF(AA27>0,AA27*0.1,0) -> 0 | AD27: =(Y27-Z27+AA27+AB27+AC27) -> 0 | AE27: =(VLOOKUP(H27,INFRACASHshares2025,25,0)-AD27) -> 96600 | AG27: =AD27 -> 0 | AJ27: =((AG27-AH27)*0.05) -> 0 | AK27: =IF(AI27>0,AI27*0.1,0) -> 0 | AL27: =(AG27-AH27+AI27+AJ27+AK27) -> 0 | AM27: =(VLOOKUP(H27,INFRACASHshares2025,25,0)-AL27) -> 96600 | AO27: =AL27 -> 0 | AR27: =((AO27-AP27)*0.05) -> 0 | AS27: =IF(AQ27>0,AQ27*0.1,0) -> 0 | AT27: =(AO27-AP27+AQ27+AR27+AS27) -> 0 | AU27: =(VLOOKUP(H27,INFRACASHshares2025,25,0)-AT27) -> 96600 | AW27: =AT27 -> 0 | AZ27: =((AW27-AX27)*0.05) -> 0 | BA27: =IF(AY27>0,AY27*0.1,0) -> 0 | BB27: =(AW27-AX27+AY27+AZ27+BA27) -> 0 | BC27: =(VLOOKUP(H27,INFRACASHshares2025,25,0)-BB27) -> 96600 | BE27: =BB27 -> 0 | BH27: =(BE27-BF27)*0.05 -> 0 | BI27: =IF(BG27>0,BG27*0.1,0) -> 0 | BJ27: =(BE27-BF27+BG27+BH27+BI27) -> 0 | BK27: =(VLOOKUP(H27,INFRACASHshares2025,25,0)-BJ27) -> 96600 | BM27: =BJ27 -> 0 | BP27: =(BM27-BN27)*0.05 -> 0 | BQ27: =IF(BO27>0,BO27*0.1,0) -> 0 | BS27: =(BM27-BN27+BO27+BP27+BQ27+BR27) -> 0 | BT27: =(VLOOKUP(H27,INFRACASHshares2025,25,0)-BS27) -> 96600 | BV27: =BS27 -> 0 | BX27: 25000 | BY27: =IF(BW27>0,(BV27-BW27)*0.05,0) -> 0 | BZ27: =IF(BX27>0,BX27*0.1,0) -> 2500 | CB27: =(BV27-BW27+BX27+BY27+BZ27) -> 27500 | CC27: =(VLOOKUP(H27,INFRACASHshares2025,25,0)-CB27) -> 69100 | CE27: =CB27 -> 27500 | CF27: 1000 | CH27: 5299.4521 | CI27: =(CE27-CF27)*0.05 -> 1325 | CJ27: =IF((CG27+CH27)>0,((CG27+CH27)*0.1),0) -> 529.94521 | CL27: =(CE27-CF27+CG27+CI27+CJ27) -> 28354.945 | CM27: =(VLOOKUP(H27,INFRACASHshares2025,25,0)-CL27) -> 68245.055 | CO27: =CL27 -> 28354.945 | CP27: 1529.95 | CR27: =((CO27-CP27)*0.05) -> 1341.2498 | CS27: =IF(CQ27>0,CQ27*0.1,0) -> 0 | CU27: =(CO27-CP27+CQ27+CR27+CS27) -> 28166.245 | CV27: =(VLOOKUP(H27,INFRACASHshares2025,25,0)-CU27) -> 68433.755 | CX27: =CU27 -> 28166.245 | DA27: =((CX27-CY28)*0.05) -> 1408.3122 | DB27: =IF(CZ27>0,CZ27*0.1,0) -> 0 | DC27: =(CX27-CY27+CZ27+DA27+DB27) -> 29574.557 | DD27: =(VLOOKUP(H27,INFRACASHshares2025,25,0)-DC27) -> 67025.443
B28: Saving | C28: Loan Application | D28: Loan Repayment | E28: Fines/Penalties | G28: 23 | H28: Shubart | L28: =IF(J28>0,(I28-J28)*0.05,0) -> 0 | M28: =IF(K28>0,K28*0.1,0) -> 0 | N28: =I28-J28+K28+L28+M28 -> 0 | O28: =(VLOOKUP(H28,INFRACASHshares2025,25,0)-N28) -> 33000 | Q28: =N28 -> 0 | T28: =IF(R28>0,(Q28-R28)*0.05,0) -> 0 | U28: =IF(S28>0,S28*0.1,0) -> 0 | V28: =(Q28-R28+S28+T28+U28) -> 0 | W28: =(VLOOKUP(H28,INFRACASHshares2025,25,0)-V28) -> 33000 | Y28: =V28 -> 0 | AB28: =IF(Z28>0,(Y28-Z28)*0.05,0) -> 0 | AC28: =IF(AA28>0,AA28*0.1,0) -> 0 | AD28: =(Y28-Z28+AA28+AB28+AC28) -> 0 | AE28: =(VLOOKUP(H28,INFRACASHshares2025,25,0)-AD28) -> 33000 | AG28: =AD28 -> 0 | AJ28: =((AG28-AH28)*0.05) -> 0 | AK28: =IF(AI28>0,AI28*0.1,0) -> 0 | AL28: =(AG28-AH28+AI28+AJ28+AK28) -> 0 | AM28: =(VLOOKUP(H28,INFRACASHshares2025,25,0)-AL28) -> 33000 | AO28: =AL28 -> 0 | AQ28: 13265 | AR28: =((AO28-AP28)*0.05) -> 0 | AS28: =IF(AQ28>0,AQ28*0.1,0) -> 1326.5 | AT28: =(AO28-AP28+AQ28+AR28+AS28) -> 14591.5 | AU28: =(VLOOKUP(H28,INFRACASHshares2025,25,0)-AT28) -> 18408.5 | AW28: =AT28 -> 14591.5 | AX28: 200 | AZ28: =((AW28-AX28)*0.05) -> 719.575 | BA28: =IF(AY28>0,AY28*0.1,0) -> 0 | BB28: =(AW28-AX28+AY28+AZ28+BA28) -> 15111.075 | BC28: =(VLOOKUP(H28,INFRACASHshares2025,25,0)-BB28) -> 17888.925 | BE28: =BB28 -> 15111.075 | BF28: 1300 | BH28: =(BE28-BF28)*0.05 -> 690.55375 | BI28: =IF(BG28>0,BG28*0.1,0) -> 0 | BJ28: =(BE28-BF28+BG28+BH28+BI28) -> 14501.629 | BK28: =(VLOOKUP(H28,INFRACASHshares2025,25,0)-BJ28) -> 18498.371 | BM28: =BJ28 -> 14501.629 | BP28: =(BM28-BN28)*0.05 -> 725.08144 | BQ28: =IF(BO28>0,BO28*0.1,0) -> 0 | BS28: =(BM28-BN28+BO28+BP28+BQ28+BR28) -> 15226.71 | BT28: =(VLOOKUP(H28,INFRACASHshares2025,25,0)-BS28) -> 17773.29 | BV28: =BS28 -> 15226.71 | BW28: 800 | BY28: =IF(BW28>0,(BV28-BW28)*0.05,0) -> 721.33551 | BZ28: =IF(BX28>0,BX28*0.1,0) -> 0 | CB28: =(BV28-BW28+BX28+BY28+BZ28) -> 15148.046 | CC28: =(VLOOKUP(H28,INFRACASHshares2025,25,0)-CB28) -> 17851.954 | CE28: =CB28 -> 15148.046 | CF28: 1000 | CH28: 1810.3718 | CI28: =(CE28-CF28)*0.05 -> 707.40228 | CJ28: =IF((CG28+CH28)>0,((CG28+CH28)*0.1),0) -> 181.03718 | CL28: =(CE28-CF28+CG28+CI28+CJ28) -> 15036.485 | CM28: =(VLOOKUP(H28,INFRACASHshares2025,25,0)-CL28) -> 17963.515 | CO28: =CL28 -> 15036.485 | CP28: 0 | CR28: =((CO28-CP28)*0.05) -> 751.82426 | CS28: =IF(CQ28>0,CQ28*0.1,0) -> 0 | CU28: =(CO28-CP28+CQ28+CR28+CS28) -> 15788.309 | CV28: =(VLOOKUP(H28,INFRACASHshares2025,25,0)-CU28) -> 17211.691 | CX28: =CU28 -> 15788.309 | DA28: =((CX28-CY29)*0.05) -> 789.41547 | DB28: =IF(CZ28>0,CZ28*0.1,0) -> 0 | DC28: =(CX28-CY28+CZ28+DA28+DB28) -> 16577.725 | DD28: =(VLOOKUP(H28,INFRACASHshares2025,25,0)-DC28) -> 16422.275
B29: Saving | C29: Loan Application | D29: Loan Repayment | E29: Fines/Penalties | G29: 24 | H29: Solomon | L29: =IF(J29>0,(I29-J29)*0.05,0) -> 0 | M29: =IF(K29>0,K29*0.1,0) -> 0 | N29: =I29-J29+K29+L29+M29 -> 0 | O29: =(VLOOKUP(H29,INFRACASHshares2025,25,0)-N29) -> 28200 | Q29: =N29 -> 0 | T29: =IF(R29>0,(Q29-R29)*0.05,0) -> 0 | U29: =IF(S29>0,S29*0.1,0) -> 0 | V29: =(Q29-R29+S29+T29+U29) -> 0 | W29: =(VLOOKUP(H29,INFRACASHshares2025,25,0)-V29) -> 28200 | Y29: =V29 -> 0 | AB29: =IF(Z29>0,(Y29-Z29)*0.05,0) -> 0 | AC29: =IF(AA29>0,AA29*0.1,0) -> 0 | AD29: =(Y29-Z29+AA29+AB29+AC29) -> 0 | AE29: =(VLOOKUP(H29,INFRACASHshares2025,25,0)-AD29) -> 28200 | AG29: =AD29 -> 0 | AJ29: =((AG29-AH29)*0.05) -> 0 | AK29: =IF(AI29>0,AI29*0.1,0) -> 0 | AL29: =(AG29-AH29+AI29+AJ29+AK29) -> 0 | AM29: =(VLOOKUP(H29,INFRACASHshares2025,25,0)-AL29) -> 28200 | AO29: =AL29 -> 0 | AR29: =((AO29-AP29)*0.05) -> 0 | AS29: =IF(AQ29>0,AQ29*0.1,0) -> 0 | AT29: =(AO29-AP29+AQ29+AR29+AS29) -> 0 | AU29: =(VLOOKUP(H29,INFRACASHshares2025,25,0)-AT29) -> 28200 | AW29: =AT29 -> 0 | AZ29: =((AW29-AX29)*0.05) -> 0 | BA29: =IF(AY29>0,AY29*0.1,0) -> 0 | BB29: =(AW29-AX29+AY29+AZ29+BA29) -> 0 | BC29: =(VLOOKUP(H29,INFRACASHshares2025,25,0)-BB29) -> 28200 | BE29: =BB29 -> 0 | BH29: =(BE29-BF29)*0.05 -> 0 | BI29: =IF(BG29>0,BG29*0.1,0) -> 0 | BJ29: =(BE29-BF29+BG29+BH29+BI29) -> 0 | BK29: =(VLOOKUP(H29,INFRACASHshares2025,25,0)-BJ29) -> 28200 | BM29: =BJ29 -> 0 | BP29: =(BM29-BN29)*0.05 -> 0 | BQ29: =IF(BO29>0,BO29*0.1,0) -> 0 | BS29: =(BM29-BN29+BO29+BP29+BQ29+BR29) -> 0 | BT29: =(VLOOKUP(H29,INFRACASHshares2025,25,0)-BS29) -> 28200 | BV29: =BS29 -> 0 | BY29: =IF(BW29>0,(BV29-BW29)*0.05,0) -> 0 | BZ29: =IF(BX29>0,BX29*0.1,0) -> 0 | CB29: =(BV29-BW29+BX29+BY29+BZ29) -> 0 | CC29: =(VLOOKUP(H29,INFRACASHshares2025,25,0)-CB29) -> 28200 | CE29: =CB29 -> 0 | CF29: 0 | CG29: 200 | CH29: 15000 | CI29: =(CE29-CF29)*0.05 -> 0 | CJ29: =IF((CG29+CH29)>0,((CG29+CH29)*0.1),0) -> 1520 | CL29: =(CE29-CF29+CG29+CI29+CJ29) -> 1720 | CM29: =(VLOOKUP(H29,INFRACASHshares2025,25,0)-CL29) -> 26480 | CO29: =CL29 -> 1720 | CP29: =1720 -> 1720 | CR29: =((CO29-CP29)*0.05) -> 0 | CS29: =IF(CQ29>0,CQ29*0.1,0) -> 0 | CU29: =(CO29-CP29+CQ29+CR29+CS29) -> 0 | CV29: =(VLOOKUP(H29,INFRACASHshares2025,25,0)-CU29) -> 28200 | CX29: =CU29 -> 0 | DA29: =((CX29-CY30)*0.05) -> 0 | DB29: =IF(CZ29>0,CZ29*0.1,0) -> 0 | DC29: =(CX29-CY29+CZ29+DA29+DB29) -> 0 | DD29: =(VLOOKUP(H29,INFRACASHshares2025,25,0)-DC29) -> 28200
G30: 25 | H30: Tumelo | L30: =IF(J30>0,(I30-J30)*0.05,0) -> 0 | M30: =IF(K30>0,K30*0.1,0) -> 0 | N30: =I30-J30+K30+L30+M30 -> 0 | O30: =(VLOOKUP(H30,INFRACASHshares2025,25,0)-N30) -> 600 | Q30: =N30 -> 0 | T30: =IF(R30>0,(Q30-R30)*0.05,0) -> 0 | U30: =IF(S30>0,S30*0.1,0) -> 0 | V30: =(Q30-R30+S30+T30+U30) -> 0 | W30: =(VLOOKUP(H30,INFRACASHshares2025,25,0)-V30) -> 600 | Y30: =V30 -> 0 | AB30: =IF(Z30>0,(Y30-Z30)*0.05,0) -> 0 | AC30: =IF(AA30>0,AA30*0.1,0) -> 0 | AD30: =(Y30-Z30+AA30+AB30+AC30) -> 0 | AE30: =(VLOOKUP(H30,INFRACASHshares2025,25,0)-AD30) -> 600 | AG30: =AD30 -> 0 | AJ30: =IF(AH30>0,(AG30-AH30)*0.05,0) -> 0 | AK30: =IF(AI30>0,AI30*0.1,0) -> 0 | AL30: =(AG30-AH30+AI30+AJ30+AK30) -> 0 | AM30: =(VLOOKUP(H30,INFRACASHshares2025,25,0)-AL30) -> 600 | AO30: =AL30 -> 0 | AR30: =((AO30-AP30)*0.05) -> 0 | AS30: =IF(AQ30>0,AQ30*0.1,0) -> 0 | AT30: =(AO30-AP30+AQ30+AR30+AS30) -> 0 | AU30: =(VLOOKUP(H30,INFRACASHshares2025,25,0)-AT30) -> 600 | AW30: =AT30 -> 0 | AZ30: =((AW30-AX30)*0.05) -> 0 | BA30: =IF(AY30>0,AY30*0.1,0) -> 0 | BB30: =(AW30-AX30+AY30+AZ30+BA30) -> 0 | BC30: =(VLOOKUP(H30,INFRACASHshares2025,25,0)-BB30) -> 600 | BE30: =BB30 -> 0 | BH30: =(BE30-BF30)*0.05 -> 0 | BI30: =IF(BG30>0,BG30*0.1,0) -> 0 | BJ30: =(BE30-BF30+BG30+BH30+BI30) -> 0 | BK30: =(VLOOKUP(H30,INFRACASHshares2025,25,0)-BJ30) -> 600 | BM30: =BJ30 -> 0 | BP30: =(BM30-BN30)*0.05 -> 0 | BQ30: =IF(BO30>0,BO30*0.1,0) -> 0 | BS30: =(BM30-BN30+BO30+BP30+BQ30+BR30) -> 0 | BT30: =(VLOOKUP(H30,INFRACASHshares2025,25,0)-BS30) -> 600 | BV30: =BS30 -> 0 | BY30: =IF(BW30>0,(BV30-BW30)*0.05,0) -> 0 | BZ30: =IF(BX30>0,BX30*0.1,0) -> 0 | CB30: =(BV30-BW30+BX30+BY30+BZ30) -> 0 | CC30: =(VLOOKUP(H30,INFRACASHshares2025,25,0)-CB30) -> 600 | CE30: =CB30 -> 0 | CI30: =IF(CG30>0,(CF30-CG30)*0.05,0) -> 0 | CJ30: =IF((CG30+CH30)>0,((CG30+CH30)*0.1),0) -> 0 | CL30: =(CE30-CF30+CG30+CI30+CJ30) -> 0 | CM30: =(VLOOKUP(H30,INFRACASHshares2025,25,0)-CL30) -> 600 | CO30: =CL30 -> 0 | CR30: =((CO30-CP30)*0.05) -> 0 | CS30: =IF(CQ30>0,CQ30*0.1,0) -> 0 | CU30: =(CO30-CP30+CQ30+CR30+CS30) -> 0 | CV30: =(VLOOKUP(H30,INFRACASHshares2025,25,0)-CU30) -> 600 | CX30: =CU30 -> 0 | DB30: =IF(CZ30>0,CZ30*0.1,0) -> 0 | DC30: =(CX30-CY30+CZ30+DA30+DB30) -> 0 | DD30: =(VLOOKUP(H30,INFRACASHshares2025,25,0)-DC30) -> 600
I31: =SUM(I6:I30) -> 0 | K31: =SUM(K6:K30) -> 48100 | N31: =SUM(N6:N30) -> 51410 | Q31: =SUM(Q6:Q30) -> 51410 | R31: =SUM(R6:R30) -> 7941 | S31: =SUM(S6:S30) -> 68640 | V31: =SUM(V6:V30) -> 120296.45 | Y31: =SUM(Y6:Y30) -> 120296.45 | Z31: =SUM(Z6:Z30) -> 8550 | AA31: =SUM(AA6:AA30) -> 43650 | AD31: =SUM(AD6:AD30) -> 162817.57 | AG31: =SUM(AG6:AG30) -> 162817.57 | AH31: =SUM(AH6:AH30) -> 21000 | AI31: =SUM(AI6:AI30) -> 72300 | AL31: =SUM(AL6:AL30) -> 228438.45 | AO31: =SUM(AO6:AO30) -> 228438.45 | AP31: =SUM(AP6:AP30) -> 31565 | AQ31: =SUM(AQ6:AQ30) -> 177265 | AT31: =SUM(AT6:AT30) -> 401708.62 | AW31: =SUM(AW6:AW30) -> 401708.62 | AX31: =SUM(AX6:AX30) -> 40467.81 | AY31: =SUM(AY6:AY30) -> 60467.81 | BB31: =SUM(BB6:BB30) -> 445817.45 | BE31: =SUM(BE6:BE30) -> 445817.45 | BF31: =SUM(BF6:BF30) -> 46448.393 | BG31: =SUM(BG6:BG30) -> 77748.39 | BH31: =IF(BF31>0,(BE31-BF31)*0.05,0) -> 19968.453 | BI31: =IF(BG31>0,BG31*0.1,0) -> 7774.839 | BJ31: =SUM(BJ6:BJ30) -> 504860.73 | BM31: =SUM(BM6:BM30) -> 504860.73 | BN31: =SUM(BN6:BN30) -> 72725 | BO31: =SUM(BO6:BO30) -> 91025 | BS31: =SUM(BS6:BS30) -> 553870.02 | BV31: =SUM(BV6:BV30) -> 553870.02 | BW31: =SUM(BW6:BW30) -> 59990 | BX31: =SUM(BX6:BX30) -> 76090 | CB31: =SUM(CB6:CB30) -> 600773.02 | CE31: =SUM(CE6:CE30) -> 600773.02 | CF31: =SUM(CF6:CF30) -> 80180 | CG31: =SUM(CG6:CG30) -> 11200 | CH31: =SUM(CH6:CH30) -> 82280 | CL31: =SUM(CL6:CL30) -> 566614.4 | CO31: =SUM(CO6:CO30) -> 566614.4 | CP31: =SUM(CP6:CP30) -> 263433.12 | CQ31: =SUM(CQ6:CQ30) -> 0 | CU31: =SUM(CU6:CU30) -> 317883.15 | CX31: =SUM(CX6:CX30) -> 317883.15 | CY31: =SUM(CY8:CY30) -> 0 | CZ31: =SUM(CZ6:CZ30) -> 0 | DA31: =SUM(DA6:DA30) -> 15436.972 | DC31: =SUM(DC6:DC30) -> 333320.12
CH33: =CG12+CH31 -> 93280

Sheet Repayment Schedule
A1: NOVEMBER LOANS REPAYMENT SCHEDULE | F1: December | I1: January | L1: February | O1: March | R1: April | U1: May | X1: June | AA1: July | AD1: August | AG1: September | AJ1: October
A2: No | B2: FULL NAMES | C2: AMOUNT | D2: INTEREST % | E2: TOTAL DUE | F2: PAID | G2: REDUCING BALANCE | H2: REDUCING BALANCE PLUS 5% | I2: PAID | J2: REDUCING BALANCE | K2: REDUCING BALANCE PLUS 5% | L2: PAID | M2: REDUCING BALANCE | N2: REDUCING BALANCE PLUS 5% | O2: PAID | P2: REDUCING BALANCE | Q2: REDUCING BALANCE PLUS 5% | R2: PAID | S2: REDUCING BALANCE | T2: REDUCING BALANCE PLUS 5% | U2: PAID | V2: REDUCING BALANCE | W2: REDUCING BALANCE PLUS 5% | X2: PAID | Y2: REDUCING BALANCE | Z2: REDUCING BALANCE PLUS 5% | AA2: PAID | AB2: REDUCING BALANCE | AC2: REDUCING BALANCE PLUS 5% | AD2: PAID | AE2: REDUCING BALANCE | AF2: REDUCING BALANCE PLUS 5% | AG2: PAID | AH2: REDUCING BALANCE | AI2: REDUCING BALANCE PLUS 5% | AJ2: PAID | AK2: REDUCING BALANCE | AL2: REDUCING BALANCE PLUS 5%
B3: Abigail Mundia | C3: 20000 | D3: =C3*0.1 -> 2000 | E3: =C3+D3 -> 22000 | F3: 12000 | G3: =E3-F3 -> 10000 | H3: =G3+(0.05*G3) -> 10500 | I3: 5500 | J3: =H3-I3 -> 5000 | K3: =J3+(0.05*J3) -> 5250 | L3: 1250 | M3: =IF(L3>0,K3-L3,0) -> 4000 | N3: =M3+(0.05*M3) -> 4200 | O3: 1200 | P3: =IF(O3>0,N3-O3,0) -> 3000 | Q3: =P3+(0.05*P3) -> 3150 | R3: 3150 | S3: Closed | V3: =IF(U3>0,T3-U3,0) -> 0 | W3: =V3+(0.05*V3) -> 0 | Y3: =IF(X3>0,W3-X3,0) -> 0 | Z3: =Y3+(0.05*Y3) -> 0 | AB3: =Z3-AA3 -> 0 | AC3: =AB3+(0.05*AB3) -> 0 | AE3: =AC3-AD3 -> 0 | AF3: =AE3+(0.05*AE3) -> 0 | AH3: =AF3-AG3 -> 0 | AI3: =AH3 -> 0 | AK3: =AI3-AJ3 -> 0 | AL3: =AK3+(0.05*AK3) -> 0
B4: Kwibisa Kalumba | C4: 13000 | D4: =C4*0.1 -> 1300 | E4: =C4+D4 -> 14300 | F4: 1500 | G4: =E4-F4 -> 12800 | H4: =G4+(0.05*G4) -> 13440 | I4: 3800 | J4: =H4-I4 -> 9640 | K4: =J4+(0.05*J4) -> 10122 | L4: 3000 | M4: =IF(L4>0,K4-L4,0) -> 7122 | N4: =M4+(0.05*M4) -> 7478.1 | O4: 1500 | P4: =IF(O4>0,N4-O4,0) -> 5978.1 | Q4: =P4+(0.05*P4) -> 6277.005 | R4: 1500 | S4: =IF(R4>0,Q4-R4,0) -> 4777.005 | T4: =S4+(0.05*S4) -> 5015.8553 | U4: 1000 | V4: =IF(U4>0,T4-U4,0) -> 4015.8553 | W4: =V4+(0.05*V4) -> 4216.648 | X4: 4217 | Y4: Closed | AB4: =Z4-AA4 -> 0 | AC4: =AB4+(0.05*AB4) -> 0 | AE4: =AC4-AD4 -> 0 | AF4: =AE4+(0.05*AE4) -> 0 | AH4: =AF4-AG4 -> 0 | AI4: =AH4 -> 0 | AK4: =AI4-AJ4 -> 0 | AL4: =AK4+(0.05*AK4) -> 0
B5: Richard | C5: 4800 | D5: =C5*0.1 -> 480 | E5: =C5+D5 -> 5280 | F5: 1000 | G5: =E5-F5 -> 4280 | H5: =G5+(0.05*G5) -> 4494 | I5: 1400 | J5: =H5-I5 -> 3094 | K5: =J5+(0.05*J5) -> 3248.7 | L5: 1000 | M5: =IF(L5>0,K5-L5,0) -> 2248.7 | N5: =M5+(0.05*M5) -> 2361.135 | O5: 1000 | P5: =IF(O5>0,N5-O5,0) -> 1361.135 | Q5: =P5+(0.05*P5) -> 1429.1917 | R5: 500 | S5: =IF(R5>0,Q5-R5,0) -> 929.19175 | T5: =S5+(0.05*S5) -> 975.65134 | U5: 975.65 | V5: Closed | Y5: =IF(X5>0,W5-X5,0) -> 0 | Z5: =Y5+(0.05*Y5) -> 0 | AB5: =Z5-AA5 -> 0 | AC5: =AB5+(0.05*AB5) -> 0 | AE5: =AC5-AD5 -> 0 | AF5: =AE5+(0.05*AE5) -> 0 | AH5: =AF5-AG5 -> 0 | AI5: =AH5 -> 0 | AK5: =AI5-AJ5 -> 0 | AL5: =AK5+(0.05*AK5) -> 0
B6: Benson | C6: 15000 | D6: =C6*0.1 -> 1500 | E6: =C6+D6 -> 16500 | F6: 1000 | G6: =E6-F6 -> 15500 | H6: =G6+(0.05*G6) -> 16275 | I6: 1000 | J6: =H6-I6 -> 15275 | K6: =J6+(0.05*J6) -> 16038.75 | L6: 1300 | M6: =IF(L6>0,K6-L6,0) -> 14738.75 | N6: =M6+(0.05*M6) -> 15475.688 | O6: 3000 | P6: =IF(O6>0,N6-O6,0) -> 12475.688 | Q6: =P6+(0.05*P6) -> 13099.472 | R6: 1000 | S6: =IF(R6>0,Q6-R6,0) -> 12099.472 | T6: =S6+(0.05*S6) -> 12704.445 | U6: 2000 | V6: =IF(U6>0,T6-U6,0) -> 10704.445 | W6: =V6+(0.05*V6) -> 11239.668 | X6: 2000 | Y6: =IF(X6>0,W6-X6,0) -> 9239.6677 | Z6: =Y6+(0.05*Y6) -> 9701.6511 | AA6: 1000 | AB6: =IF(AA6>0,Z6-AA6,0) -> 8701.6511 | AC6: =AB6+(0.05*AB6) -> 9136.7337 | AD6: 800 | AE6: =IF(AD6>0,AC6-AD6,0) -> 8336.7337 | AF6: =AE6+(0.05*AE6) -> 8753.5704 | AH6: =AF6-AG6 -> 8753.5704 | AI6: =AH6 -> 8753.5704 | AK6: =AI6-AJ6 -> 8753.5704 | AL6: =AK6+(0.05*AK6) -> 9191.2489
B7: Keji | C7: 4800 | D7: =C7*0.1 -> 480 | E7: =C7+D7 -> 5280 | F7: 0 | G7: =E7-F7 -> 5280 | H7: =G7+(0.05*G7) -> 5544 | I7: 1760 | J7: =H7-I7 -> 3784 | K7: =J7+(0.05*J7) -> 3973.2 | L7: 2100 | M7: =IF(L7>0,K7-L7,0) -> 1873.2 | N7: =M7+(0.05*M7) -> 1966.86 | O7: 1966.86 | P7: Closed | S7: =IF(R7>0,Q7-R7,0) -> 0 | T7: =S7+(0.05*S7) -> 0 | V7: =IF(U7>0,T7-U7,0) -> 0 | W7: =V7+(0.05*V7) -> 0 | Y7: =IF(X7>0,W7-X7,0) -> 0 | Z7: =Y7+(0.05*Y7) -> 0 | AB7: =Z7-AA7 -> 0 | AC7: =AB7+(0.05*AB7) -> 0 | AE7: =AC7-AD7 -> 0 | AF7: =AE7+(0.05*AE7) -> 0 | AH7: =AF7-AG7 -> 0 | AI7: =AH7 -> 0 | AK7: =AI7-AJ7 -> 0 | AL7: =AK7+(0.05*AK7) -> 0
C8: =SUM(C3:C7) -> 57600 | D8: =SUM(D3:D7) -> 5760 | E8: =SUM(E3:E7) -> 63360 | F8: =SUM(F3:F7) -> 15500 | G8: =SUM(G3:G7) -> 47860 | H8: =SUM(H3:H7) -> 50253 | I8: =SUM(I3:I7) -> 13460 | J8: =SUM(J3:J7) -> 36793 | ... AL8: =SUM(AL3:AL7) -> 9191.2489
A11: DECEMBER LOANS REPAYMENT SCHEDULE | F11: January | I11: February | L11: March | O11: April | R11: May | U11: June | X11: July | AA11: August | AD11: September | AG11: October
A12: No | B12: FULL NAMES | C12: AMOUNT | D12: INTEREST % | E12: TOTAL DUE | F12: PAID | G12: REDUCING BALANCE | H12: REDUCING BALANCE PLUS 5% | I12: PAID | J12: REDUCING BALANCE | K12: REDUCING BALANCE PLUS 5% | L12: PAID | M12: REDUCING BALANCE | N12: REDUCING BALANCE PLUS 5% | O12: PAID | P12: REDUCING BALANCE | Q12: REDUCING BALANCE PLUS 5% | R12: PAID | S12: REDUCING BALANCE | T12: REDUCING BALANCE PLUS 5% | U12: PAID | V12: REDUCING BALANCE | W12: REDUCING BALANCE PLUS 5% | X12: PAID | Y12: REDUCING BALANCE | Z12: REDUCING BALANCE PLUS 5% | AA12: PAID | AB12: REDUCING BALANCE | AC12: REDUCING BALANCE PLUS 5% | AD12: PAID | AE12: REDUCING BALANCE | AF12: REDUCING BALANCE PLUS 5% | AG12: PAID | AH12: REDUCING BALANCE | AI12: REDUCING BALANCE PLUS 5%
A13: 1 | B13: Keji 2 | C13: 4200 | D13: =0.1*C13 -> 420 | E13: =D13+C13 -> 4620 | F13: 1540 | G13: =E13-F13 -> 3080 | H13: =G13+(0.05*G13) -> 3234 | I13: 1700 | J13: =IF(I13>0,H13-I13,0) -> 1534 | K13: =J13+(0.05*J13) -> 1610.7 | L13: 1610.7 | M13: Closed | P13: =IF(O13>0,N13-O13,0) -> 0 | Q13: =P13+(0.05*P13) -> 0 | S13: =IF(R13>0,Q13-R13,0) -> 0 | T13: =S13+(0.05*S13) -> 0 | V13: =IF(U13>0,T13-U13,0) -> 0 | W13: =V13+(0.05*V13) -> 0 | Y13: =IF(X13>0,W13-X13,0) -> 0 | Z13: =Y13+(0.05*Y13) -> 0 | AB13: =IF(AA13>0,Z13-AA13,0) -> 0 | AC13: =AB13+(0.05*AB13) -> 0 | AE13: =IF(AD13>0,AC13-AD13,0) -> 0 | AF13: =AE13 -> 0 | AH13: =IF(AG13>0,AF13-AG13,0) -> 0 | AI13: =AH13+(0.05*AH13) -> 0
A14: 2 | B14: Solomon | C14: 15000 | D14: =0.1*C14 -> 1500 | E14: =D14+C14 -> 16500 | F14: 4000 | G14: =E14-F14 -> 12500 | H14: =G14+(0.05*G14) -> 13125 | I14: 4000 | J14: =IF(I14>0,H14-I14,0) -> 9125 | K14: =J14+(0.05*J14) -> 9581.25 | L14: 2000 | M14: =IF(L14>0,K14-L14,0) -> 7581.25 | N14: =M14+(0.05*M14) -> 7960.3125 | O14: 4000 | P14: =IF(O14>0,N14-O14,0) -> 3960.3125 | Q14: =P14+(0.05*P14) -> 4158.3281 | R14: 3000 | S14: =IF(R14>0,Q14-R14,0) -> 1158.3281 | T14: =S14+(0.05*S14) -> 1216.2445 | U14: 600 | V14: =IF(U14>0,T14-U14,0) -> 616.24453 | W14: =V14+(0.05*V14) -> 647.05676 | X14: 300 | Y14: =IF(X14>0,W14-X14,0) -> 347.05676 | Z14: =Y14+(0.05*Y14) -> 364.4096 | AA14: 364.41 | AB14: Closed | AE14: =IF(AD14>0,AC14-AD14,0) -> 0 | AF14: =AE14 -> 0 | AH14: =IF(AG14>0,AF14-AG14,0) -> 0 | AI14: =AH14+(0.05*AH14) -> 0
A15: 3 | B15: Shubart | C15: 6000 | D15: =0.1*C15 -> 600 | E15: =D15+C15 -> 6600 | F15: 1000 | G15: =E15-F15 -> 5600 | H15: =G15+(0.05*G15) -> 5880 | I15: 500 | J15: =IF(I15>0,H15-I15,0) -> 5380 | K15: =J15+(0.05*J15) -> 5649 | L15: 500 | M15: =IF(L15>0,K15-L15,0) -> 5149 | N15: =M15+(0.05*M15) -> 5406.45 | O15: 500 | P15: =IF(O15>0,N15-O15,0) -> 4906.45 | Q15: =P15+(0.05*P15) -> 5151.7725 | R15: 500 | S15: =IF(R15>0,Q15-R15,0) -> 4651.7725 | T15: =S15+(0.05*S15) -> 4884.3611 | U15: 1000 | V15: =IF(U15>0,T15-U15,0) -> 3884.3611 | W15: =V15+(0.05*V15) -> 4078.5792 | X15: 1100 | Y15: =IF(X15>0,W15-X15,0) -> 2978.5792 | Z15: =Y15+(0.05*Y15) -> 3127.5081 | AA15: 500 | AB15: =IF(AA15>0,Z15-AA15,0) -> 2627.5081 | AC15: =AB15+(0.05*AB15) -> 2758.8835 | AE15: =AC15-AD15 -> 2758.8835 | AF15: =AE15 -> 2758.8835 | AH15: =IF(AG15>0,AF15-AG15,0) -> 0 | AI15: =AH15+(0.05*AH15) -> 0
A16: 4 | B16: Kebby | C16: 3000 | D16: =0.1*C16 -> 300 | E16: =D16+C16 -> 3300 | F16: 1500 | G16: =E16-F16 -> 1800 | H16: =G16+(0.05*G16) -> 1890 | I16: 1600 | J16: =IF(I16>0,H16-I16,0) -> 290 | K16: =J16+(0.05*J16) -> 304.5 | L16: 304.5 | M16: Closed | P16: =IF(O16>0,N16-O16,0) -> 0 | Q16: =P16+(0.05*P16) -> 0 | S16: =IF(R16>0,Q16-R16,0) -> 0 | T16: =S16+(0.05*S16) -> 0 | V16: =IF(U16>0,T16-U16,0) -> 0 | W16: =V16+(0.05*V16) -> 0 | Y16: =IF(X16>0,W16-X16,0) -> 0 | Z16: =Y16+(0.05*Y16) -> 0 | AB16: =IF(AA16>0,Z16-AA16,0) -> 0 | AC16: =AB16+(0.05*AB16) -> 0 | AE16: =IF(AD16>0,AC16-AD16,0) -> 0 | AF16: =AE16 -> 0 | AH16: =IF(AG16>0,AF16-AG16,0) -> 0 | AI16: =AH16+(0.05*AH16) -> 0
A17: 5 | B17: Evans | C17: 11000 | D17: =0.1*C17 -> 1100 | E17: =D17+C17 -> 12100 | F17: 2000 | G17: =E17-F17 -> 10100 | H17: =G17+(0.05*G17) -> 10605 | I17: 3500 | J17: =IF(I17>0,H17-I17,0) -> 7105 | K17: =J17+(0.05*J17) -> 7460.25 | L17: 2500 | M17: =IF(L17>0,K17-L17,0) -> 4960.25 | N17: =M17+(0.05*M17) -> 5208.2625 | O17: 500 | P17: =IF(O17>0,N17-O17,0) -> 4708.2625 | Q17: =P17+(0.05*P17) -> 4943.6756 | R17: 1000 | S17: =IF(R17>0,Q17-R17,0) -> 3943.6756 | T17: =S17+(0.05*S17) -> 4140.8594 | U17: 1000 | V17: =IF(U17>0,T17-U17,0) -> 3140.8594 | W17: =V17+(0.05*V17) -> 3297.9024 | X17: 1000 | Y17: =IF(X17>0,W17-X17,0) -> 2297.9024 | Z17: =Y17+(0.05*Y17) -> 2412.7975 | AA17: 500 | AB17: =IF(AA17>0,Z17-AA17,0) -> 1912.7975 | AC17: =AB17+(0.05*AB17) -> 2008.4374 | AE17: =AC17-AD17 -> 2008.4374 | AF17: =AE17 -> 2008.4374 | AH17: =IF(AG17>0,AF17-AG17,0) -> 0 | AI17: =AH17+(0.05*AH17) -> 0
A18: 6 | B18: Gilbert | C18: 9000 | D18: =0.1*C18 -> 900 | E18: =D18+C18 -> 9900 | F18: 3300 | G18: =E18-F18 -> 6600 | H18: =G18+(0.05*G18) -> 6930 | I18: 500 | J18: =IF(I18>0,H18-I18,0) -> 6430 | K18: =J18+(0.05*J18) -> 6751.5 | L18: 3000 | M18: =IF(L18>0,K18-L18,0) -> 3751.5 | N18: =M18+(0.05*M18) -> 3939.075 | O18: 3940 | P18: Closed | S18: =IF(R18>0,Q18-R18,0) -> 0 | T18: =S18+(0.05*S18) -> 0 | V18: =IF(U18>0,T18-U18,0) -> 0 | W18: =V18+(0.05*V18) -> 0 | Y18: =IF(X18>0,W18-X18,0) -> 0 | Z18: =Y18+(0.05*Y18) -> 0 | AB18: =IF(AA18>0,Z18-AA18,0) -> 0 | AC18: =AB18+(0.05*AB18) -> 0 | AE18: =IF(AD18>0,AC18-AD18,0) -> 0 | AF18: =AE18 -> 0 | AH18: =IF(AG18>0,AF18-AG18,0) -> 0 | AI18: =AH18+(0.05*AH18) -> 0
A19: 7 | B19: Millie | C19: 8000 | D19: =0.1*C19 -> 800 | E19: =D19+C19 -> 8800 | F19: 3000 | G19: =E19-F19 -> 5800 | H19: =G19+(0.05*G19) -> 6090 | I19: 2200 | J19: =IF(I19>0,H19-I19,0) -> 3890 | K19: =J19+(0.05*J19) -> 4084.5 | L19: 2085 | M19: =IF(L19>0,K19-L19,0) -> 1999.5 | N19: =M19+(0.05*M19) -> 2099.475 | O19: 2100 | P19: Closed | S19: =IF(R19>0,Q19-R19,0) -> 0 | T19: =S19+(0.05*S19) -> 0 | V19: =IF(U19>0,T19-U19,0) -> 0 | W19: =V19+(0.05*V19) -> 0 | Y19: =IF(X19>0,W19-X19,0) -> 0 | Z19: =Y19+(0.05*Y19) -> 0 | AB19: =IF(AA19>0,Z19-AA19,0) -> 0 | AC19: =AB19+(0.05*AB19) -> 0 | AE19: =IF(AD19>0,AC19-AD19,0) -> 0 | AF19: =AE19 -> 0 | AH19: =IF(AG19>0,AF19-AG19,0) -> 0 | AI19: =AH19+(0.05*AH19) -> 0
A20: 8 | B20: Shuller | C20: 1800 | D20: =0.1*C20 -> 180 | E20: =D20+C20 -> 1980 | F20: 1980 | G20: Closed | J20: =IF(I20>0,H20-I20,0) -> 0 | K20: =J20+(0.05*J20) -> 0 | M20: =IF(L20>0,K20-L20,0) -> 0 | N20: =M20+(0.05*M20) -> 0 | P20: =IF(O20>0,N20-O20,0) -> 0 | Q20: =P20+(0.05*P20) -> 0 | S20: =IF(R20>0,Q20-R20,0) -> 0 | T20: =S20+(0.05*S20) -> 0 | V20: =IF(U20>0,T20-U20,0) -> 0 | W20: =V20+(0.05*V20) -> 0 | Y20: =IF(X20>0,W20-X20,0) -> 0 | Z20: =Y20+(0.05*Y20) -> 0 | AB20: =IF(AA20>0,Z20-AA20,0) -> 0 | AC20: =AB20+(0.05*AB20) -> 0 | AE20: =IF(AD20>0,AC20-AD20,0) -> 0 | AF20: =AE20 -> 0 | AH20: =IF(AG20>0,AF20-AG20,0) -> 0 | AI20: =AH20+(0.05*AH20) -> 0
A21: 9 | B21: Mukuma | C21: 4000 | D21: =0.1*C21 -> 400 | E21: =D21+C21 -> 4400 | F21: 1000 | G21: =E21-F21 -> 3400 | H21: =G21+(0.05*G21) -> 3570 | I21: 1600 | J21: =IF(I21>0,H21-I21,0) -> 1970 | K21: =J21+(0.05*J21) -> 2068.5 | L21: 500 | M21: =IF(L21>0,K21-L21,0) -> 1568.5 | N21: =M21+(0.05*M21) -> 1646.925 | O21: 1646.93 | P21: Closed | S21: =IF(R21>0,Q21-R21,0) -> 0 | T21: =S21+(0.05*S21) -> 0 | V21: =IF(U21>0,T21-U21,0) -> 0 | W21: =V21+(0.05*V21) -> 0 | Y21: =IF(X21>0,W21-X21,0) -> 0 | Z21: =Y21+(0.05*Y21) -> 0 | AB21: =IF(AA21>0,Z21-AA21,0) -> 0 | AC21: =AB21+(0.05*AB21) -> 0 | AE21: =IF(AD21>0,AC21-AD21,0) -> 0 | AF21: =AE21 -> 0 | AH21: =IF(AG21>0,AF21-AG21,0) -> 0 | AI21: =AH21+(0.05*AH21) -> 0
A22: 10 | B22: Davies | C22: 3000 | D22: =0.1*C22 -> 300 | E22: =D22+C22 -> 3300 | F22: 1650 | G22: =E22-F22 -> 1650 | H22: =G22+(0.05*G22) -> 1732.5 | I22: 1732.5 | J22: Closed | M22: =IF(L22>0,K22-L22,0) -> 0 | N22: =M22+(0.05*M22) -> 0 | P22: =IF(O22>0,N22-O22,0) -> 0 | Q22: =P22+(0.05*P22) -> 0 | S22: =IF(R22>0,Q22-R22,0) -> 0 | T22: =S22+(0.05*S22) -> 0 | V22: =IF(U22>0,T22-U22,0) -> 0 | W22: =V22+(0.05*V22) -> 0 | Y22: =IF(X22>0,W22-X22,0) -> 0 | Z22: =Y22+(0.05*Y22) -> 0 | AB22: =IF(AA22>0,Z22-AA22,0) -> 0 | AC22: =AB22+(0.05*AB22) -> 0 | AE22: =IF(AD22>0,AC22-AD22,0) -> 0 | AF22: =AE22 -> 0 | AH22: =IF(AG22>0,AF22-AG22,0) -> 0 | AI22: =AH22+(0.05*AH22) -> 0
A23: 11 | B23: Micheal | C23: 3300 | D23: =0.1*C23 -> 330 | E23: =D23+C23 -> 3630 | F23: 2530 | G23: =E23-F23 -> 1100 | H23: =G23+(0.05*G23) -> 1155 | I23: 1155 | J23: Closed | M23: =IF(L23>0,K23-L23,0) -> 0 | N23: =M23+(0.05*M23) -> 0 | P23: =IF(O23>0,N23-O23,0) -> 0 | Q23: =P23+(0.05*P23) -> 0 | S23: =IF(R23>0,Q23-R23,0) -> 0 | T23: =S23+(0.05*S23) -> 0 | V23: =IF(U23>0,T23-U23,0) -> 0 | W23: =V23+(0.05*V23) -> 0 | Y23: =IF(X23>0,W23-X23,0) -> 0 | Z23: =Y23+(0.05*Y23) -> 0 | AB23: =IF(AA23>0,Z23-AA23,0) -> 0 | AC23: =AB23+(0.05*AB23) -> 0 | AE23: =IF(AD23>0,AC23-AD23,0) -> 0 | AF23: =AE23 -> 0 | AH23: =IF(AG23>0,AF23-AG23,0) -> 0 | AI23: =AH23+(0.05*AH23) -> 0
A24: 12 | B24: Richard | C24: 4800 | D24: =0.1*C24 -> 480 | E24: =D24+C24 -> 5280 | F24: 1000 | G24: =E24-F24 -> 4280 | H24: =G24+(0.05*G24) -> 4494 | I24: 1000 | J24: =IF(I24>0,H24-I24,0) -> 3494 | K24: =J24+(0.05*J24) -> 3668.7 | L24: 1000 | M24: =IF(L24>0,K24-L24,0) -> 2668.7 | N24: =M24+(0.05*M24) -> 2802.135 | O24: 1800 | P24: =IF(O24>0,N24-O24,0) -> 1002.135 | Q24: =P24+(0.05*P24) -> 1052.2417 | R24: 1052.24 | S24: Closed | V24: =IF(U24>0,T24-U24,0) -> 0 | W24: =V24+(0.05*V24) -> 0 | Y24: =IF(X24>0,W24-X24,0) -> 0 | Z24: =Y24+(0.05*Y24) -> 0 | AB24: =IF(AA24>0,Z24-AA24,0) -> 0 | AC24: =AB24+(0.05*AB24) -> 0 | AE24: =IF(AD24>0,AC24-AD24,0) -> 0 | AF24: =AE24 -> 0 | AH24: =IF(AG24>0,AF24-AG24,0) -> 0 | AI24: =AH24+(0.05*AH24) -> 0
A25: 13 | B25: Arthur | C25: 2200 | D25: =0.1*C25 -> 220 | E25: =D25+C25 -> 2420 | F25: 1100 | G25: =E25-F25 -> 1320 | H25: =G25+(0.05*G25) -> 1386 | I25: 1386 | J25: Closed | M25: =IF(L25>0,K25-L25,0) -> 0 | N25: =M25+(0.05*M25) -> 0 | P25: =IF(O25>0,N25-O25,0) -> 0 | Q25: =P25+(0.05*P25) -> 0 | S25: =IF(R25>0,Q25-R25,0) -> 0 | T25: =S25+(0.05*S25) -> 0 | V25: =IF(U25>0,T25-U25,0) -> 0 | W25: =V25+(0.05*V25) -> 0 | Y25: =IF(X25>0,W25-X25,0) -> 0 | Z25: =Y25+(0.05*Y25) -> 0 | AB25: =IF(AA25>0,Z25-AA25,0) -> 0 | AC25: =AB25+(0.05*AB25) -> 0 | AE25: =IF(AD25>0,AC25-AD25,0) -> 0 | AF25: =AE25 -> 0 | AH25: =IF(AG25>0,AF25-AG25,0) -> 0 | AI25: =AH25+(0.05*AH25) -> 0
A26: 14 | B26: Kamps | C26: 5000 | D26: =0.1*C26 -> 500 | E26: =D26+C26 -> 5500 | F26: 1000 | G26: =E26-F26 -> 4500 | H26: =G26+(0.05*G26) -> 4725 | I26: 800 | J26: =IF(I26>0,H26-I26,0) -> 3925 | K26: =J26+(0.05*J26) -> 4121.25 | L26: 1000 | M26: =IF(L26>0,K26-L26,0) -> 3121.25 | N26: =M26+(0.05*M26) -> 3277.3125 | O26: 3277.31 | P26: Closed | S26: =IF(R26>0,Q26-R26,0) -> 0 | T26: =S26+(0.05*S26) -> 0 | V26: =IF(U26>0,T26-U26,0) -> 0 | W26: =V26+(0.05*V26) -> 0 | Y26: =IF(X26>0,W26-X26,0) -> 0 | Z26: =Y26+(0.05*Y26) -> 0 | AB26: =IF(AA26>0,Z26-AA26,0) -> 0 | AC26: =AB26+(0.05*AB26) -> 0 | AE26: =IF(AD26>0,AC26-AD26,0) -> 0 | AF26: =AE26 -> 0 | AH26: =IF(AG26>0,AF26-AG26,0) -> 0 | AI26: =AH26+(0.05*AH26) -> 0
A27: Total | C27: =SUM(C13:C26) -> 80300 | D27: =SUM(D13:D26) -> 8030 | E27: =SUM(E13:E26) -> 88330 | F27: =SUM(F13:F26) -> 26600 | G27: =SUM(G13:G26) -> 61730 | H27: =SUM(H13:H26) -> 64816.5 | I27: =SUM(I13:I26) -> 21673.5 | J27: =SUM(J13:J26) -> 43143 | ... AI27: =SUM(AI13:AI26) -> 0
A31: JANUARY LOANS REPAYMENT SCHEDULE | F31: February | I31: March | L31: April | O31: May | R31: June | U31: July | X31: August | AA31: September | AD31: October
A32: No | B32: FULL NAMES | C32: AMOUNT | D32: INTEREST % | E32: TOTAL DUE | F32: PAID | G32: REDUCING BALANCE | H32: REDUCING BALANCE PLUS 5% | I32: PAID | J32: REDUCING BALANCE | K32: REDUCING BALANCE PLUS 5% | L32: PAID | M32: REDUCING BALANCE | N32: REDUCING BALANCE PLUS 5% | O32: PAID | P32: REDUCING BALANCE | Q32: REDUCING BALANCE PLUS 5% | R32: PAID | S32: REDUCING BALANCE | T32: REDUCING BALANCE PLUS 5% | U32: PAID | V32: REDUCING BALANCE | W32: REDUCING BALANCE PLUS 5% | X32: PAID | Y32: REDUCING BALANCE | Z32: REDUCING BALANCE PLUS 5% | AA32: PAID | AB32: REDUCING BALANCE | AC32: REDUCING BALANCE PLUS 5% | AD32: PAID | AE32: REDUCING BALANCE | AF32: REDUCING BALANCE PLUS 5%
B33: Gilbert | C33: 7200 | D33: =0.1*C33 -> 720 | E33: =D33+C33 -> 7920 | F33: 500 | G33: =E33-F33 -> 7420 | H33: =G33+(0.05*G33) -> 7791 | I33: 1500 | J33: =IF(I33>0,H33-I33,0) -> 6291 | K33: =J33+(0.05*J33) -> 6605.55 | L33: 2000 | M33: =IF(L33>0,K33-L33,0) -> 4605.55 | N33: =M33+(0.05*M33) -> 4835.8275 | O33: 4835.83 | P33: Closed | S33: =IF(R33>0,Q33-R33,0) -> 0 | T33: =S33+(0.05*S33) -> 0 | V33: =IF(U33>0,T33-U33,0) -> 0 | W33: =V33+(0.05*V33) -> 0 | Y33: =IF(X33>0,W33-X33,0) -> 0 | Z33: =Y33+(0.05*Y33) -> 0 | AB33: =IF(AA33>0,Z33-AA33,0) -> 0 | AC33: =AB33 -> 0 | AE33: =IF(AD33>0,AC33-AD33,0) -> 0 | AF33: =AE33+(0.05*AE33) -> 0
B34: Mwenya | C34: 20000 | D34: =0.1*C34 -> 2000 | E34: =D34+C34 -> 22000 | F34: 2000 | G34: =E34-F34 -> 20000 | H34: =G34+(0.05*G34) -> 21000 | I34: 2000 | J34: =IF(I34>0,H34-I34,0) -> 19000 | K34: =J34+(0.05*J34) -> 19950 | L34: 2000 | M34: =IF(L34>0,K34-L34,0) -> 17950 | N34: =M34+(0.05*M34) -> 18847.5 | O34: 5000 | P34: =IF(O34>0,N34-O34,0) -> 13847.5 | Q34: =P34+(0.05*P34) -> 14539.875 | R34: 1000 | S34: =IF(R34>0,Q34-R34,0) -> 13539.875 | T34: =S34+(0.05*S34) -> 14216.869 | U34: 1200 | V34: =IF(U34>0,T34-U34,0) -> 13016.869 | W34: =V34+(0.05*V34) -> 13667.712 | X34: 800 | Y34: =IF(X34>0,W34-X34,0) -> 12867.712 | Z34: =Y34+(0.05*Y34) -> 13511.098 | AB34: =Z34-AA34 -> 13511.098 | AC34: =AB34 -> 13511.098 | AE34: =IF(AD34>0,AC34-AD34,0) -> 0 | AF34: =AE34+(0.05*AE34) -> 0
B35: Abigail | C35: 25000 | D35: =0.1*C35 -> 2500 | E35: =D35+C35 -> 27500 | F35: 7500 | G35: =E35-F35 -> 20000 | H35: =G35+(0.05*G35) -> 21000 | I35: 10000 | J35: =IF(I35>0,H35-I35,0) -> 11000 | K35: =J35+(0.05*J35) -> 11550 | L35: 11550 | M35: Closed | P35: =IF(O35>0,N35-O35,0) -> 0 | Q35: =P35+(0.05*P35) -> 0 | S35: =IF(R35>0,Q35-R35,0) -> 0 | T35: =S35+(0.05*S35) -> 0 | V35: =IF(U35>0,T35-U35,0) -> 0 | W35: =V35+(0.05*V35) -> 0 | Y35: =IF(X35>0,W35-X35,0) -> 0 | Z35: =Y35+(0.05*Y35) -> 0 | AB35: =IF(AA35>0,Z35-AA35,0) -> 0 | AC35: =AB35 -> 0 | AE35: =IF(AD35>0,AC35-AD35,0) -> 0 | AF35: =AE35+(0.05*AE35) -> 0
B36: Mike | C36: 3060 | D36: =0.1*C36 -> 306 | E36: =D36+C36 -> 3366 | F36: 1100 | G36: =E36-F36 -> 2266 | H36: =G36+(0.05*G36) -> 2379.3 | I36: 1000 | J36: =IF(I36>0,H36-I36,0) -> 1379.3 | K36: =J36+(0.05*J36) -> 1448.265 | L36: 1100 | M36: =IF(L36>0,K36-L36,0) -> 348.265 | N36: =M36+(0.05*M36) -> 365.67825 | O36: 366 | P36: Closed | S36: =IF(R36>0,Q36-R36,0) -> 0 | T36: =S36+(0.05*S36) -> 0 | V36: =IF(U36>0,T36-U36,0) -> 0 | W36: =V36+(0.05*V36) -> 0 | Y36: =IF(X36>0,W36-X36,0) -> 0 | Z36: =Y36+(0.05*Y36) -> 0 | AB36: =IF(AA36>0,Z36-AA36,0) -> 0 | AC36: =AB36 -> 0 | AE36: =IF(AD36>0,AC36-AD36,0) -> 0 | AF36: =AE36+(0.05*AE36) -> 0
B37: Schuller | C37: 4800 | D37: =0.1*C37 -> 480 | E37: =D37+C37 -> 5280 | F37: 2000 | G37: =E37-F37 -> 3280 | H37: =G37+(0.05*G37) -> 3444 | I37: 1000 | J37: =IF(I37>0,H37-I37,0) -> 2444 | K37: =J37+(0.05*J37) -> 2566.2 | L37: 1000 | M37: =IF(L37>0,K37-L37,0) -> 1566.2 | N37: =M37+(0.05*M37) -> 1644.51 | O37: 1644.51 | P37: Closed | S37: =IF(R37>0,Q37-R37,0) -> 0 | T37: =S37+(0.05*S37) -> 0 | V37: =IF(U37>0,T37-U37,0) -> 0 | W37: =V37+(0.05*V37) -> 0 | Y37: =IF(X37>0,W37-X37,0) -> 0 | Z37: =Y37+(0.05*Y37) -> 0 | AB37: =IF(AA37>0,Z37-AA37,0) -> 0 | AC37: =AB37 -> 0 | AE37: =IF(AD37>0,AC37-AD37,0) -> 0 | AF37: =AE37+(0.05*AE37) -> 0
B38: Benson | C38: 5000 | D38: =0.1*C38 -> 500 | E38: =D38+C38 -> 5500 | F38: 1000 | G38: =E38-F38 -> 4500 | H38: =G38+(0.05*G38) -> 4725 | I38: 1000 | J38: =IF(I38>0,H38-I38,0) -> 3725 | K38: =J38+(0.05*J38) -> 3911.25 | L38: 2000 | M38: =IF(L38>0,K38-L38,0) -> 1911.25 | N38: =M38+(0.05*M38) -> 2006.8125 | O38: 500 | P38: =IF(O38>0,N38-O38,0) -> 1506.8125 | Q38: =P38+(0.05*P38) -> 1582.1531 | R38: 500 | S38: =IF(R38>0,Q38-R38,0) -> 1082.1531 | T38: =S38+(0.05*S38) -> 1136.2608 | U38: 400 | V38: =IF(U38>0,T38-U38,0) -> 736.26078 | W38: =V38+(0.05*V38) -> 773.07382 | X38: 200 | Y38: =IF(X38>0,W38-X38,0) -> 573.07382 | Z38: =Y38+(0.05*Y38) -> 601.72751 | AB38: =Z38-AA38 -> 601.72751 | AC38: =AB38 -> 601.72751 | AE38: =IF(AD38>0,AC38-AD38,0) -> 0 | AF38: =AE38+(0.05*AE38) -> 0
B39: Shubart | C39: 2000 | D39: =0.1*C39 -> 200 | E39: =D39+C39 -> 2200 | F39: 500 | G39: =E39-F39 -> 1700 | H39: =G39+(0.05*G39) -> 1785 | I39: 500 | J39: =IF(I39>0,H39-I39,0) -> 1285 | K39: =J39+(0.05*J39) -> 1349.25 | L39: 500 | M39: =L39+(0.05*L39) -> 525 | N39: =M39+(0.05*M39) -> 551.25 | O39: 551.25 | P39: Closed | S39: =IF(R39>0,Q39-R39,0) -> 0 | T39: =S39+(0.05*S39) -> 0 | V39: =IF(U39>0,T39-U39,0) -> 0 | W39: =V39+(0.05*V39) -> 0 | Y39: =IF(X39>0,W39-X39,0) -> 0 | Z39: =Y39+(0.05*Y39) -> 0 | AB39: =IF(AA39>0,Z39-AA39,0) -> 0 | AC39: =AB39 -> 0 | AE39: =IF(AD39>0,AC39-AD39,0) -> 0 | AF39: =AE39+(0.05*AE39) -> 0
B40: Paul | C40: 5000 | D40: =0.1*C40 -> 500 | E40: =D40+C40 -> 5500 | F40: 3000 | G40: =E40-F40 -> 2500 | H40: =G40+(0.05*G40) -> 2625 | I40: 2000 | J40: =IF(I40>0,H40-I40,0) -> 625 | K40: =J40+(0.05*J40) -> 656.25 | L40: 656.25 | M40: Closed | P40: =IF(O40>0,N40-O40,0) -> 0 | Q40: =P40+(0.05*P40) -> 0 | S40: =IF(R40>0,Q40-R40,0) -> 0 | T40: =S40+(0.05*S40) -> 0 | V40: =IF(U40>0,T40-U40,0) -> 0 | W40: =V40+(0.05*V40) -> 0 | Y40: =IF(X40>0,W40-X40,0) -> 0 | Z40: =Y40+(0.05*Y40) -> 0 | AB40: =IF(AA40>0,Z40-AA40,0) -> 0 | AC40: =AB40 -> 0 | AE40: =IF(AD40>0,AC40-AD40,0) -> 0 | AF40: =AE40+(0.05*AE40) -> 0
B41: Evans | C41: 6000 | D41: =0.1*C41 -> 600 | E41: =D41+C41 -> 6600 | F41: 3000 | G41: =E41-F41 -> 3600 | H41: =G41+(0.05*G41) -> 3780 | I41: 3780 | J41: Closed | M41: =IF(L41>0,K41-L41,0) -> 0 | N41: =M41+(0.05*M41) -> 0 | P41: =IF(O41>0,N41-O41,0) -> 0 | Q41: =P41+(0.05*P41) -> 0 | S41: =IF(R41>0,Q41-R41,0) -> 0 | T41: =S41+(0.05*S41) -> 0 | V41: =IF(U41>0,T41-U41,0) -> 0 | W41: =V41+(0.05*V41) -> 0 | Y41: =IF(X41>0,W41-X41,0) -> 0 | Z41: =Y41+(0.05*Y41) -> 0 | AB41: =IF(AA41>0,Z41-AA41,0) -> 0 | AC41: =AB41 -> 0 | AE41: =IF(AD41>0,AC41-AD41,0) -> 0 | AF41: =AE41+(0.05*AE41) -> 0
B42: Kamps2 | C42: 6000 | D42: =0.1*C42 -> 600 | E42: =D42+C42 -> 6600 | F42: 800 | G42: =E42-F42 -> 5800 | H42: =G42+(0.05*G42) -> 6090 | J42: =H42-I42 -> 6090 | K42: =J42+(0.05*J42) -> 6394.5 | L42: 1000 | M42: =IF(L42>0,K42-L42,0) -> 5394.5 | N42: =M42+(0.05*M42) -> 5664.225 | O42: 1000 | P42: =IF(O42>0,N42-O42,0) -> 4664.225 | Q42: =P42+(0.05*P42) -> 4897.4363 | R42: 1000 | S42: =IF(R42>0,Q42-R42,0) -> 3897.4363 | T42: =S42+(0.05*S42) -> 4092.3081 | U42: 1000 | V42: =IF(U42>0,T42-U42,0) -> 3092.3081 | W42: =V42+(0.05*V42) -> 3246.9235 | X42: 400 | Y42: =IF(X42>0,W42-X42,0) -> 2846.9235 | Z42: =Y42+(0.05*Y42) -> 2989.2696 | AB42: =Z42-AA42 -> 2989.2696 | AC42: =AB42 -> 2989.2696 | AE42: =IF(AD42>0,AC42-AD42,0) -> 0 | AF42: =AE42+(0.05*AE42) -> 0
B43: Zeko | C43: 10000 | D43: =0.1*C43 -> 1000 | E43: =D43+C43 -> 11000 | F43: 4000 | G43: =E43-F43 -> 7000 | H43: =G43+(0.05*G43) -> 7350 | I43: 2000 | J43: =IF(I43>0,H43-I43,0) -> 5350 | K43: =J43+(0.05*J43) -> 5617.5 | L43: 2000 | M43: =IF(L43>0,K43-L43,0) -> 3617.5 | N43: =M43+(0.05*M43) -> 3798.375 | O43: 2000 | P43: =IF(O43>0,N43-O43,0) -> 1798.375 | Q43: =P43+(0.05*P43) -> 1888.2938 | R43: 2000 | S43: =IF(R43>0,Q43-R43,0) -> -111.70625 | T43: =S43+(0.05*S43) -> -117.29156 | V43: Closed | Y43: =IF(X43>0,W43-X43,0) -> 0 | Z43: =Y43+(0.05*Y43) -> 0 | AB43: =IF(AA43>0,Z43-AA43,0) -> 0 | AC43: =AB43 -> 0 | AE43: =IF(AD43>0,AC43-AD43,0) -> 0 | AF43: =AE43+(0.05*AE43) -> 0
A44: Total | C44: =SUM(C33:C43) -> 94060 | D44: =SUM(D33:D43) -> 9406 | E44: =SUM(E33:E43) -> 103466 | F44: =SUM(F33:F43) -> 25400 | G44: =SUM(G33:G43) -> 78066 | H44: =SUM(H33:H43) -> 81969.3 | I44: =SUM(I33:I43) -> 24780 | J44: =SUM(J33:J43) -> 57189.3 | ... AF44: =SUM(AF33:AF43) -> 0
A47: FEBRUARY LOANS REPAYMENT SCHEDULE | F47: March | I47: April | L47: May | O47: June | R47: July | U47: August | X47: September | AA47: October
A48: No | B48: FULL NAMES | C48: AMOUNT | D48: INTEREST % | E48: TOTAL DUE | F48: PAID | G48: REDUCING BALANCE | H48: REDUCING BALANCE PLUS 5% | I48: PAID | J48: REDUCING BALANCE | K48: REDUCING BALANCE PLUS 5% | L48: PAID | M48: REDUCING BALANCE | N48: REDUCING BALANCE PLUS 5% | O48: PAID | P48: REDUCING BALANCE | Q48: REDUCING BALANCE PLUS 5% | R48: PAID | S48: REDUCING BALANCE | T48: REDUCING BALANCE PLUS 5% | U48: PAID | V48: REDUCING BALANCE | W48: REDUCING BALANCE PLUS 5% | X48: PAID | Y48: REDUCING BALANCE | Z48: REDUCING BALANCE PLUS 5% | AA48: PAID | AB48: REDUCING BALANCE | AC48: REDUCING BALANCE PLUS 5%
B49: Kwibisa | C49: 25000 | D49: =0.1*C49 -> 2500 | E49: =D49+C49 -> 27500 | F49: 3000 | G49: =IF(F49>0,E49-F49,0) -> 24500 | H49: =G49+(0.05*G49) -> 25725 | I49: 3500 | J49: =IF(I49>0,H49-I49,0) -> 22225 | K49: =J49+(0.05*J49) -> 23336.25 | L49: 1000 | M49: =IF(L49>0,K49-L49,0) -> 22336.25 | N49: =M49+(0.05*M49) -> 23453.062 | O49: 3500 | P49: =IF(O49>0,N49-O49,0) -> 19953.062 | Q49: =P49+(0.05*P49) -> 20950.716 | R49: 1000 | S49: =IF(R49>0,Q49-R49,0) -> 19950.716 | T49: =S49+(0.05*S49) -> 20948.251 | U49: 2000 | V49: =IF(U49>0,T49-U49,0) -> 18948.251 | W49: =V49+(0.05*V49) -> 19895.664 | Y49: =W49-X49 -> 19895.664 | Z49: =Y49 -> 19895.664 | AB49: =IF(AA49>0,Z49-AA49,0) -> 0 | AC49: =AB49+(0.05*AB49) -> 0
B50: Mukuma | C50: 15000 | D50: =0.1*C50 -> 1500 | E50: =D50+C50 -> 16500 | F50: 600 | G50: =IF(F50>0,E50-F50,0) -> 15900 | H50: =G50+(0.05*G50) -> 16695 | I50: 2000 | J50: =IF(I50>0,H50-I50,0) -> 14695 | K50: =J50+(0.05*J50) -> 15429.75 | L50: 800 | M50: =IF(L50>0,K50-L50,0) -> 14629.75 | N50: =M50+(0.05*M50) -> 15361.237 | O50: 1000 | P50: =IF(O50>0,N50-O50,0) -> 14361.237 | Q50: =P50+(0.05*P50) -> 15079.299 | R50: 3000 | S50: =IF(R50>0,Q50-R50,0) -> 12079.299 | T50: =S50+(0.05*S50) -> 12683.264 | U50: 900 | V50: =IF(U50>0,T50-U50,0) -> 11783.264 | W50: =V50+(0.05*V50) -> 12372.428 | Y50: =W50-X50 -> 12372.428 | Z50: =Y50 -> 12372.428 | AB50: =IF(AA50>0,Z50-AA50,0) -> 0 | AC50: =AB50+(0.05*AB50) -> 0
B51: Paul | C51: 10000 | D51: =0.1*C51 -> 1000 | E51: =D51+C51 -> 11000 | F51: 6300 | G51: =IF(F51>0,E51-F51,0) -> 4700 | H51: =G51+(0.05*G51) -> 4935 | I51: 2000 | J51: =IF(I51>0,H51-I51,0) -> 2935 | K51: =J51+(0.05*J51) -> 3081.75 | L51: 3081.75 | M51: Closed | P51: =IF(O51>0,N51-O51,0) -> 0 | Q51: =P51+(0.05*P51) -> 0 | S51: =IF(R51>0,Q51-R51,0) -> 0 | T51: =S51+(0.05*S51) -> 0 | V51: =IF(U51>0,T51-U51,0) -> 0 | W51: =V51+(0.05*V51) -> 0 | Y51: =W51-X51 -> 0 | Z51: =Y51 -> 0 | AB51: =IF(AA51>0,Z51-AA51,0) -> 0 | AC51: =AB51+(0.05*AB51) -> 0
B52: Jesper | C52: 15000 | D52: =0.1*C52 -> 1500 | E52: =D52+C52 -> 16500 | F52: 3500 | G52: =IF(F52>0,E52-F52,0) -> 13000 | H52: =G52+(0.05*G52) -> 13650 | I52: 2500 | J52: =IF(I52>0,H52-I52,0) -> 11150 | K52: =J52+(0.05*J52) -> 11707.5 | L52: 2000 | M52: =IF(L52>0,K52-L52,0) -> 9707.5 | N52: =M52+(0.05*M52) -> 10192.875 | O52: 2000 | P52: =IF(O52>0,N52-O52,0) -> 8192.875 | Q52: =P52+(0.05*P52) -> 8602.5187 | R52: 2500 | S52: =IF(R52>0,Q52-R52,0) -> 6102.5187 | T52: =S52+(0.05*S52) -> 6407.6447 | U52: 2500 | V52: =IF(U52>0,T52-U52,0) -> 3907.6447 | W52: =V52+(0.05*V52) -> 4103.0269 | Y52: =W52-X52 -> 4103.0269 | Z52: =Y52 -> 4103.0269 | AB52: =IF(AA52>0,Z52-AA52,0) -> 0 | AC52: =AB52+(0.05*AB52) -> 0
B53: Shuller | C53: 2400 | D53: =0.1*C53 -> 240 | E53: =D53+C53 -> 2640 | F53: 1000 | G53: =IF(F53>0,E53-F53,0) -> 1640 | H53: =G53+(0.05*G53) -> 1722 | I53: 1722 | J53: Closed | M53: =IF(L53>0,K53-L53,0) -> 0 | N53: =M53+(0.05*M53) -> 0 | P53: =IF(O53>0,N53-O53,0) -> 0 | Q53: =P53+(0.05*P53) -> 0 | S53: =IF(R53>0,Q53-R53,0) -> 0 | T53: =S53+(0.05*S53) -> 0 | V53: =IF(U53>0,T53-U53,0) -> 0 | W53: =V53+(0.05*V53) -> 0 | Y53: =W53-X53 -> 0 | Z53: =Y53 -> 0 | AB53: =IF(AA53>0,Z53-AA53,0) -> 0 | AC53: =AB53+(0.05*AB53) -> 0
B54: Kamps | C54: 6000 | D54: =0.1*C54 -> 600 | E54: =D54+C54 -> 6600 | G54: =E54-F54 -> 6600 | H54: =G54+(0.05*G54) -> 6930 | I54: 1000 | J54: =IF(I54>0,H54-I54,0) -> 5930 | K54: =J54+(0.05*J54) -> 6226.5 | L54: 1000 | M54: =IF(L54>0,K54-L54,0) -> 5226.5 | N54: =M54+(0.05*M54) -> 5487.825 | O54: 1000 | P54: =IF(O54>0,N54-O54,0) -> 4487.825 | Q54: =P54+(0.05*P54) -> 4712.2162 | R54: 1000 | S54: =IF(R54>0,Q54-R54,0) -> 3712.2162 | T54: =S54+(0.05*S54) -> 3897.8271 | U54: 400 | V54: =IF(U54>0,T54-U54,0) -> 3497.8271 | W54: =V54+(0.05*V54) -> 3672.7184 | Y54: =W54-X54 -> 3672.7184 | Z54: =Y54 -> 3672.7184 | AB54: =IF(AA54>0,Z54-AA54,0) -> 0 | AC54: =AB54+(0.05*AB54) -> 0
B55: Evans | C55: 8323.5 | D55: =0.1*C55 -> 832.35 | E55: =D55+C55 -> 9155.85 | F55: 2000 | G55: =IF(F55>0,E55-F55,0) -> 7155.85 | H55: =G55+(0.05*G55) -> 7513.6425 | I55: 2000 | J55: =IF(I55>0,H55-I55,0) -> 5513.6425 | K55: =J55+(0.05*J55) -> 5789.3246 | L55: 1000 | M55: =IF(L55>0,K55-L55,0) -> 4789.3246 | N55: =M55+(0.05*M55) -> 5028.7909 | O55: 500 | P55: =IF(O55>0,N55-O55,0) -> 4528.7909 | Q55: =P55+(0.05*P55) -> 4755.2304 | R55: 3000 | S55: =IF(R55>0,Q55-R55,0) -> 1755.2304 | T55: =S55+(0.05*S55) -> 1842.9919 | U55: 1000 | V55: =IF(U55>0,T55-U55,0) -> 842.99192 | W55: =V55+(0.05*V55) -> 885.14151 | Y55: =W55-X55 -> 885.14151 | Z55: =Y55 -> 885.14151 | AB55: =IF(AA55>0,Z55-AA55,0) -> 0 | AC55: =AB55+(0.05*AB55) -> 0
A56: Total | C56: =SUM(C49:C55) -> 81723.5 | D56: =SUM(D49:D55) -> 8172.35 | E56: =SUM(E49:E55) -> 89895.85 | F56: =SUM(F49:F55) -> 16400 | G56: =SUM(G49:G55) -> 73495.85 | H56: =SUM(H49:H55) -> 77170.643 | I56: =SUM(I49:I55) -> 14722 | J56: =SUM(J49:J55) -> 62448.643 | ... AC56: =SUM(AC49:AC55) -> 0
A59: MARCH LOANS REPAYMENT SCHEDULE | F59: April | I59: May | L59: June | O59: July | R59: August | U59: September | X59: October | AA59: October
A60: No | B60: FULL NAMES | C60: AMOUNT | D60: INTEREST % | E60: TOTAL DUE | F60: PAID | G60: REDUCING BALANCE | H60: REDUCING BALANCE PLUS 5% | I60: PAID | J60: REDUCING BALANCE | K60: REDUCING BALANCE PLUS 5% | L60: PAID | M60: REDUCING BALANCE | N60: REDUCING BALANCE PLUS 5% | O60: PAID | P60: REDUCING BALANCE | Q60: REDUCING BALANCE PLUS 5% | R60: PAID | S60: REDUCING BALANCE | T60: REDUCING BALANCE PLUS 5% | U60: PAID | V60: REDUCING BALANCE | W60: REDUCING BALANCE PLUS 5% | X60: PAID | Y60: REDUCING BALANCE | Z60: REDUCING BALANCE PLUS 5% | AA60: PAID | AB60: REDUCING BALANCE | AC60: REDUCING BALANCE PLUS 5%
B61: Arthur | C61: 10000 | D61: =0.1*C61 -> 1000 | E61: =D61+C61 -> 11000 | F61: 1400 | G61: =IF(F61>0,E61-F61,0) -> 9600 | H61: =G61+(0.05*G61) -> 10080 | I61: 1000 | J61: =IF(I61>0,H61-I61,0) -> 9080 | K61: =J61+(0.05*J61) -> 9534 | L61: 1500 | M61: =IF(L61>0,K61-L61,0) -> 8034 | N61: =M61+(0.05*M61) -> 8435.7 | O61: 1000 | P61: =IF(O61>0,N61-O61,0) -> 7435.7 | Q61: =P61+(0.05*P61) -> 7807.485 | R61: 1800 | S61: =IF(R61>0,Q61-R61,0) -> 6007.485 | T61: =S61+(0.05*S61) -> 6307.8593 | V61: =T61-U61 -> 6307.8593 | W61: =V61 -> 6307.8593 | Y61: =IF(X61>0,W61-X61,0) -> 0 | Z61: =Y61+(0.05*Y61) -> 0 | AB61: =IF(AA61>0,Z61-AA61,0) -> 0 | AC61: =AB61+(0.05*AB61) -> 0
B62: Davies | C62: 15200 | D62: =0.1*C62 -> 1520 | E62: =D62+C62 -> 16720 | F62: 1500 | G62: =IF(F62>0,E62-F62,0) -> 15220 | H62: =G62+(0.05*G62) -> 15981 | I62: 1700 | J62: =IF(I62>0,H62-I62,0) -> 14281 | K62: =J62+(0.05*J62) -> 14995.05 | L62: 1500 | M62: =IF(L62>0,K62-L62,0) -> 13495.05 | N62: =M62+(0.05*M62) -> 14169.802 | O62: 1000 | P62: =IF(O62>0,N62-O62,0) -> 13169.802 | Q62: =P62+(0.05*P62) -> 13828.293 | R62: 1500 | S62: =IF(R62>0,Q62-R62,0) -> 12328.293 | T62: =S62+(0.05*S62) -> 12944.707 | V62: =T62-U62 -> 12944.707 | W62: =V62 -> 12944.707 | Y62: =IF(X62>0,W62-X62,0) -> 0 | Z62: =Y62+(0.05*Y62) -> 0 | AB62: =IF(AA62>0,Z62-AA62,0) -> 0 | AC62: =AB62+(0.05*AB62) -> 0
B63: Andrew | C63: 10000 | D63: =0.1*C63 -> 1000 | E63: =D63+C63 -> 11000 | F63: 5000 | G63: =IF(F63>0,E63-F63,0) -> 6000 | H63: =G63+(0.05*G63) -> 6300 | I63: 4500 | J63: =IF(I63>0,H63-I63,0) -> 1800 | K63: =J63+(0.05*J63) -> 1890 | L63: 1890 | M63: Closed | P63: =IF(O63>0,N63-O63,0) -> 0 | Q63: =P63+(0.05*P63) -> 0 | S63: =IF(R63>0,Q63-R63,0) -> 0 | T63: =S63+(0.05*S63) -> 0 | V63: =T63-U63 -> 0 | W63: =V63 -> 0 | Y63: =IF(X63>0,W63-X63,0) -> 0 | Z63: =Y63+(0.05*Y63) -> 0 | AB63: =IF(AA63>0,Z63-AA63,0) -> 0 | AC63: =AB63+(0.05*AB63) -> 0
B64: Karen | C64: 12000 | D64: =0.1*C64 -> 1200 | E64: =D64+C64 -> 13200 | F64: 2000 | G64: =IF(F64>0,E64-F64,0) -> 11200 | H64: =G64+(0.05*G64) -> 11760 | I64: 1000 | J64: =IF(I64>0,H64-I64,0) -> 10760 | K64: =J64+(0.05*J64) -> 11298 | L64: 2000 | M64: =IF(L64>0,K64-L64,0) -> 9298 | N64: =M64+(0.05*M64) -> 9762.9 | O64: 2000 | P64: =IF(O64>0,N64-O64,0) -> 7762.9 | Q64: =P64+(0.05*P64) -> 8151.045 | R64: 1000 | S64: =IF(R64>0,Q64-R64,0) -> 7151.045 | T64: =S64+(0.05*S64) -> 7508.5972 | V64: =T64-U64 -> 7508.5972 | W64: =V64 -> 7508.5972 | Y64: =IF(X64>0,W64-X64,0) -> 0 | Z64: =Y64+(0.05*Y64) -> 0 | AB64: =IF(AA64>0,Z64-AA64,0) -> 0 | AC64: =AB64+(0.05*AB64) -> 0
B65: Micheal | C65: 5000 | D65: =0.1*C65 -> 500 | E65: =D65+C65 -> 5500 | F65: 1000 | G65: =IF(F65>0,E65-F65,0) -> 4500 | H65: =G65+(0.05*G65) -> 4725 | I65: 1000 | J65: =IF(I65>0,H65-I65,0) -> 3725 | K65: =J65+(0.05*J65) -> 3911.25 | L65: 2000 | M65: =IF(L65>0,K65-L65,0) -> 1911.25 | N65: =M65+(0.05*M65) -> 2006.8125 | O65: 2009 | P65: Closed | S65: =IF(R65>0,Q65-R65,0) -> 0 | T65: =S65+(0.05*S65) -> 0 | V65: =T65-U65 -> 0 | W65: =V65 -> 0 | Y65: =IF(X65>0,W65-X65,0) -> 0 | Z65: =Y65+(0.05*Y65) -> 0 | AB65: =IF(AA65>0,Z65-AA65,0) -> 0 | AC65: =AB65+(0.05*AB65) -> 0
B66: Keji | C66: 6000 | D66: =0.1*C66 -> 600 | E66: =D66+C66 -> 6600 | F66: 1600 | G66: =IF(F66>0,E66-F66,0) -> 5000 | H66: =G66+(0.05*G66) -> 5250 | I66: 1000 | J66: =IF(I66>0,H66-I66,0) -> 4250 | K66: =J66+(0.05*J66) -> 4462.5 | L66: 1462.5 | M66: =IF(L66>0,K66-L66,0) -> 3000 | N66: =M66+(0.05*M66) -> 3150 | O66: 1150 | P66: =IF(O66>0,N66-O66,0) -> 2000 | Q66: =P66+(0.05*P66) -> 2100 | R66: 2100 | S66: Closed | V66: =T66-U66 -> 0 | W66: =V66 -> 0 | Y66: =IF(X66>0,W66-X66,0) -> 0 | Z66: =Y66+(0.05*Y66) -> 0 | AB66: =IF(AA66>0,Z66-AA66,0) -> 0 | AC66: =AB66+(0.05*AB66) -> 0
B67: Solomon | C67: 3000 | D67: =0.1*C67 -> 300 | E67: =D67+C67 -> 3300 | F67: 600 | G67: =IF(F67>0,E67-F67,0) -> 2700 | H67: =G67+(0.05*G67) -> 2835 | I67: 600 | J67: =IF(I67>0,H67-I67,0) -> 2235 | K67: =J67+(0.05*J67) -> 2346.75 | L67: 600 | M67: =IF(L67>0,K67-L67,0) -> 1746.75 | N67: =M67+(0.05*M67) -> 1834.0875 | O67: 300 | P67: =IF(O67>0,N67-O67,0) -> 1534.0875 | Q67: =P67+(0.05*P67) -> 1610.7919 | R67: 1610.79 | S67: Closed | V67: =T67-U67 -> 0 | W67: =V67 -> 0
B68: Mofya | C68: 10000 | D68: =0.1*C68 -> 1000 | E68: =D68+C68 -> 11000 | F68: 1000 | G68: =IF(F68>0,E68-F68,0) -> 10000 | H68: =G68+(0.05*G68) -> 10500 | I68: 1300 | J68: =IF(I68>0,H68-I68,0) -> 9200 | K68: =J68+(0.05*J68) -> 9660 | L68: 1400 | M68: =IF(L68>0,K68-L68,0) -> 8260 | N68: =M68+(0.05*M68) -> 8673 | O68: 1000 | P68: =IF(O68>0,N68-O68,0) -> 7673 | Q68: =P68+(0.05*P68) -> 8056.65 | R68: 1000 | S68: =IF(R68>0,Q68-R68,0) -> 7056.65 | T68: =S68+(0.05*S68) -> 7409.4825 | V68: =T68-U68 -> 7409.4825 | W68: =V68 -> 7409.4825
B69: Richard | C69: 5067.06 | D69: =0.1*C69 -> 506.706 | E69: =D69+C69 -> 5573.766 | F69: 1800 | G69: =IF(F69>0,E69-F69,0) -> 3773.766 | H69: =G69+(0.05*G69) -> 3962.4543 | I69: 1573 | J69: =IF(I69>0,H69-I69,0) -> 2389.4543 | K69: =J69+(0.05*J69) -> 2508.927 | L69: 1500 | M69: =IF(L69>0,K69-L69,0) -> 1008.927 | N69: =M69+(0.05*M69) -> 1059.3734 | O69: 1059.37 | P69: Closed | S69: =IF(R69>0,Q69-R69,0) -> 0 | T69: =S69+(0.05*S69) -> 0 | V69: =T69-U69 -> 0 | W69: =V69 -> 0
B70: Kamps | C70: 5000 | D70: =0.1*C70 -> 500 | E70: =D70+C70 -> 5500 | F70: 1000 | G70: =IF(F70>0,E70-F70,0) -> 4500 | H70: =G70+(0.05*G70) -> 4725 | I70: 1000 | J70: =IF(I70>0,H70-I70,0) -> 3725 | K70: =J70+(0.05*J70) -> 3911.25 | L70: 1000 | M70: =IF(L70>0,K70-L70,0) -> 2911.25 | N70: =M70+(0.05*M70) -> 3056.8125 | O70: 1000 | P70: =IF(O70>0,N70-O70,0) -> 2056.8125 | Q70: =P70+(0.05*P70) -> 2159.6531 | R70: 400 | S70: =IF(R70>0,Q70-R70,0) -> 1759.6531 | T70: =S70+(0.05*S70) -> 1847.6358 | V70: =T70-U70 -> 1847.6358 | W70: =V70 -> 1847.6358
A71: Total | C71: =SUM(C61:C70) -> 81267.06 | D71: =SUM(D61:D70) -> 8126.706 | E71: =SUM(E61:E70) -> 89393.766 | F71: =SUM(F61:F70) -> 16900 | G71: =SUM(G61:G70) -> 72493.766 | H71: =SUM(H61:H70) -> 76118.454 | I71: =SUM(I61:I70) -> 14673 | J71: =SUM(J61:J70) -> 61445.454 | ... AC71: =SUM(AC61:AC70) -> 0
A75: APRIL LOANS REPAYMENT SCHEDULE | F75: May | I75: June | L75: July | O75: August | R75: September | U75: October | X75: October
A76: No | B76: FULL NAMES | C76: AMOUNT | D76: INTEREST % | E76: TOTAL DUE | F76: PAID | G76: REDUCING BALANCE | H76: REDUCING BALANCE PLUS 5% | I76: PAID | J76: REDUCING BALANCE | K76: REDUCING BALANCE PLUS 5% | L76: PAID | M76: REDUCING BALANCE | N76: REDUCING BALANCE PLUS 5% | O76: PAID | P76: REDUCING BALANCE | Q76: REDUCING BALANCE PLUS 5% | R76: PAID | S76: REDUCING BALANCE | T76: REDUCING BALANCE PLUS 5% | U76: PAID | V76: REDUCING BALANCE | W76: REDUCING BALANCE PLUS 5% | X76: PAID | Y76: REDUCING BALANCE | Z76: REDUCING BALANCE PLUS 5%
B77: Mwenya | C77: 12000 | D77: =0.1*C77 -> 1200 | E77: =D77+C77 -> 13200 | F77: 1800 | G77: =IF(F77>0,E77-F77,0) -> 11400 | H77: =G77+(0.05*G77) -> 11970 | I77: 1600 | J77: =IF(I77>0,H77-I77,0) -> 10370 | K77: =J77+(0.05*J77) -> 10888.5 | L77: 1000 | M77: =IF(L77>0,K77-L77,0) -> 9888.5 | N77: =M77+(0.05*M77) -> 10382.925 | O77: 800 | P77: =IF(O77>0,N77-O77,0) -> 9582.925 | Q77: =P77+(0.05*P77) -> 10062.071 | S77: =Q77-R77 -> 10062.071 | T77: =S77 -> 10062.071 | V77: =IF(U77>0,T77-U77,0) -> 0 | W77: =V77+(0.05*V77) -> 0 | Y77: =IF(X77>0,W77-X77,0) -> 0 | Z77: =Y77+(0.05*Y77) -> 0
B78: Mike | C78: 10000 | D78: =0.1*C78 -> 1000 | E78: =D78+C78 -> 11000 | F78: 1500 | G78: =IF(F78>0,E78-F78,0) -> 9500 | H78: =G78+(0.05*G78) -> 9975 | I78: 1000 | J78: =IF(I78>0,H78-I78,0) -> 8975 | K78: =J78+(0.05*J78) -> 9423.75 | L78: 2000 | M78: =IF(L78>0,K78-L78,0) -> 7423.75 | N78: =M78+(0.05*M78) -> 7794.9375 | O78: 500 | P78: =IF(O78>0,N78-O78,0) -> 7294.9375 | Q78: =P78+(0.05*P78) -> 7659.6844 | S78: =Q78-R78 -> 7659.6844 | T78: =S78 -> 7659.6844 | V78: =IF(U78>0,T78-U78,0) -> 0 | W78: =V78+(0.05*V78) -> 0 | Y78: =IF(X78>0,W78-X78,0) -> 0 | Z78: =Y78+(0.05*Y78) -> 0
B79: Abigal | C79: 40000 | D79: =0.1*C79 -> 4000 | E79: =D79+C79 -> 44000 | F79: 5000 | G79: =IF(F79>0,E79-F79,0) -> 39000 | H79: =G79+(0.05*G79) -> 40950 | I79: 12000 | J79: =IF(I79>0,H79-I79,0) -> 28950 | K79: =J79+(0.05*J79) -> 30397.5 | L79: 10000 | M79: =IF(L79>0,K79-L79,0) -> 20397.5 | N79: =M79+(0.05*M79) -> 21417.375 | O79: 10000 | P79: =IF(O79>0,N79-O79,0) -> 11417.375 | Q79: =P79+(0.05*P79) -> 11988.244 | S79: =Q79-R79 -> 11988.244 | T79: =S79 -> 11988.244 | V79: =IF(U79>0,T79-U79,0) -> 0 | W79: =V79+(0.05*V79) -> 0 | Y79: =IF(X79>0,W79-X79,0) -> 0 | Z79: =Y79+(0.05*Y79) -> 0
B80: Davies | C80: 6000 | D80: =0.1*C80 -> 600 | E80: =D80+C80 -> 6600 | F80: 1000 | G80: =IF(F80>0,E80-F80,0) -> 5600 | H80: =G80+(0.05*G80) -> 5880 | I80: 1000 | J80: =IF(I80>0,H80-I80,0) -> 4880 | K80: =J80+(0.05*J80) -> 5124 | L80: 650 | M80: =IF(L80>0,K80-L80,0) -> 4474 | N80: =M80+(0.05*M80) -> 4697.7 | O80: 1000 | P80: =IF(O80>0,N80-O80,0) -> 3697.7 | Q80: =P80+(0.05*P80) -> 3882.585 | S80: =Q80-R80 -> 3882.585 | T80: =S80 -> 3882.585 | V80: =IF(U80>0,T80-U80,0) -> 0 | W80: =V80+(0.05*V80) -> 0 | Y80: =IF(X80>0,W80-X80,0) -> 0 | Z80: =Y80+(0.05*Y80) -> 0
B81: Arthur | C81: 5000 | D81: =0.1*C81 -> 500 | E81: =D81+C81 -> 5500 | F81: 1000 | G81: =IF(F81>0,E81-F81,0) -> 4500 | H81: =G81+(0.05*G81) -> 4725 | I81: 1300 | J81: =IF(I81>0,H81-I81,0) -> 3425 | K81: =J81+(0.05*J81) -> 3596.25 | L81: 2000 | M81: =IF(L81>0,K81-L81,0) -> 1596.25 | N81: =M81+(0.05*M81) -> 1676.0625 | O81: 1000 | P81: =IF(O81>0,N81-O81,0) -> 676.0625 | Q81: =P81+(0.05*P81) -> 709.86563 | S81: =Q81-R81 -> 709.86563 | T81: =S81 -> 709.86563 | V81: =IF(U81>0,T81-U81,0) -> 0 | W81: =V81+(0.05*V81) -> 0 | Y81: =IF(X81>0,W81-X81,0) -> 0 | Z81: =Y81+(0.05*Y81) -> 0
B82: Khucwayo | C82: 2500 | D82: =0.1*C82 -> 250 | E82: =D82+C82 -> 2750 | F82: 2750 | G82: Closed | J82: =IF(I82>0,H82-I82,0) -> 0 | K82: =J82+(0.05*J82) -> 0 | M82: =IF(L82>0,K82-L82,0) -> 0 | N82: =M82+(0.05*M82) -> 0 | P82: =IF(O82>0,N82-O82,0) -> 0 | Q82: =P82+(0.05*P82) -> 0 | S82: =Q82-R82 -> 0 | T82: =S82 -> 0 | V82: =IF(U82>0,T82-U82,0) -> 0 | W82: =V82+(0.05*V82) -> 0 | Y82: =IF(X82>0,W82-X82,0) -> 0 | Z82: =Y82+(0.05*Y82) -> 0
B83: Micheal | C83: 6000 | D83: =0.1*C83 -> 600 | E83: =D83+C83 -> 6600 | F83: 2000 | G83: =IF(F83>0,E83-F83,0) -> 4600 | H83: =G83+(0.05*G83) -> 4830 | I83: 2000 | J83: =IF(I83>0,H83-I83,0) -> 2830 | K83: =J83+(0.05*J83) -> 2971.5 | L83: 2972 | M83: Closed | P83: =IF(O83>0,N83-O83,0) -> 0 | Q83: =P83+(0.05*P83) -> 0 | S83: =Q83-R83 -> 0 | T83: =S83 -> 0
B84: Millie | C84: 11895.18 | D84: =0.1*C84 -> 1189.518 | E84: =D84+C84 -> 13084.698 | F84: 2500 | G84: =IF(F84>0,E84-F84,0) -> 10584.698 | H84: =G84+(0.05*G84) -> 11113.933 | I84: 1000 | J84: =IF(I84>0,H84-I84,0) -> 10113.933 | K84: =J84+(0.05*J84) -> 10619.63 | L84: 1500 | M84: =IF(L84>0,K84-L84,0) -> 9119.6295 | N84: =M84+(0.05*M84) -> 9575.611 | O84: 1200 | P84: =IF(O84>0,N84-O84,0) -> 8375.611 | Q84: =P84+(0.05*P84) -> 8794.3916 | S84: =Q84-R84 -> 8794.3916 | T84: =S84 -> 8794.3916
A85: Total | C85: =SUM(C77:C84) -> 93395.18 | D85: =SUM(D77:D84) -> 9339.518 | E85: =SUM(E77:E84) -> 102734.7 | F85: =SUM(F77:F84) -> 17550 | G85: =SUM(G77:G84) -> 85184.698 | H85: =SUM(H77:H84) -> 89443.933 | I85: =SUM(I77:I84) -> 19900 | J85: =SUM(J77:J84) -> 69543.933 | ... Z85: =SUM(Z77:Z84) -> 0
A89: MAY LOANS REPAYMENT SCHEDULE | F89: June | I89: July | L89: August | O89: September | R89: October | U89: October
A90: No | B90: FULL NAMES | C90: AMOUNT | D90: INTEREST % | E90: TOTAL DUE | F90: PAID | G90: REDUCING BALANCE | H90: REDUCING BALANCE PLUS 5% | I90: PAID | J90: REDUCING BALANCE | K90: REDUCING BALANCE PLUS 5% | L90: PAID | M90: REDUCING BALANCE | N90: REDUCING BALANCE PLUS 5% | O90: PAID | P90: REDUCING BALANCE | Q90: REDUCING BALANCE PLUS 5% | R90: PAID | S90: REDUCING BALANCE | T90: REDUCING BALANCE PLUS 5% | U90: PAID | V90: REDUCING BALANCE | W90: REDUCING BALANCE PLUS 5%
B91: Gilbert | C91: 24000 | D91: =0.1*C91 -> 2400 | E91: =D91+C91 -> 26400 | F91: 15000 | G91: =IF(F91>0,E91-F91,0) -> 11400 | H91: =G91+(0.05*G91) -> 11970 | I91: 1000 | J91: =IF(I91>0,H91-I91,0) -> 10970 | K91: =J91+(0.05*J91) -> 11518.5 | L91: 1500 | M91: =K91-L91 -> 10018.5 | N91: =M91+(0.05*M91) -> 10519.425 | P91: =N91-O91 -> 10519.425 | Q91: =P91 -> 10519.425 | S91: =IF(R91>0,Q91-R91,0) -> 0 | T91: =S91+(0.05*S91) -> 0 | V91: =IF(U91>0,T91-U91,0) -> 0 | W91: =V91+(0.05*V91) -> 0
B92: Moya | C92: 6000 | D92: =0.1*C92 -> 600 | E92: =D92+C92 -> 6600 | F92: 1400 | G92: =IF(F92>0,E92-F92,0) -> 5200 | H92: =G92+(0.05*G92) -> 5460 | I92: 1000 | J92: =IF(I92>0,H92-I92,0) -> 4460 | K92: =J92+(0.05*J92) -> 4683 | L92: 1000 | M92: =K92-L92 -> 3683 | N92: =M92+(0.05*M92) -> 3867.15 | P92: =N92-O92 -> 3867.15 | Q92: =P92 -> 3867.15 | S92: =IF(R92>0,Q92-R92,0) -> 0 | T92: =S92+(0.05*S92) -> 0 | V92: =IF(U92>0,T92-U92,0) -> 0 | W92: =V92+(0.05*V92) -> 0
B93: Mukuma | C93: 5800 | D93: =0.1*C93 -> 580 | E93: =D93+C93 -> 6380 | F93: 600 | G93: =IF(F93>0,E93-F93,0) -> 5780 | H93: =G93+(0.05*G93) -> 6069 | I93: 2000 | J93: =IF(I93>0,H93-I93,0) -> 4069 | K93: =J93+(0.05*J93) -> 4272.45 | L93: 900 | M93: =K93-L93 -> 3372.45 | N93: =M93+(0.05*M93) -> 3541.0725 | P93: =N93-O93 -> 3541.0725 | Q93: =P93 -> 3541.0725 | S93: =IF(R93>0,Q93-R93,0) -> 0 | T93: =S93+(0.05*S93) -> 0 | V93: =IF(U93>0,T93-U93,0) -> 0 | W93: =V93+(0.05*V93) -> 0
B94: Kebby | C94: 9000 | D94: =0.1*C94 -> 900 | E94: =D94+C94 -> 9900 | F94: 3100 | G94: =IF(F94>0,E94-F94,0) -> 6800 | H94: =G94+(0.05*G94) -> 7140 | I94: 3300 | J94: =IF(I94>0,H94-I94,0) -> 3840 | K94: =J94+(0.05*J94) -> 4032 | L94: 1000 | M94: =K94-L94 -> 3032 | N94: =M94+(0.05*M94) -> 3183.6 | P94: =N94-O94 -> 3183.6 | Q94: =P94 -> 3183.6 | S94: =IF(R94>0,Q94-R94,0) -> 0 | T94: =S94+(0.05*S94) -> 0 | V94: =IF(U94>0,T94-U94,0) -> 0 | W94: =V94+(0.05*V94) -> 0
B95: Khucwayo | C95: 5000 | D95: =0.1*C95 -> 500 | E95: =D95+C95 -> 5500 | F95: 1800 | G95: =IF(F95>0,E95-F95,0) -> 3700 | H95: =G95+(0.05*G95) -> 3885 | I95: 1200 | J95: =IF(I95>0,H95-I95,0) -> 2685 | K95: =J95+(0.05*J95) -> 2819.25 | L95: 1200 | M95: =K95-L95 -> 1619.25 | N95: =M95+(0.05*M95) -> 1700.2125 | P95: =N95-O95 -> 1700.2125 | Q95: =P95 -> 1700.2125 | S95: =IF(R95>0,Q95-R95,0) -> 0 | T95: =S95+(0.05*S95) -> 0 | V95: =IF(U95>0,T95-U95,0) -> 0 | W95: =V95+(0.05*V95) -> 0
B96: Shuller | C96: 5000 | D96: =0.1*C96 -> 500 | E96: =D96+C96 -> 5500 | F96: 2000 | G96: =IF(F96>0,E96-F96,0) -> 3500 | H96: =G96+(0.05*G96) -> 3675 | I96: 1200 | J96: =IF(I96>0,H96-I96,0) -> 2475 | K96: =J96+(0.05*J96) -> 2598.75 | L96: 1300 | M96: =K96-L96 -> 1298.75 | N96: =M96+(0.05*M96) -> 1363.6875 | P96: =N96-O96 -> 1363.6875 | Q96: =P96 -> 1363.6875
B97: Davies | C97: 6000 | D97: =0.1*C97 -> 600 | E97: =D97+C97 -> 6600 | F97: 1000 | G97: =IF(F97>0,E97-F97,0) -> 5600 | H97: =G97+(0.05*G97) -> 5880 | I97: 650 | J97: =IF(I97>0,H97-I97,0) -> 5230 | K97: =J97+(0.05*J97) -> 5491.5 | L97: 500 | M97: =K97-L97 -> 4991.5 | N97: =M97+(0.05*M97) -> 5241.075 | P97: =N97-O97 -> 5241.075 | Q97: =P97 -> 5241.075
B98: Millie | C98: 8000 | D98: =0.1*C98 -> 800 | E98: =D98+C98 -> 8800 | F98: 1000 | G98: =IF(F98>0,E98-F98,0) -> 7800 | H98: =G98+(0.05*G98) -> 8190 | I98: 1500 | J98: =IF(I98>0,H98-I98,0) -> 6690 | K98: =J98+(0.05*J98) -> 7024.5 | L98: 1000 | M98: =K98-L98 -> 6024.5 | N98: =M98+(0.05*M98) -> 6325.725 | P98: =N98-O98 -> 6325.725 | Q98: =P98 -> 6325.725
B99: Keji | C99: 10000 | D99: =0.1*C99 -> 1000 | E99: =D99+C99 -> 11000 | F99: 2000 | G99: =IF(F99>0,E99-F99,0) -> 9000 | H99: =G99+(0.05*G99) -> 9450 | I99: 1450 | J99: =IF(I99>0,H99-I99,0) -> 8000 | K99: =J99+(0.05*J99) -> 8400 | L99: 2400 | M99: =K99-L99 -> 6000 | N99: =M99+(0.05*M99) -> 6300 | P99: =N99-O99 -> 6300 | Q99: =P99 -> 6300
B100: Shubart | C100: 5678.09 | D100: =0.1*C100 -> 567.809 | E100: =D100+C100 -> 6245.899 | F100: 500 | G100: =IF(F100>0,E100-F100,0) -> 5745.899 | H100: =G100+(0.05*G100) -> 6033.194 | I100: 1000 | J100: =IF(I100>0,H100-I100,0) -> 5033.194 | K100: =J100+(0.05*J100) -> 5284.8536 | L100: 500 | M100: =K100-L100 -> 4784.8536 | N100: =M100+(0.05*M100) -> 5024.0963 | P100: =N100-O100 -> 5024.0963 | Q100: =P100 -> 5024.0963 | S100: =IF(R100>0,Q100-R100,0) -> 0 | T100: =S100+(0.05*S100) -> 0 | V100: =IF(U100>0,T100-U100,0) -> 0 | W100: =V100+(0.05*V100) -> 0
A101: Total | C101: =SUM(C91:C100) -> 84478.09 | D101: =SUM(D91:D100) -> 8447.809 | E101: =SUM(E91:E100) -> 92925.899 | F101: =SUM(F91:F100) -> 28400 | G101: =SUM(G91:G100) -> 64525.899 | H101: =SUM(H91:H100) -> 67752.194 | I101: =SUM(I91:I100) -> 14300 | J101: =SUM(J91:J100) -> 53452.194 | ... W101: =SUM(W91:W100) -> 0
A105: JUNE LOANS REPAYMENT SCHEDULE | F105: July | I105: August | L105: September | O105: October | R105: October
A106: No | B106: FULL NAMES | C106: AMOUNT | D106: INTEREST % | E106: TOTAL DUE | F106: PAID | G106: REDUCING BALANCE | H106: REDUCING BALANCE PLUS 5% | I106: PAID | J106: REDUCING BALANCE | K106: REDUCING BALANCE PLUS 5% | L106: PAID | M106: REDUCING BALANCE | N106: REDUCING BALANCE PLUS 5% | O106: PAID | P106: REDUCING BALANCE | Q106: REDUCING BALANCE PLUS 5% | R106: PAID | S106: REDUCING BALANCE | T106: REDUCING BALANCE PLUS 5%
B107: Kwibisa Kalumba | C107: 13000 | D107: =0.1*C107 -> 1300 | E107: =D107+C107 -> 14300 | F107: 1000 | G107: =IF(F107>0,E107-F107,0) -> 13300 | H107: =G107+(0.05*G107) -> 13965 | I107: 1500 | J107: =H107-I107 -> 12465 | K107: =J107+(0.05*J107) -> 13088.25 | M107: =K107-L107 -> 13088.25 | N107: =M107 -> 13088.25 | P107: =IF(O107>0,N107-O107,0) -> 0 | Q107: =P107+(0.05*P107) -> 0 | S107: =IF(R107>0,Q107-R107,0) -> 0 | T107: =S107+(0.05*S107) -> 0
B108: Paul | C108: 20000 | D108: =0.1*C108 -> 2000 | E108: =D108+C108 -> 22000 | F108: 4000 | G108: =IF(F108>0,E108-F108,0) -> 18000 | H108: =G108+(0.05*G108) -> 18900 | I108: 18000 | J108: =H108-I108 -> 900 | K108: =J108+(0.05*J108) -> 945 | M108: =K108-L108 -> 945 | N108: =M108 -> 945 | P108: =IF(O108>0,N108-O108,0) -> 0 | Q108: =P108+(0.05*P108) -> 0 | S108: =IF(R108>0,Q108-R108,0) -> 0 | T108: =S108+(0.05*S108) -> 0
B109: Mrs Phiri | C109: 15000 | D109: =0.1*C109 -> 1500 | E109: =D109+C109 -> 16500 | F109: 3500 | G109: =IF(F109>0,E109-F109,0) -> 13000 | H109: =G109+(0.05*G109) -> 13650 | I109: 2500 | J109: =H109-I109 -> 11150 | K109: =J109+(0.05*J109) -> 11707.5 | M109: =K109-L109 -> 11707.5 | N109: =M109 -> 11707.5 | P109: =IF(O109>0,N109-O109,0) -> 0 | Q109: =P109+(0.05*P109) -> 0 | S109: =IF(R109>0,Q109-R109,0) -> 0 | T109: =S109+(0.05*S109) -> 0
B110: Evans | C110: 40000 | D110: =0.1*C110 -> 4000 | E110: =D110+C110 -> 44000 | F110: 1000 | G110: =IF(F110>0,E110-F110,0) -> 43000 | H110: =G110+(0.05*G110) -> 45150 | I110: 3500 | J110: =H110-I110 -> 41650 | K110: =J110+(0.05*J110) -> 43732.5 | M110: =K110-L110 -> 43732.5 | N110: =M110 -> 43732.5 | P110: =IF(O110>0,N110-O110,0) -> 0 | Q110: =P110+(0.05*P110) -> 0 | S110: =IF(R110>0,Q110-R110,0) -> 0 | T110: =S110+(0.05*S110) -> 0
B111: Mwinga | C111: 15000 | D111: =0.1*C111 -> 1500 | E111: =D111+C111 -> 16500 | F111: 2000 | G111: =IF(F111>0,E111-F111,0) -> 14500 | H111: =G111+(0.05*G111) -> 15225 | I111: 3000 | J111: =H111-I111 -> 12225 | K111: =J111+(0.05*J111) -> 12836.25 | M111: =K111-L111 -> 12836.25 | N111: =M111 -> 12836.25 | P111: =IF(O111>0,N111-O111,0) -> 0 | Q111: =P111+(0.05*P111) -> 0 | S111: =IF(R111>0,Q111-R111,0) -> 0 | T111: =S111+(0.05*S111) -> 0
B112: Davies | C112: 10000 | D112: =0.1*C112 -> 1000 | E112: =D112+C112 -> 11000 | F112: 1000 | G112: =IF(F112>0,E112-F112,0) -> 10000 | H112: =G112+(0.05*G112) -> 10500 | I112: 500 | J112: =H112-I112 -> 10000 | K112: =J112+(0.05*J112) -> 10500 | M112: =K112-L112 -> 10500 | N112: =M112 -> 10500
B113: Pamela | C113: 13569.5 | D113: =0.1*C113 -> 1356.95 | E113: =D113+C113 -> 14926.45 | F113: 2000 | G113: =IF(F113>0,E113-F113,0) -> 12926.45 | H113: =G113+(0.05*G113) -> 13572.773 | I113: 3000 | J113: =H113-I113 -> 10572.773 | K113: =J113+(0.05*J113) -> 11101.411 | M113: =K113-L113 -> 11101.411 | N113: =M113 -> 11101.411
A114: Total | C114: =SUM(C107:C113) -> 126569.5 | D114: =SUM(D107:D113) -> 12656.95 | E114: =SUM(E107:E113) -> 139226.45 | F114: =SUM(F107:F113) -> 14500 | G114: =SUM(G107:G113) -> 124726.45 | H114: =SUM(H107:H113) -> 130962.77 | I114: =SUM(I107:I113) -> 32000 | J114: =SUM(J107:J113) -> 98962.773 | ... T114: =SUM(T107:T113) -> 0
A117: JULY LOANS REPAYMENT SCHEDULE | F117: August | I117: September | L117: October | O117: October
A118: No | B118: FULL NAMES | C118: AMOUNT | D118: INTEREST % | E118: TOTAL DUE | F118: PAID | G118: REDUCING BALANCE | H118: REDUCING BALANCE PLUS 5% | I118: PAID | J118: REDUCING BALANCE | K118: REDUCING BALANCE PLUS 5% | L118: PAID | M118: REDUCING BALANCE | N118: REDUCING BALANCE PLUS 5% | O118: PAID | P118: REDUCING BALANCE | Q118: REDUCING BALANCE PLUS 5%
B119: Milllie | C119: 6940 | D119: =0.1*C119 -> 694 | E119: =D119+C119 -> 7634 | F119: 1000 | G119: =E119-F119 -> 6634 | H119: =G119+(0.05*G119) -> 6965.7 | J119: =H119-I119 -> 6965.7 | K119: =J119 -> 6965.7 | M119: =IF(L119>0,K119-L119,0) -> 0 | N119: =M119+(0.05*M119) -> 0 | P119: =IF(O119>0,N119-O119,0) -> 0 | Q119: =P119+(0.05*P119) -> 0
B120: Arthur | C120: 10000 | D120: =0.1*C120 -> 1000 | E120: =D120+C120 -> 11000 | F120: 1000 | G120: =E120-F120 -> 10000 | H120: =G120+(0.05*G120) -> 10500 | J120: =H120-I120 -> 10500 | K120: =J120 -> 10500 | M120: =IF(L120>0,K120-L120,0) -> 0 | N120: =M120+(0.05*M120) -> 0 | P120: =IF(O120>0,N120-O120,0) -> 0 | Q120: =P120+(0.05*P120) -> 0
...

Sheet Loan Applicants
B1: LOAN APPLICANTS
B2: Names | C2: November | D2: December | E2: January | F2: February | G2: March | H2: April | I2: May | J2: June | K2: July | L2: August | M2: September | O2: Total
A3: 1 | B3: Abigail Mundia | C3: ='New Repayment Schedule'!K6 -> 0 | D3: ='New Repayment Schedule'!S6 -> 44800 | E3: ='New Repayment Schedule'!AA6 -> 0 | F3: ='New Repayment Schedule'!AI6 -> 0 | G3: ='New Repayment Schedule'!AQ6 -> 50000 | I3: 3429 | L3: 4509.4716 | O3: =SUM(C3:N3) -> 102738.47
A4: 2 | B4: Abel Kunda | C4: ='New Repayment Schedule'!K7 -> 0 | D4: ='New Repayment Schedule'!S7 -> 0 | E4: ='New Repayment Schedule'!AA7 -> 0 | F4: ='New Repayment Schedule'!AI7 -> 0 | G4: ='New Repayment Schedule'!AQ7 -> 0 | J4: 14025 | K4: 26090 | L4: 8064.3836 | O4: =SUM(C4:N4) -> 48179.384
A5: 3 | B5: Andrew | C5: ='New Repayment Schedule'!K8 -> 6400 | D5: ='New Repayment Schedule'!S8 -> 0 | E5: ='New Repayment Schedule'!AA8 -> 0 | F5: ='New Repayment Schedule'!AI8 -> 0 | G5: ='New Repayment Schedule'!AQ8 -> 24000 | I5: 8000 | L5: 954.55969 | O5: =SUM(C5:N5) -> 39354.56
A6: 4 | B6: Arthur | C6: ='New Repayment Schedule'!K9 -> 0 | D6: ='New Repayment Schedule'!S9 -> 0 | E6: ='New Repayment Schedule'!AA9 -> 0 | F6: ='New Repayment Schedule'!AI9 -> 0 | G6: ='New Repayment Schedule'!AQ9 -> 0 | J6: 17000 | L6: 1020.3914 | O6: =SUM(C6:N6) -> 18020.391
A7: 5 | B7: Evans | C7: ='New Repayment Schedule'!K10 -> 20000 | D7: ='New Repayment Schedule'!S10 -> 11340 | E7: ='New Repayment Schedule'!AA10 -> 0 | F7: ='New Repayment Schedule'!AI10 -> 0 | G7: ='New Repayment Schedule'!AQ10 -> 0 | H7: 9967.81 | I7: 5300 | K7: 10000 | L7: 1711.6243 | O7: =SUM(C7:N7) -> 58319.434
A8: 6 | B8: Jesper | C8: ='New Repayment Schedule'!K11 -> 0 | D8: ='New Repayment Schedule'!S11 -> 0 | E8: ='New Repayment Schedule'!AA11 -> 0 | F8: ='New Repayment Schedule'!AI11 -> 0 | G8: ='New Repayment Schedule'!AQ11 -> 0 | L8: 362.07436 | O8: =SUM(C8:N8) -> 362.07436
A9: 7 | B9: Joshua | C9: ='New Repayment Schedule'!K12 -> 0 | D9: ='New Repayment Schedule'!S12 -> 0 | E9: ='New Repayment Schedule'!AA12 -> 3400 | F9: ='New Repayment Schedule'!AI12 -> 0 | G9: ='New Repayment Schedule'!AQ12 -> 0 | L9: 11000 | O9: =SUM(C9:N9) -> 14400
A10: 8 | B10: Kampamba | C10: ='New Repayment Schedule'!K13 -> 600 | D10: ='New Repayment Schedule'!S13 -> 0 | E10: ='New Repayment Schedule'!AA13 -> 0 | F10: ='New Repayment Schedule'!AI13 -> 0 | G10: ='New Repayment Schedule'!AQ13 -> 0 | H10: 17500 | L10: 1217.8865 | O10: =SUM(C10:N10) -> 19317.886
A11: 9 | B11: Karen Mwinga | C11: ='New Repayment Schedule'!K14 -> 0 | D11: ='New Repayment Schedule'!S14 -> 0 | E11: ='New Repayment Schedule'!AA14 -> 11300 | F11: ='New Repayment Schedule'!AI14 -> 0 | G11: ='New Repayment Schedule'!AQ14 -> 0 | J11: 50000 | L11: 855.81213 | O11: =SUM(C11:N11) -> 62155.812
A12: 10 | B12: Keji | C12: ='New Repayment Schedule'!K15 -> 6100 | D12: ='New Repayment Schedule'!S15 -> 0 | E12: ='New Repayment Schedule'!AA15 -> 0 | F12: ='New Repayment Schedule'!AI15 -> 21000 | G12: ='New Repayment Schedule'!AQ15 -> 0 | L12: 1086.2231 | O12: =SUM(C12:N12) -> 28186.223
A13: 11 | B13: Kombe | C13: ='New Repayment Schedule'!K16 -> 0 | D13: ='New Repayment Schedule'!S16 -> 6000 | E13: ='New Repayment Schedule'!AA16 -> 8750 | F13: ='New Repayment Schedule'!AI16 -> 0 | G13: ='New Repayment Schedule'!AQ16 -> 50000 | I13: 55000 | L13: 5233.6204 | O13: =SUM(C13:N13) -> 124983.62
A14: 12 | B14: Khucwayo | C14: ='New Repayment Schedule'!K17 -> 0 | D14: ='New Repayment Schedule'!S17 -> 0 | E14: ='New Repayment Schedule'!AA17 -> 1400 | F14: ='New Repayment Schedule'!AI17 -> 0 | G14: ='New Repayment Schedule'!AQ17 -> 0 | L14: 526.65362 | O14: =SUM(C14:N14) -> 1926.6536
A15: 13 | B15: Kwibisa | C15: ='New Repayment Schedule'!K18 -> 15000 | D15: ='New Repayment Schedule'!S18 -> 3500 | E15: ='New Repayment Schedule'!AA18 -> 2800 | F15: ='New Repayment Schedule'!AI18 -> 0 | G15: ='New Repayment Schedule'!AQ18 -> 0 | H15: 8000 | L15: 1250.8023 | O15: =SUM(C15:N15) -> 30550.802
A16: 14 | B16: Michael | C16: ='New Repayment Schedule'!K19 -> 0 | D16: ='New Repayment Schedule'!S19 -> 0 | E16: ='New Repayment Schedule'!AA19 -> 0 | F16: ='New Repayment Schedule'!AI19 -> 0 | G16: ='New Repayment Schedule'!AQ19 -> 0 | H16: 15000 | L16: 8031.4677 | O16: =SUM(C16:N16) -> 23031.468
A17: 15 | B17: Millie | C17: ='New Repayment Schedule'!K20 -> 0 | D17: ='New Repayment Schedule'!S20 -> 0 | E17: ='New Repayment Schedule'!AA20 -> 10000 | F17: ='New Repayment Schedule'!AI20 -> 0 | G17: ='New Repayment Schedule'!AQ20 -> 0 | J17: 10000 | L17: 592.48532 | O17: =SUM(C17:N17) -> 20592.485
A18: 16 | B18: Mukuma | C18: ='New Repayment Schedule'!K21 -> 0 | D18: ='New Repayment Schedule'!S21 -> 0 | E18: ='New Repayment Schedule'!AA21 -> 3000 | F18: ='New Repayment Schedule'!AI21 -> 0 | G18: ='New Repayment Schedule'!AQ21 -> 0 | H18: 10000 | L18: 4147.3973 | O18: =SUM(C18:N18) -> 17147.397
A19: 17 | B19: Mumba | C19: ='New Repayment Schedule'!K22 -> 0 | D19: ='New Repayment Schedule'!S22 -> 0 | E19: ='New Repayment Schedule'!AA22 -> 0 | F19: ='New Repayment Schedule'!AI22 -> 0 | G19: ='New Repayment Schedule'!AQ22 -> 10000 | L19: 4147.3973 | O19: =SUM(C19:N19) -> 14147.397
A20: 18 | B20: Mumbi | C20: ='New Repayment Schedule'!K23 -> 0 | D20: ='New Repayment Schedule'!S23 -> 3000 | E20: ='New Repayment Schedule'!AA23 -> 3000 | F20: ='New Repayment Schedule'!AI23 -> 0 | G20: ='New Repayment Schedule'!AQ23 -> 0 | I20: 5000 | L20: 4443.6399 | O20: =SUM(C20:N20) -> 15443.64
A21: 19 | B21: Mwenya | C21: ='New Repayment Schedule'!K24 -> 0 | D21: ='New Repayment Schedule'!S24 -> 0 | E21: ='New Repayment Schedule'!AA24 -> 0 | F21: ='New Repayment Schedule'!AI24 -> 0 | G21: ='New Repayment Schedule'!AQ24 -> 0 | K21: 15000 | L21: 5562.7789 | O21: =SUM(C21:N21) -> 20562.779
A22: 20 | B22: Nyanyiwe | C22: ='New Repayment Schedule'!K25 -> 0 | D22: ='New Repayment Schedule'!S25 -> 0 | E22: ='New Repayment Schedule'!AA25 -> 0 | F22: ='New Repayment Schedule'!AI25 -> 51300 | G22: ='New Repayment Schedule'!AQ25 -> 0 | L22: 4114.4814 | O22: =SUM(C22:N22) -> 55414.481
A23: 21 | B23: Pamela | C23: ='New Repayment Schedule'!K26 -> 0 | D23: ='New Repayment Schedule'!S26 -> 0 | E23: ='New Repayment Schedule'!AA26 -> 0 | F23: ='New Repayment Schedule'!AI26 -> 0 | G23: ='New Repayment Schedule'!AQ26 -> 30000 | L23: 2337.0254 | O23: =SUM(C23:N23) -> 32337.025
A24: 22 | B24: Schuller | C24: ='New Repayment Schedule'!K27 -> 0 | D24: ='New Repayment Schedule'!S27 -> 0 | E24: ='New Repayment Schedule'!AA27 -> 0 | F24: ='New Repayment Schedule'!AI27 -> 0 | G24: ='New Repayment Schedule'!AQ27 -> 0 | K24: 25000 | L24: 5299.4521 | O24: =SUM(C24:N24) -> 30299.452
A25: 23 | B25: Shubart | C25: ='New Repayment Schedule'!K28 -> 0 | D25: ='New Repayment Schedule'!S28 -> 0 | E25: ='New Repayment Schedule'!AA28 -> 0 | F25: ='New Repayment Schedule'!AI28 -> 0 | G25: ='New Repayment Schedule'!AQ28 -> 13265 | L25: 1810.3718 | O25: =SUM(C25:N25) -> 15075.372
A26: 24 | B26: Solomon | C26: ='New Repayment Schedule'!K29 -> 0 | D26: ='New Repayment Schedule'!S29 -> 0 | E26: ='New Repayment Schedule'!AA29 -> 0 | F26: ='New Repayment Schedule'!AI29 -> 0 | G26: ='New Repayment Schedule'!AQ29 -> 0 | L26: 15000 | O26: =SUM(C26:N26) -> 15000
A27: 25 | B27: Tumelo | C27: ='New Repayment Schedule'!K30 -> 0 | D27: ='New Repayment Schedule'!S30 -> 0 | E27: ='New Repayment Schedule'!AA30 -> 0 | F27: ='New Repayment Schedule'!AI30 -> 0 | G27: ='New Repayment Schedule'!AQ30 -> 0 | O27: =SUM(C27:N27) -> 0
B28: TOTAL LOAN | C28: ='New Repayment Schedule'!K31 -> 48100 | D28: ='New Repayment Schedule'!S31 -> 68640 | E28: ='New Repayment Schedule'!AA31 -> 43650 | F28: ='New Repayment Schedule'!AI31 -> 72300 | G28: ='New Repayment Schedule'!AQ31 -> 177265 | H28: =SUM(H3:H27) -> 60467.81 | I28: =SUM(I3:I27) -> 76729 | J28: =SUM(J3:J27) -> 91025 | K28: =SUM(K3:K27) -> 76090 | L28: =SUM(L3:L27) -> 93280 | M28: =SUM(M3:M27) -> 0 | N28: =SUM(N3:N27) -> 0 | O28: =SUM(O3:O27) -> 807546.81

Sheet REDLIST ALERT
A1: No | B1: FULL NAMES | C1: Shares | D1: GROSS SHARES OUT | E1: Loan | F1: Net Share Out | G1: Share Out | H1: Red List | I1: Excess | J1: Insurance | K1: Net Shareout | N1: Admin | P1: Nyanyiwe | Q1: Evans | R1: Kwibisa | S1: Pamela | T1: Totals
A2: 1 | B2: Abigail Mundia | C2: =Shares!Y4 -> 27400 | D2: =Shareout!C85 -> 41458.426 | E2: =Shareout!C86 -> 75216.482 | F2: =D2-E2 -> -33758.056 | G2: =IF(F2>0,F2,0) -> 0 | H2: =(IF(F2<0,F2,0))*-1 -> 33758.056 | K2: =G2-H2+I2 -> -33758.056 | P2: =SUM(P3:P29) -> 43162.515 | Q2: =SUM(Q3:Q29) -> 69027.49 | R2: =SUM(R3:R29) -> 33938.871 | S2: =SUM(S3:S29) -> 68646.212
A3: 2 | B3: Abel Kunda | C3: =Shares!Y5 -> 49000 | D3: =Shareout!G85 -> 68603.305 | E3: =Shareout!G86 -> 16162.944 | F3: =D3-E3 -> 52440.361 | G3: =IF(F3>0,F3,0) -> 52440.361 | H3: =(IF(F3<0,F3,0))*-1 -> 0 | K3: =G3-H3+I3 -> 52440.361 | N3: 1 | O3: Abigail Mundia | P3: 4004.8594 | T3: =SUM(P3:S3) -> 4004.8594 | U3: =K2-T3 -> -37762.915
A4: 3 | B4: Andrew | C4: =Shares!Y6 -> 5800 | D4: =Shareout!K85 -> 8404.5446 | E4: =Shareout!K86 -> 1141.2562 | F4: =D4-E4 -> 7263.2884 | G4: =IF(F4>0,F4,0) -> 7263.2884 | H4: =(IF(F4<0,F4,0))*-1 -> 0 | K4: =G4-H4+I4 -> 7263.2884 | N4: 2 | O4: Andrew | P4: 331.24916 | T4: =SUM(P4:S4) -> 331.24916
A5: 4 | B5: Arthur | C5: =Shares!Y7 -> 6200 | D5: =Shareout!O85 -> 8039.3018 | E5: =Shareout!O86 -> 5351.8097 | F5: =D5-E5 -> 2687.4921 | G5: =IF(F5>0,F5,0) -> 2687.4921 | H5: =(IF(F5<0,F5,0))*-1 -> 0 | K5: =I5 -> 0 | M5: =I5+I12+I19 -> 0 | N5: 3 | O5: Arthur | P5: 4150.3196 | T5: =SUM(P5:S5) -> 4150.3196
A6: 5 | B6: Evans | C6: =Shares!Y8 -> 10400 | D6: =Shareout!S85 -> 16150.911 | E6: =Shareout!S86 -> 10566.477 | F6: =D6-E6 -> 5584.4338 | G6: =IF(F6>0,F6,0) -> 5584.4338 | H6: =(IF(F6<0,F6,0))*-1 -> 0 | K6: =G6-H6+I6 -> 5584.4338 | N6: 5 | O6: Evans | Q6: 1977.959 | T6: =SUM(P6:S6) -> 1977.959
A7: 6 | B7: Jesper | C7: =Shares!Y9 -> 2200 | D7: =Shareout!X85 -> 3009.6864 | E7: =Shareout!X86 -> -4.1813014 | F7: =D7-E7 -> 3013.8677 | G7: =IF(F7>0,F7,0) -> 3013.8677 | H7: =(IF(F7<0,F7,0))*-1 -> 0 | K7: =G7-H7+I7 -> 3013.8677 | N7: 6 | O7: Gilbert | Q7: 7198.6679 | T7: =SUM(P7:S7) -> 7198.6679
A8: 7 | B8: Joshua | C8: =Shares!Y10 -> 13400 | D8: =Shareout!AB85 -> 16456.086 | E8: =Shareout!AB86 -> 12127.5 | F8: =D8-E8 -> 4328.5864 | G8: =IF(F8>0,F8,0) -> 4328.5864 | H8: =(IF(F8<0,F8,0))*-1 -> 0 | K8: =G8-H8+I8 -> 4328.5864 | N8: 7 | O8: Jesper Chola | R8: 1175.2799 | T8: =SUM(P8:S8) -> 1175.2799
A9: 8 | B9: Kampamba | C9: =Shares!Y11 -> 7400 | D9: =Shareout!AF85 -> 10322.876 | E9: =Shareout!AF86 -> 13494.111 | F9: =D9-E9 -> -3171.2357 | G9: =IF(F9>0,F9,0) -> 0 | H9: =(IF(F9<0,F9,0))*-1 -> 3171.2357 | K9: =G9-H9+I9 -> -3171.2357 | N9: 8 | O9: Joshua | Q9: 23858.854 | T9: =SUM(P9:S9) -> 23858.854
A10: 9 | B10: Karen Mwinga | C10: =Shares!Y12 -> 5200 | D10: =Shareout!AJ85 -> 7244.343 | E10: =Shareout!AJ86 -> 4847.7509 | F10: =D10-E10 -> 2396.592 | G10: =IF(F10>0,F10,0) -> 2396.592 | H10: =(IF(F10<0,F10,0))*-1 -> 0 | K10: =G10-H10+I10 -> 2396.592 | N10: 9 | O10: Kampamba | P10: 852.1152 | T10: =SUM(P10:S10) -> 852.1152
A11: 10 | B11: Keji | C11: =Shares!Y13 -> 6600 | D11: =Shareout!AN85 -> 9548.0203 | E11: =Shareout!AN86 -> 10586.081 | F11: =D11-E11 -> -1038.0603 | G11: =IF(F11>0,F11,0) -> 0 | H11: =(IF(F11<0,F11,0))*-1 -> 1038.0603 | K11: =G11-H11+I11 -> -1038.0603 | N11: 10 | O11: Karen Mwinga | P11: 2410.8575 | T11: =SUM(P11:S11) -> 2410.8575
A12: 11 | B12: Kombe | C12: =Shares!Y14 -> 31800 | D12: =Shareout!AV85 -> 42633.685 | E12: =Shareout!AV86 -> 83718.175 | F12: =D12-E12 -> -41084.49 | G12: =IF(F12>0,F12,0) -> 0 | H12: =(IF(F12<0,F12,0))*-1 -> 41084.49 | K12: =I12 -> 0 | N12: 12 | O12: Keji | P12: 9145.4984 | T12: =SUM(P12:S12) -> 9145.4984
A13: 12 | B13: Khucwayo | C13: =Shares!Y15 -> 3200 | D13: =Shareout!AR85 -> 4258.7266 | E13: =Shareout!AR86 -> -416.72233 | F13: =D13-E13 -> 4675.4489 | G13: =IF(F13>0,F13,0) -> 4675.4489 | H13: =(IF(F13<0,F13,0))*-1 -> 0 | K13: =G13-H13+I13 -> 4675.4489 | N13: 13 | O13: Kombe | P13: 2822.901 | T13: =SUM(P13:S13) -> 2822.901
A14: 13 | B14: Kwibisa | C14: =Shares!Y16 -> 7600 | D14: =Shareout!AZ85 -> 11976.859 | E14: =Shareout!AZ86 -> 11425.696 | F14: =D14-E14 -> 551.16374 | G14: =IF(F14>0,F14,0) -> 551.16374 | H14: =(IF(F14<0,F14,0))*-1 -> 0 | K14: =G14-H14+I14 -> 551.16374 | N14: 14 | O14: Khucwayo | P14: 3143.2081 | T14: =SUM(P14:S14) -> 3143.2081
A15: 14 | B15: Michael | C15: =Shares!Y17 -> 48800 | D15: =Shareout!BD85 -> 69300.958 | E15: =Shareout!BE86 -> 0 | F15: =D15-E15 -> 69300.958 | G15: =IF(F15>0,F15,0) -> 69300.958 | H15: =(IF(F15<0,F15,0))*-1 -> 0 | K15: =G15-H15+I15 -> 69300.958 | N15: 15 | O15: Kwibisa | R15: 713.59971 | T15: =SUM(P15:S15) -> 713.59971
A16: 15 | B16: Millie | C16: =Shares!Y18 -> 3600 | D16: =Shareout!BH85 -> 5100.8299 | E16: =Shareout!BH86 -> 5178.3221 | F16: =D16-E16 -> -77.492136 | G16: =IF(F16>0,F16,0) -> 0 | H16: =(IF(F16<0,F16,0))*-1 -> 77.492136 | K16: =I16 -> 0 | N16: 16 | O16: Michael | P16: 12283.398 | T16: =SUM(P16:S16) -> 12283.398
A17: 16 | B17: Mukuma | C17: =Shares!Y19 -> 25200 | D17: =Shareout!BL85 -> 35608.031 | E17: =Shareout!BL86 -> 1003.2706 | F17: =D17-E17 -> 34604.76 | G17: =IF(F17>0,F17,0) -> 34604.76 | H17: =(IF(F17<0,F17,0))*-1 -> 0 | K17: =G17-H17+I17 -> 34604.76 | N17: 17 | O17: Mike | R17: 2261.2038 | T17: =SUM(P17:S17) -> 2261.2038
A18: 17 | B18: Mumba | C18: =Shares!Y20 -> 25200 | D18: =Shareout!BP85 -> 35718.613 | E18: =Shareout!BP86 -> -0.00030205479 | F18: =D18-E18 -> 35718.613 | G18: =IF(F18>0,F18,0) -> 35718.613 | H18: =(IF(F18<0,F18,0))*-1 -> 0 | K18: =G18-H18+I18 -> 35718.613 | N18: 18 | O18: Millie | S18: 547.09311 | T18: =SUM(P18:S18) -> 547.09311
A19: 18 | B19: Mumbi | C19: =Shares!Y21 -> 27000 | D19: =Shareout!BT85 -> 39807.92 | E19: =Shareout!BT86 -> 6491.2086 | F19: =D19-E19 -> 33316.711 | G19: =IF(F19>0,F19,0) -> 33316.711 | H19: =(IF(F19<0,F19,0))*-1 -> 0 | K19: =I19 -> 0 | N19: 19 | O19: Mofya | S19: 7386.6872 | T19: =SUM(P19:S19) -> 7386.6872
A20: 19 | B20: Mwenya | C20: =Shares!Y22 -> 33800 | D20: =Shareout!BX85 -> 48194.34 | E20: =Shareout!BX86 -> 9143.72 | F20: =D20-E20 -> 39050.62 | G20: =IF(F20>0,F20,0) -> 39050.62 | H20: =(IF(F20<0,F20,0))*-1 -> 0 | K20: =G20-H20+I20 -> 39050.62 | N20: 20 | O20: Mukuma | S20: 37044.945 | T20: =SUM(P20:S20) -> 37044.945
A21: 20 | B21: Nyanyiwe | C21: =Shares!Y23 -> 25000 | D21: =Shareout!CB85 -> 39135.116 | E21: =Shareout!CB86 -> 2044.6104 | F21: =D21-E21 -> 37090.505 | G21: =IF(F21>0,F21,0) -> 37090.505 | H21: =(IF(F21<0,F21,0))*-1 -> 0 | K21: =G21-H21+I21 -> 37090.505 | N21: 21 | O21: Mumba | R21: 4611.9389 | T21: =SUM(P21:S21) -> 4611.9389
A22: 21 | B22: Pamela | C22: =Shares!Y24 -> 14200 | D22: =Shareout!CF85 -> 20082.571 | E22: =Shareout!CF86 -> 19210.884 | F22: =D22-E22 -> 871.68675 | G22: =IF(F22>0,F22,0) -> 871.68675 | H22: =(IF(F22<0,F22,0))*-1 -> 0 | K22: =G22-H22+I22 -> 871.68675 | N22: 22 | O22: Mumbi | R22: 25176.849 | T22: =SUM(P22:S22) -> 25176.849
A23: 22 | B23: Schuller | C23: =Shares!Y25 -> 32200 | D23: =Shareout!CJ85 -> 48288.145 | E23: =Shareout!CJ86 -> 29574.557 | F23: =D23-E23 -> 18713.587 | G23: =IF(F23>0,F23,0) -> 18713.587 | H23: =(IF(F23<0,F23,0))*-1 -> 0 | K23: =G23-H23+I23 -> 18713.587 | N23: 23 | O23: Nyanyiwe | P23: 2212.1591 | T23: =SUM(P23:S23) -> 2212.1591
A24: 23 | B24: Shubart | C24: =Shares!Y26 -> 11000 | D24: =Shareout!CN85 -> 17250.526 | E24: =Shareout!CN86 -> 16577.725 | F24: =D24-E24 -> 672.80075 | G24: =IF(F24>0,F24,0) -> 672.80075 | H24: =(IF(F24<0,F24,0))*-1 -> 0 | K24: =I24 -> 0 | N24: 24 | O24: Pamela | S24: 1218.7284 | T24: =SUM(P24:S24) -> 1218.7284
A25: 24 | B25: Solomon | C25: =Shares!Y27 -> 9400 | D25: =Shareout!CR85 -> 14514.645 | E25: =Shareout!CR86 -> 0 | F25: =D25-E25 -> 14514.645 | G25: =IF(F25>0,F25,0) -> 14514.645 | H25: =(IF(F25<0,F25,0))*-1 -> 0 | K25: =G25-H25+I25 -> 14514.645 | N25: 26 | O25: Schuller | S25: 9310.2102 | T25: =SUM(P25:S25) -> 9310.2102
A26: 25 | B26: Tumelo | C26: =Shares!Y28 -> 200 | D26: =Shareout!CV85 -> 341.29221 | E26: =Shareout!CV86 -> 0 | F26: =D26-E26 -> 341.29221 | G26: =IF(F26>0,F26,0) -> 341.29221 | H26: =(IF(F26<0,F26,0))*-1 -> 0 | K26: =I26 -> 0 | N26: 27 | O26: Shubart | S26: 13138.549 | T26: =SUM(P26:S26) -> 13138.549
C27: =Shares!Y29 -> 27800 | D27: =Shareout!CZ85 -> 42115.686 | E27: =Shareout!CZ86 -> 0 | F27: =D27-E27 -> 42115.686 | H27: =(IF(F27<0,F27,0))*-1 -> 0 | N27: 28 | O27: Solomon | Q27: 10324.316 | T27: =SUM(P27:S27) -> 10324.316
B28: TOTAL | C28: =SUM(C2:C27) -> 459600 | D28: =SUM(D2:D27) -> 663565.44 | E28: =SUM(E2:E27) -> 333441.68 | F28: =SUM(F2:F27) -> 330123.76 | G28: =SUM(G2:G27) -> 367137.41 | H28: =SUM(H2:H27) -> 79129.334 | I28: =SUM(I2:I27) -> 0 | J28: =SUM(J2:J27) -> 0 | K28: =SUM(K2:K27) -> 292151.76 | N28: 29 | O28: Tumelo | P28: 1805.9499 | T28: =SUM(P28:S28) -> 1805.9499
N29: 30 | O29: Zeko | Q29: 25667.693 | T29: =SUM(P29:S29) -> 25667.693
P30: 49396.37 | Q30: 73316.73 | R30: 38585.614 | S30: 68760 | T30: =SUM(T3:T29) -> 214775.09
B31: Admins | D31: =Admins!L8 -> 341793.43 | N31: 333 | O31: Bal | P31: =P30-P2 -> 6233.8551 | Q31: =Q30-Q2-Q34 -> 947.2146 | R31: =R30-R2 -> 4646.7429 | S31: =S30-S2 -> 113.78757 | T31: =SUM(P31:S31) -> 11941.6
B32: Loans | D32: =H28 -> 79129.334 | Q32: =Q31-T34 -> -48008.034 | T32: =H28+T31 -> 91070.935
B33: Total | D33: =SUM(D31:H32) -> 420922.77 | T33: =H28+T31 -> 91070.935
B34: Share Out | D34: =G28 -> 367137.41 | Q34: 3342.0253 | T34: =T33-D35 -> 48955.249
B35: Insurance | D35: =F27 -> 42115.686
B36: Total ShareOut | D36: =D34+D35 -> 409253.1
B38: Excess | D38: =D33-D36 -> 11669.667

Sheet Shareout
B1: Abigail Mundia | F1: Abel Kunda | J1: Andrew | N1: Arthur | R1: Evans | W1: Jesper | AA1: Joshua | AE1: Kampamba | AI1: Karen Mwinga | AM1: Keji | AQ1: Khucwayo | AU1: Kombe | AY1: Kwibisa | BC1: Michael | BG1: Millie | BK1: Mukuma | BO1: Mumba | BS1: Mumbi | BW1: Mwenya | CA1: Nyanyiwe | CE1: Pamela | CI1: Schuller | CM1: Shubart | CQ1: Solomon | CU1: Tumelo | CY1: INSURANCE
C2: InfraCash | D2: Interest | G2: InfraCash | H2: Interest | K2: InfraCash | L2: Interest | O2: InfraCash | P2: Interest | S2: InfraCash | T2: Interest | X2: InfraCash | Y2: Interest | AB2: InfraCash | AC2: Interest | AF2: InfraCash | AG2: Interest | AJ2: InfraCash | AK2: Interest | AN2: InfraCash | AO2: Interest | AR2: InfraCash | AS2: Interest | AV2: InfraCash | AW2: Interest | AZ2: InfraCash | BA2: Interest | BD2: InfraCash | BE2: Interest | BH2: InfraCash | BI2: Interest | BL2: InfraCash | BM2: Interest | BP2: InfraCash | BQ2: Interest | BT2: InfraCash | BU2: Interest | BX2: InfraCash | BY2: Interest | CB2: InfraCash | CC2: Interest | CF2: InfraCash | CG2: Interest | CJ2: InfraCash | CK2: Interest | CN2: InfraCash | CO2: Interest | CR2: InfraCash | CS2: Interest | CV2: InfraCash | CW2: Interest | CZ2: InfraCash | DA2: Interest
B4: NOV | C4: =VLOOKUP(B1,INFRACASHshares2025,3,0) -> 200 | F4: NOV | G4: =VLOOKUP(F1,INFRACASHshares2025,3,0) -> 0 | J4: NOV | K4: =VLOOKUP(J1,INFRACASHshares2025,3,0) -> 1200 | N4: NOV | O4: =VLOOKUP(N1,INFRACASHshares2025,3,0) -> 200 | R4: NOV | S4: =VLOOKUP(R1,INFRACASHshares2025,3,0) -> 5000 | W4: NOV | X4: =VLOOKUP(W1,INFSHARES,3,0) -> 200 | AA4: NOV | AB4: =VLOOKUP(AA1,INFRACASHshares2025,3,0) -> 200 | AE4: NOV | AF4: =VLOOKUP(AE1,INFRACASHshares2025,3,0) -> 400 | AI4: NOV | AJ4: =VLOOKUP(AI1,INFRACASHshares2025,3,0) -> 1000 | AM4: NOV | AN4: =VLOOKUP(AM1,INFRACASHshares2025,3,0) -> 200 | AQ4: NOV | AR4: =VLOOKUP(AQ1,INFRACASHshares2025,3,0) -> 200 | AU4: NOV | AV4: =VLOOKUP(AU1,INFSHARES,3,0) -> 200 | AY4: NOV | AZ4: =VLOOKUP(AY1,INFSHARES,3,0) -> 5000 | BC4: NOV | BD4: =VLOOKUP(BC1,INFRACASHshares2025,3,0) -> 5000 | BG4: NOV | BH4: =VLOOKUP(BG1,INFRACASHshares2025,3,0) -> 600 | BK4: NOV | BL4: =VLOOKUP(BK1,INFRACASHshares2025,3,0) -> 3000 | BO4: NOV | BP4: =VLOOKUP(BO1,INFRACASHshares2025,3,0) -> 1000 | BS4: NOV | BT4: =VLOOKUP(BS1,INFRACASHshares2025,3,0) -> 1000 | BW4: NOV | BX4: =VLOOKUP(BW1,INFRACASHshares2025,3,0) -> 0 | CA4: NOV | CB4: =VLOOKUP(CA1,INFRACASHshares2025,3,0) -> 6000 | CE4: NOV | CF4: =VLOOKUP(CE1,INFRACASHshares2025,3,0) -> 200 | CI4: NOV | CJ4: =VLOOKUP(CI1,INFRACASHshares2025,3,0) -> 5000 | CM4: NOV | CN4: =VLOOKUP(CM1,INFRACASHshares2025,3,0) -> 5000 | CQ4: NOV | CR4: =VLOOKUP(CQ1,INFRACASHshares2025,3,0) -> 2000 | CU4: NOV | CV4: =VLOOKUP(CU1,INFRACASHshares2025,3,0) -> 200 | CY4: NOV | CZ4: =VLOOKUP(CY1,INFRACASHshares2025,3,0) -> 4600
B5: DEC | C5: =C4*1.1 -> 220 | D5: =C4*0.1 -> 20 | F5: DEC | G5: =G4*1.1 -> 0 | H5: =G4*0.1 -> 0 | J5: DEC | K5: =K4*1.1 -> 1320 | L5: =K4*0.1 -> 120 | N5: DEC | O5: =O4*1.1 -> 220 | P5: =O4*0.1 -> 20 | R5: DEC | S5: =S4*1.1 -> 5500 | T5: =S4*0.1 -> 500 | W5: DEC | X5: =X4*1.1 -> 220 | Y5: =X4*0.1 -> 20 | AA5: DEC | AB5: =AB4*1.1 -> 220 | AC5: =AB4*0.1 -> 20 | AE5: DEC | AF5: =AF4*1.1 -> 440 | AG5: =AF4*0.1 -> 40 | AI5: DEC | AJ5: =AJ4*1.1 -> 1100 | AK5: =AJ4*0.1 -> 100 | AM5: DEC | AN5: =AN4*1.1 -> 220 | AO5: =AN4*0.1 -> 20 | AQ5: DEC | AR5: =AR4*1.1 -> 220 | AS5: =AR4*0.1 -> 20 | AU5: DEC | AV5: =AV4*1.1 -> 220 | AW5: =AV4*0.1 -> 20 | AY5: DEC | AZ5: =AZ4*1.1 -> 5500 | BA5: =AZ4*0.1 -> 500 | BC5: DEC | BD5: =BD4*1.1 -> 5500 | BE5: =BD4*0.1 -> 500 | BG5: DEC | BH5: =BH4*1.1 -> 660 | BI5: =BH4*0.1 -> 60 | BK5: DEC | BL5: =BL4*1.1 -> 3300 | BM5: =BL4*0.1 -> 300 | BO5: DEC | BP5: =BP4*1.1 -> 1100 | BQ5: =BP4*0.1 -> 100 | BS5: DEC | BT5: =BT4*1.1 -> 1100 | BU5: =BT4*0.1 -> 100 | BW5: DEC | BX5: =BX4*1.1 -> 0 | BY5: =BX4*0.1 -> 0 | CA5: DEC | CB5: =CB4*1.1 -> 6600 | CC5: =CB4*0.1 -> 600 | CE5: DEC | CF5: =CF4*1.1 -> 220 | CG5: =CF4*0.1 -> 20 | CI5: DEC | CJ5: =CJ4*1.1 -> 5500 | CK5: =CJ4*0.1 -> 500 | CM5: DEC | CN5: =CN4*1.1 -> 5500 | CO5: =CN4*0.1 -> 500 | CQ5: DEC | CR5: =CR4*1.1 -> 2200 | CS5: =CR4*0.1 -> 200 | CU5: DEC | CV5: =CV4*1.1 -> 220 | CW5: =CV4*0.1 -> 20 | CY5: DEC | CZ5: =CZ4*1.1 -> 5060 | DA5: =CZ4*0.1 -> 460
B6: JAN | C6: =C5*1.05 -> 231 | D6: =C5*0.05 -> 11 | F6: JAN | G6: =G5*1.05 -> 0 | H6: =G5*0.05 -> 0 | J6: JAN | K6: =K5*1.05 -> 1386 | L6: =K5*0.05 -> 66 | N6: JAN | O6: =O5*1.05 -> 231 | P6: =O5*0.05 -> 11 | R6: JAN | S6: =S5*1.05 -> 5775 | T6: =S5*0.05 -> 275 | W6: JAN | X6: =X5*1.05 -> 231 | Y6: =X5*0.05 -> 11 | AA6: JAN | AB6: =AB5*1.05 -> 231 | AC6: =AB5*0.05 -> 11 | AE6: JAN | AF6: =AF5*1.05 -> 462 | AG6: =AF5*0.05 -> 22 | AI6: JAN | AJ6: =AJ5*1.05 -> 1155 | AK6: =AJ5*0.05 -> 55 | AM6: JAN | AN6: =AN5*1.05 -> 231 | AO6: =AN5*0.05 -> 11 | AQ6: JAN | AR6: =AR5*1.05 -> 231 | AS6: =AR5*0.05 -> 11 | AU6: JAN | AV6: =AV5*1.05 -> 231 | AW6: =AV5*0.05 -> 11 | AY6: JAN | AZ6: =AZ5*1.05 -> 5775 | BA6: =AZ5*0.05 -> 275 | BC6: JAN | BD6: =BD5*1.05 -> 5775 | BE6: =BD5*0.05 -> 275 | BG6: JAN | BH6: =BH5*1.05 -> 693 | BI6: =BH5*0.05 -> 33 | BK6: JAN | BL6: =BL5*1.05 -> 3465 | BM6: =BL5*0.05 -> 165 | BO6: JAN | BP6: =BP5*1.05 -> 1155 | BQ6: =BP5*0.05 -> 55 | BS6: JAN | BT6: =BT5*1.05 -> 1155 | BU6: =BT5*0.05 -> 55 | BW6: JAN | BX6: =BX5*1.05 -> 0 | BY6: =BX5*0.05 -> 0 | CA6: JAN | CB6: =CB5*1.05 -> 6930 | CC6: =CB5*0.05 -> 330 | CE6: JAN | CF6: =CF5*1.05 -> 231 | CG6: =CF5*0.05 -> 11 | CI6: JAN | CJ6: =CJ5*1.05 -> 5775 | CK6: =CJ5*0.05 -> 275 | CM6: JAN | CN6: =CN5*1.05 -> 5775 | CO6: =CN5*0.05 -> 275 | CQ6: JAN | CR6: =CR5*1.05 -> 2310 | CS6: =CR5*0.05 -> 110 | CU6: JAN | CV6: =CV5*1.05 -> 231 | CW6: =CV5*0.05 -> 11 | CY6: JAN | CZ6: =CZ5*1.05 -> 5313 | DA6: =CZ5*0.05 -> 253
B7: FEB | C7: =C6*1.05 -> 242.55 | D7: =C6*0.05 -> 11.55 | F7: FEB | G7: =G6*1.05 -> 0 | H7: =G6*0.05 -> 0 | J7: FEB | K7: =K6*1.05 -> 1455.3 | L7: =K6*0.05 -> 69.3 | N7: FEB | O7: =O6*1.05 -> 242.55 | P7: =O6*0.05 -> 11.55 | R7: FEB | S7: =S6*1.05 -> 6063.75 | T7: =S6*0.05 -> 288.75 | W7: FEB | X7: =X6*1.05 -> 242.55 | Y7: =X6*0.05 -> 11.55 | AA7: FEB | AB7: =AB6*1.05 -> 242.55 | AC7: =AB6*0.05 -> 11.55 | AE7: FEB | AF7: =AF6*1.05 -> 485.1 | AG7: =AF6*0.05 -> 23.1 | AI7: FEB | AJ7: =AJ6*1.05 -> 1212.75 | AK7: =AJ6*0.05 -> 57.75 | AM7: FEB | AN7: =AN6*1.05 -> 242.55 | AO7: =AN6*0.05 -> 11.55 | AQ7: FEB | AR7: =AR6*1.05 -> 242.55 | AS7: =AR6*0.05 -> 11.55 | AU7: FEB | AV7: =AV6*1.05 -> 242.55 | AW7: =AV6*0.05 -> 11.55 | AY7: FEB | AZ7: =AZ6*1.05 -> 6063.75 | BA7: =AZ6*0.05 -> 288.75 | BC7: FEB | BD7: =BD6*1.05 -> 6063.75 | BE7: =BD6*0.05 -> 288.75 | BG7: FEB | BH7: =BH6*1.05 -> 727.65 | BI7: =BH6*0.05 -> 34.65 | BK7: FEB | BL7: =BL6*1.05 -> 3638.25 | BM7: =BL6*0.05 -> 173.25 | BO7: FEB | BP7: =BP6*1.05 -> 1212.75 | BQ7: =BP6*0.05 -> 57.75 | BS7: FEB | BT7: =BT6*1.05 -> 1212.75 | BU7: =BT6*0.05 -> 57.75 | BW7: FEB | BX7: =BX6*1.05 -> 0 | BY7: =BX6*0.05 -> 0 | CA7: FEB | CB7: =CB6*1.05 -> 7276.5 | CC7: =CB6*0.05 -> 346.5 | CE7: FEB | CF7: =CF6*1.05 -> 242.55 | CG7: =CF6*0.05 -> 11.55 | CI7: FEB | CJ7: =CJ6*1.05 -> 6063.75 | CK7: =CJ6*0.05 -> 288.75 | CM7: FEB | CN7: =CN6*1.05 -> 6063.75 | CO7: =CN6*0.05 -> 288.75 | CQ7: FEB | CR7: =CR6*1.05 -> 2425.5 | CS7: =CR6*0.05 -> 115.5 | CU7: FEB | CV7: =CV6*1.05 -> 242.55 | CW7: =CV6*0.05 -> 11.55 | CY7: FEB | CZ7: =CZ6*1.05 -> 5578.65 | DA7: =CZ6*0.05 -> 265.65
B8: MAR | C8: =C7*1.05 -> 254.6775 | D8: =C7*0.05 -> 12.1275 | F8: MAR | G8: =G7*1.05 -> 0 | H8: =G7*0.05 -> 0 | J8: MAR | K8: =K7*1.05 -> 1528.065 | L8: =K7*0.05 -> 72.765 | N8: MAR | O8: =O7*1.05 -> 254.6775 | P8: =O7*0.05 -> 12.1275 | R8: MAR | S8: =S7*1.05 -> 6366.9375 | T8: =S7*0.05 -> 303.1875 | W8: MAR | X8: =X7*1.05 -> 254.6775 | Y8: =X7*0.05 -> 12.1275 | AA8: MAR | AB8: =AB7*1.05 -> 254.6775 | AC8: =AB7*0.05 -> 12.1275 | AE8: MAR | AF8: =AF7*1.05 -> 509.355 | AG8: =AF7*0.05 -> 24.255 | AI8: MAR | AJ8: =AJ7*1.05 -> 1273.3875 | AK8: =AJ7*0.05 -> 60.6375 | AM8: MAR | AN8: =AN7*1.05 -> 254.6775 | AO8: =AN7*0.05 -> 12.1275 | AQ8: MAR | AR8: =AR7*1.05 -> 254.6775 | AS8: =AR7*0.05 -> 12.1275 | AU8: MAR | AV8: =AV7*1.05 -> 254.6775 | AW8: =AV7*0.05 -> 12.1275 | AY8: MAR | AZ8: =AZ7*1.05 -> 6366.9375 | BA8: =AZ7*0.05 -> 303.1875 | BC8: MAR | BD8: =BD7*1.05 -> 6366.9375 | BE8: =BD7*0.05 -> 303.1875 | BG8: MAR | BH8: =BH7*1.05 -> 764.0325 | BI8: =BH7*0.05 -> 36.3825 | BK8: MAR | BL8: =BL7*1.05 -> 3820.1625 | BM8: =BL7*0.05 -> 181.9125 | BO8: MAR | BP8: =BP7*1.05 -> 1273.3875 | BQ8: =BP7*0.05 -> 60.6375 | BS8: MAR | BT8: =BT7*1.05 -> 1273.3875 | BU8: =BT7*0.05 -> 60.6375 | BW8: MAR | BX8: =BX7*1.05 -> 0 | BY8: =BX7*0.05 -> 0 | CA8: MAR | CB8: =CB7*1.05 -> 7640.325 | CC8: =CB7*0.05 -> 363.825 | CE8: MAR | CF8: =CF7*1.05 -> 254.6775 | CG8: =CF7*0.05 -> 12.1275 | CI8: MAR | CJ8: =CJ7*1.05 -> 6366.9375 | CK8: =CJ7*0.05 -> 303.1875 | CM8: MAR | CN8: =CN7*1.05 -> 6366.9375 | CO8: =CN7*0.05 -> 303.1875 | CQ8: MAR | CR8: =CR7*1.05 -> 2546.775 | CS8: =CR7*0.05 -> 121.275 | CU8: MAR | CV8: =CV7*1.05 -> 254.6775 | CW8: =CV7*0.05 -> 12.1275 | CY8: MAR | CZ8: =CZ7*1.05 -> 5857.5825 | DA8: =CZ7*0.05 -> 278.9325
B9: APRIL | C9: =C8*1.05 -> 267.41138 | D9: =C8*0.05 -> 12.733875 | F9: APRIL | G9: =G8*1.05 -> 0 | H9: =G8*0.05 -> 0 | J9: APRIL | K9: =K8*1.05 -> 1604.4683 | L9: =K8*0.05 -> 76.40325 | N9: APRIL | O9: =O8*1.05 -> 267.41138 | P9: =O8*0.05 -> 12.733875 | R9: APRIL | S9: =S8*1.05 -> 6685.2844 | T9: =S8*0.05 -> 318.34688 | W9: APRIL | X9: =X8*1.05 -> 267.41138 | Y9: =X8*0.05 -> 12.733875 | AA9: APRIL | AB9: =AB8*1.05 -> 267.41138 | AC9: =AB8*0.05 -> 12.733875 | AE9: APRIL | AF9: =AF8*1.05 -> 534.82275 | AG9: =AF8*0.05 -> 25.46775 | AI9: APRIL | AJ9: =AJ8*1.05 -> 1337.0569 | AK9: =AJ8*0.05 -> 63.669375 | AM9: APRIL | AN9: =AN8*1.05 -> 267.41138 | AO9: =AN8*0.05 -> 12.733875 | AQ9: APRIL | AR9: =AR8*1.05 -> 267.41138 | AS9: =AR8*0.05 -> 12.733875 | AU9: APRIL | AV9: =AV8*1.05 -> 267.41138 | AW9: =AV8*0.05 -> 12.733875 | AY9: APRIL | AZ9: =AZ8*1.05 -> 6685.2844 | BA9: =AZ8*0.05 -> 318.34688 | BC9: APRIL | BD9: =BD8*1.05 -> 6685.2844 | BE9: =BD8*0.05 -> 318.34688 | BG9: APRIL | BH9: =BH8*1.05 -> 802.23413 | BI9: =BH8*0.05 -> 38.201625 | BK9: APRIL | BL9: =BL8*1.05 -> 4011.1706 | BM9: =BL8*0.05 -> 191.00813 | BO9: APRIL | BP9: =BP8*1.05 -> 1337.0569 | BQ9: =BP8*0.05 -> 63.669375 | BS9: APRIL | BT9: =BT8*1.05 -> 1337.0569 | BU9: =BT8*0.05 -> 63.669375 | BW9: APRIL | BX9: =BX8*1.05 -> 0 | BY9: =BX8*0.05 -> 0 | CA9: APRIL | CB9: =CB8*1.05 -> 8022.3413 | CC9: =CB8*0.05 -> 382.01625 | CE9: APRIL | CF9: =CF8*1.05 -> 267.41138 | CG9: =CF8*0.05 -> 12.733875 | CI9: APRIL | CJ9: =CJ8*1.05 -> 6685.2844 | CK9: =CJ8*0.05 -> 318.34688 | CM9: APRIL | CN9: =CN8*1.05 -> 6685.2844 | CO9: =CN8*0.05 -> 318.34688 | CQ9: APRIL | CR9: =CR8*1.05 -> 2674.1137 | CS9: =CR8*0.05 -> 127.33875 | CU9: APRIL | CV9: =CV8*1.05 -> 267.41138 | CW9: =CV8*0.05 -> 12.733875 | CY9: APRIL | CZ9: =CZ8*1.05 -> 6150.4616 | DA9: =CZ8*0.05 -> 292.87913
B10: MAY | C10: =C9*1.05 -> 280.78194 | D10: =C9*0.05 -> 13.370569 | F10: MAY | G10: =G9*1.05 -> 0 | H10: =G9*0.05 -> 0 | J10: MAY | K10: =K9*1.05 -> 1684.6917 | L10: =K9*0.05 -> 80.223413 | N10: MAY | O10: =O9*1.05 -> 280.78194 | P10: =O9*0.05 -> 13.370569 | R10: MAY | S10: =S9*1.05 -> 7019.5486 | T10: =S9*0.05 -> 334.26422 | W10: MAY | X10: =X9*1.05 -> 280.78194 | Y10: =X9*0.05 -> 13.370569 | AA10: MAY | AB10: =AB9*1.05 -> 280.78194 | AC10: =AB9*0.05 -> 13.370569 | AE10: MAY | AF10: =AF9*1.05 -> 561.56389 | AG10: =AF9*0.05 -> 26.741138 | AI10: MAY | AJ10: =AJ9*1.05 -> 1403.9097 | AK10: =AJ9*0.05 -> 66.852844 | AM10: MAY | AN10: =AN9*1.05 -> 280.78194 | AO10: =AN9*0.05 -> 13.370569 | AQ10: MAY | AR10: =AR9*1.05 -> 280.78194 | AS10: =AR9*0.05 -> 13.370569 | AU10: MAY | AV10: =AV9*1.05 -> 280.78194 | AW10: =AV9*0.05 -> 13.370569 | AY10: MAY | AZ10: =AZ9*1.05 -> 7019.5486 | BA10: =AZ9*0.05 -> 334.26422 | BC10: MAY | BD10: =BD9*1.05 -> 7019.5486 | BE10: =BD9*0.05 -> 334.26422 | BG10: MAY | BH10: =BH9*1.05 -> 842.34583 | BI10: =BH9*0.05 -> 40.111706 | BK10: MAY | BL10: =BL9*1.05 -> 4211.7292 | BM10: =BL9*0.05 -> 200.55853 | BO10: MAY | BP10: =BP9*1.05 -> 1403.9097 | BQ10: =BP9*0.05 -> 66.852844 | BS10: MAY | BT10: =BT9*1.05 -> 1403.9097 | BU10: =BT9*0.05 -> 66.852844 | BW10: MAY | BX10: =BX9*1.05 -> 0 | BY10: =BX9*0.05 -> 0 | CA10: MAY | CB10: =CB9*1.05 -> 8423.4583 | CC10: =CB9*0.05 -> 401.11706 | CE10: MAY | CF10: =CF9*1.05 -> 280.78194 | CG10: =CF9*0.05 -> 13.370569 | CI10: MAY | CJ10: =CJ9*1.05 -> 7019.5486 | CK10: =CJ9*0.05 -> 334.26422 | CM10: MAY | CN10: =CN9*1.05 -> 7019.5486 | CO10: =CN9*0.05 -> 334.26422 | CQ10: MAY | CR10: =CR9*1.05 -> 2807.8194 | CS10: =CR9*0.05 -> 133.70569 | CU10: MAY | CV10: =CV9*1.05 -> 280.78194 | CW10: =CV9*0.05 -> 13.370569 | CY10: MAY | CZ10: =CZ9*1.05 -> 6457.9847 | DA10: =CZ9*0.05 -> 307.52308
B11: JUNE | C11: =C10*1.05 -> 294.82104 | D11: =C10*0.05 -> 14.039097 | F11: JUNE | G11: =G10*1.05 -> 0 | H11: =G10*0.05 -> 0 | J11: JUNE | K11: =K10*1.05 -> 1768.9262 | L11: =K10*0.05 -> 84.234583 | N11: JUNE | O11: =O10*1.05 -> 294.82104 | P11: =O10*0.05 -> 14.039097 | R11: JUNE | S11: =S10*1.05 -> 7370.526 | T11: =S10*0.05 -> 350.97743 | W11: JUNE | X11: =X10*1.05 -> 294.82104 | Y11: =X10*0.05 -> 14.039097 | AA11: JUNE | AB11: =AB10*1.05 -> 294.82104 | AC11: =AB10*0.05 -> 14.039097 | AE11: JUNE | AF11: =AF10*1.05 -> 589.64208 | AG11: =AF10*0.05 -> 28.078194 | AI11: JUNE | AJ11: =AJ10*1.05 -> 1474.1052 | AK11: =AJ10*0.05 -> 70.195486 | AM11: JUNE | AN11: =AN10*1.05 -> 294.82104 | AO11: =AN10*0.05 -> 14.039097 | AQ11: JUNE | AR11: =AR10*1.05 -> 294.82104 | AS11: =AR10*0.05 -> 14.039097 | AU11: JUNE | AV11: =AV10*1.05 -> 294.82104 | AW11: =AV10*0.05 -> 14.039097 | AY11: JUNE | AZ11: =AZ10*1.05 -> 7370.526 | BA11: =AZ10*0.05 -> 350.97743 | BC11: JUNE | BD11: =BD10*1.05 -> 7370.526 | BE11: =BD10*0.05 -> 350.97743 | BG11: JUNE | BH11: =BH10*1.05 -> 884.46312 | BI11: =BH10*0.05 -> 42.117292 | BK11: JUNE | BL11: =BL10*1.05 -> 4422.3156 | BM11: =BL10*0.05 -> 210.58646 | BO11: JUNE | BP11: =BP10*1.05 -> 1474.1052 | BQ11: =BP10*0.05 -> 70.195486 | BS11: JUNE | BT11: =BT10*1.05 -> 1474.1052 | BU11: =BT10*0.05 -> 70.195486 | BW11: JUNE | BX11: =BX10*1.05 -> 0 | BY11: =BX10*0.05 -> 0 | CA11: JUNE | CB11: =CB10*1.05 -> 8844.6312 | CC11: =CB10*0.05 -> 421.17292 | CE11: JUNE | CF11: =CF10*1.05 -> 294.82104 | CG11: =CF10*0.05 -> 14.039097 | CI11: JUNE | CJ11: =CJ10*1.05 -> 7370.526 | CK11: =CJ10*0.05 -> 350.97743 | CM11: JUNE | CN11: =CN10*1.05 -> 7370.526 | CO11: =CN10*0.05 -> 350.97743 | CQ11: JUNE | CR11: =CR10*1.05 -> 2948.2104 | CS11: =CR10*0.05 -> 140.39097 | CU11: JUNE | CV11: =CV10*1.05 -> 294.82104 | CW11: =CV10*0.05 -> 14.039097 | CY11: JUNE | CZ11: =CZ10*1.05 -> 6780.8839 | DA11: =CZ10*0.05 -> 322.89924
B12: JULY | C12: =C11*1.05 -> 309.56209 | D12: =C11*0.05 -> 14.741052 | F12: JULY | G12: =G11*1.05 -> 0 | H12: =G11*0.05 -> 0 | J12: JULY | K12: =K11*1.05 -> 1857.3726 | L12: =K11*0.05 -> 88.446312 | N12: JULY | O12: =O11*1.05 -> 309.56209 | P12: =O11*0.05 -> 14.741052 | R12: JULY | S12: =S11*1.05 -> 7739.0523 | T12: =S11*0.05 -> 368.5263 | W12: JULY | X12: =X11*1.05 -> 309.56209 | Y12: =X11*0.05 -> 14.741052 | AA12: JULY | AB12: =AB11*1.05 -> 309.56209 | AC12: =AB11*0.05 -> 14.741052 | AE12: JULY | AF12: =AF11*1.05 -> 619.12419 | AG12: =AF11*0.05 -> 29.482104 | AI12: JULY | AJ12: =AJ11*1.05 -> 1547.8105 | AK12: =AJ11*0.05 -> 73.70526 | AM12: JULY | AN12: =AN11*1.05 -> 309.56209 | AO12: =AN11*0.05 -> 14.741052 | AQ12: JULY | AR12: =AR11*1.05 -> 309.56209 | AS12: =AR11*0.05 -> 14.741052 | AU12: JULY | AV12: =AV11*1.05 -> 309.56209 | AW12: =AV11*0.05 -> 14.741052 | AY12: JULY | AZ12: =AZ11*1.05 -> 7739.0523 | BA12: =AZ11*0.05 -> 368.5263 | BC12: JULY | BD12: =BD11*1.05 -> 7739.0523 | BE12: =BD11*0.05 -> 368.5263 | BG12: JULY | BH12: =BH11*1.05 -> 928.68628 | BI12: =BH11*0.05 -> 44.223156 | BK12: JULY | BL12: =BL11*1.05 -> 4643.4314 | BM12: =BL11*0.05 -> 221.11578 | BO12: JULY | BP12: =BP11*1.05 -> 1547.8105 | BQ12: =BP11*0.05 -> 73.70526 | BS12: JULY | BT12: =BT11*1.05 -> 1547.8105 | BU12: =BT11*0.05 -> 73.70526 | BW12: JULY | BX12: =BX11*1.05 -> 0 | BY12: =BX11*0.05 -> 0 | CA12: JULY | CB12: =CB11*1.05 -> 9286.8628 | CC12: =CB11*0.05 -> 442.23156 | CE12: JULY | CF12: =CF11*1.05 -> 309.56209 | CG12: =CF11*0.05 -> 14.741052 | CI12: JULY | CJ12: =CJ11*1.05 -> 7739.0523 | CK12: =CJ11*0.05 -> 368.5263 | CM12: JULY | CN12: =CN11*1.05 -> 7739.0523 | CO12: =CN11*0.05 -> 368.5263 | CQ12: JULY | CR12: =CR11*1.05 -> 3095.6209 | CS12: =CR11*0.05 -> 147.41052 | CU12: JULY | CV12: =CV11*1.05 -> 309.56209 | CW12: =CV11*0.05 -> 14.741052 | CY12: JULY | CZ12: =CZ11*1.05 -> 7119.9281 | DA12: =CZ11*0.05 -> 339.0442
B13: AUG | C13: =C12*1.05 -> 325.0402 | D13: =C12*0.05 -> 15.478105 | F13: AUG | G13: =G12*1.05 -> 0 | H13: =G12*0.05 -> 0 | J13: AUG | K13: =K12*1.05 -> 1950.2412 | L13: =K12*0.05 -> 92.868628 | N13: AUG | O13: =O12*1.05 -> 325.0402 | P13: =O12*0.05 -> 15.478105 | R13: AUG | S13: =S12*1.05 -> 8126.0049 | T13: =S12*0.05 -> 386.95262 | W13: AUG | X13: =X12*1.05 -> 325.0402 | Y13: =X12*0.05 -> 15.478105 | AA13: AUG | AB13: =AB12*1.05 -> 325.0402 | AC13: =AB12*0.05 -> 15.478105 | AE13: AUG | AF13: =AF12*1.05 -> 650.0804 | AG13: =AF12*0.05 -> 30.956209 | AI13: AUG | AJ13: =AJ12*1.05 -> 1625.201 | AK13: =AJ12*0.05 -> 77.390523 | AM13: AUG | AN13: =AN12*1.05 -> 325.0402 | AO13: =AN12*0.05 -> 15.478105 | AQ13: AUG | AR13: =AR12*1.05 -> 325.0402 | AS13: =AR12*0.05 -> 15.478105 | AU13: AUG | AV13: =AV12*1.05 -> 325.0402 | AW13: =AV12*0.05 -> 15.478105 | AY13: AUG | AZ13: =AZ12*1.05 -> 8126.0049 | BA13: =AZ12*0.05 -> 386.95262 | BC13: AUG | BD13: =BD12*1.05 -> 8126.0049 | BE13: =BD12*0.05 -> 386.95262 | BG13: AUG | BH13: =BH12*1.05 -> 975.12059 | BI13: =BH12*0.05 -> 46.434314 | BK13: AUG | BL13: =BL12*1.05 -> 4875.603 | BM13: =BL12*0.05 -> 232.17157 | BO13: AUG | BP13: =BP12*1.05 -> 1625.201 | BQ13: =BP12*0.05 -> 77.390523 | BS13: AUG | BT13: =BT12*1.05 -> 1625.201 | BU13: =BT12*0.05 -> 77.390523 | BW13: AUG | BX13: =BX12*1.05 -> 0 | BY13: =BX12*0.05 -> 0 | CA13: AUG | CB13: =CB12*1.05 -> 9751.2059 | CC13: =CB12*0.05 -> 464.34314 | CE13: AUG | CF13: =CF12*1.05 -> 325.0402 | CG13: =CF12*0.05 -> 15.478105 | CI13: AUG | CJ13: =CJ12*1.05 -> 8126.0049 | CK13: =CJ12*0.05 -> 386.95262 | CM13: AUG | CN13: =CN12*1.05 -> 8126.0049 | CO13: =CN12*0.05 -> 386.95262 | CQ13: AUG | CR13: =CR12*1.05 -> 3250.402 | CS13: =CR12*0.05 -> 154.78105 | CU13: AUG | CV13: =CV12*1.05 -> 325.0402 | CW13: =CV12*0.05 -> 15.478105 | CY13: AUG | CZ13: =CZ12*1.05 -> 7475.9245 | DA13: =CZ12*0.05 -> 355.99641
B14: SEP | C14: =C13*1.05 -> 341.29221 | D14: =C13*0.05 -> 16.25201 | F14: SEP | G14: =G13*1.05 -> 0 | H14: =G13*0.05 -> 0 | J14: SEP | K14: =K13*1.05 -> 2047.7532 | L14: =K13*0.05 -> 97.512059 | N14: SEP | O14: =O13*1.05 -> 341.29221 | P14: =O13*0.05 -> 16.25201 | R14: SEP | S14: =S13*1.05 -> 8532.3052 | T14: =S13*0.05 -> 406.30025 | W14: SEP | X14: =X13*1.05 -> 341.29221 | Y14: =X13*0.05 -> 16.25201 | AA14: SEP | AB14: =AB13*1.05 -> 341.29221 | AC14: =AB13*0.05 -> 16.25201 | AE14: SEP | AF14: =AF13*1.05 -> 682.58442 | AG14: =AF13*0.05 -> 32.50402 | AI14: SEP | AJ14: =AJ13*1.05 -> 1706.461 | AK14: =AJ13*0.05 -> 81.260049 | AM14: SEP | AN14: =AN13*1.05 -> 341.29221 | AO14: =AN13*0.05 -> 16.25201 | AQ14: SEP | AR14: =AR13*1.05 -> 341.29221 | AS14: =AR13*0.05 -> 16.25201 | AU14: SEP | AV14: =AV13*1.05 -> 341.29221 | AW14: =AV13*0.05 -> 16.25201 | AY14: SEP | AZ14: =AZ13*1.05 -> 8532.3052 | BA14: =AZ13*0.05 -> 406.30025 | BC14: SEP | BD14: =BD13*1.05 -> 8532.3052 | BE14: =BD13*0.05 -> 406.30025 | BG14: SEP | BH14: =BH13*1.05 -> 1023.8766 | BI14: =BH13*0.05 -> 48.75603 | BK14: SEP | BL14: =BL13*1.05 -> 5119.3831 | BM14: =BL13*0.05 -> 243.78015 | BO14: SEP | BP14: =BP13*1.05 -> 1706.461 | BQ14: =BP13*0.05 -> 81.260049 | BS14: SEP | BT14: =BT13*1.05 -> 1706.461 | BU14: =BT13*0.05 -> 81.260049 | BW14: SEP | BX14: =BX13*1.05 -> 0 | BY14: =BX13*0.05 -> 0 | CA14: SEP | CB14: =CB13*1.05 -> 10238.766 | CC14: =CB13*0.05 -> 487.5603 | CE14: SEP | CF14: =CF13*1.05 -> 341.29221 | CG14: =CF13*0.05 -> 16.25201 | CI14: SEP | CJ14: =CJ13*1.05 -> 8532.3052 | CK14: =CJ13*0.05 -> 406.30025 | CM14: SEP | CN14: =CN13*1.05 -> 8532.3052 | CO14: =CN13*0.05 -> 406.30025 | CQ14: SEP | CR14: =CR13*1.05 -> 3412.9221 | CS14: =CR13*0.05 -> 162.5201 | CU14: SEP | CV14: =CV13*1.05 -> 341.29221 | CW14: =CV13*0.05 -> 16.25201 | CY14: SEP | CZ14: =CZ13*1.05 -> 7849.7208 | DA14: =CZ13*0.05 -> 373.79623
B16: DEC | C16: =VLOOKUP(B1,INFSHARES,5,0) -> 15000 | F16: DEC | G16: =VLOOKUP(F1,INFSHARES,5,0) -> 0 | J16: DEC | K16: =VLOOKUP(J1,INFSHARES,5,0) -> 200 | N16: DEC | O16: =VLOOKUP(N1,INFSHARES,5,0) -> 200 | R16: DEC | S16: =VLOOKUP(R1,INFSHARES,5,0) -> 200 | W16: DEC | X16: =VLOOKUP(W1,INFSHARES,5,0) -> 200 | AA16: DEC | AB16: =VLOOKUP(AA1,INFSHARES,5,0) -> 200 | AE16: DEC | AF16: =VLOOKUP(AE1,INFSHARES,5,0) -> 400 | AI16: DEC | AJ16: =VLOOKUP(AI1,INFSHARES,5,0) -> 200 | AM16: DEC | AN16: =VLOOKUP(AM1,INFSHARES,5,0) -> 200 | AQ16: DEC | AR16: =VLOOKUP(AQ1,INFSHARES,5,0) -> 400 | AU16: DEC | AV16: =VLOOKUP(AU1,INFSHARES,5,0) -> 200 | AY16: DEC | AZ16: =VLOOKUP(AY1,INFSHARES,5,0) -> 200 | BC16: DEC | BD16: =VLOOKUP(BC1,INFSHARES,5,0) -> 5000 | BG16: DEC | BH16: =VLOOKUP(BG1,INFSHARES,5,0) -> 200 | BK16: DEC | BL16: =VLOOKUP(BK1,INFSHARES,5,0) -> 3000 | BO16: DEC | BP16: =VLOOKUP(BO1,INFSHARES,5,0) -> 1000 | BS16: DEC | BT16: =VLOOKUP(BS1,INFSHARES,5,0) -> 2000 | BW16: DEC | BX16: =VLOOKUP(BW1,INFSHARES,5,0) -> 1000 | CA16: DEC | CB16: =VLOOKUP(CA1,INFSHARES,5,0) -> 10000 | CE16: DEC | CF16: =VLOOKUP(CE1,INFSHARES,5,0) -> 1000 | CI16: DEC | CJ16: =VLOOKUP(CI1,INFSHARES,5,0) -> 10000 | CM16: DEC | CN16: =VLOOKUP(CM1,INFSHARES,5,0) -> 1000 | CQ16: DEC | CR16: =VLOOKUP(CQ1,INFSHARES,5,0) -> 4000 | CU16: DEC | CV16: =VLOOKUP(CU1,INFSHARES,5,0) -> 0 | CY16: DEC | CZ16: =VLOOKUP(CY1,INFRACASHshares2025,5,0) -> 4600
B17: JAN | C17: =C16*1.1 -> 16500 | D17: =C16*0.1 -> 1500 | F17: JAN | G17: =G16*1.1 -> 0 | H17: =G16*0.1 -> 0 | J17: JAN | K17: =K16*1.1 -> 220 | L17: =K16*0.1 -> 20 | N17: JAN | O17: =O16*1.1 -> 220 | P17: =O16*0.1 -> 20 | R17: JAN | S17: =S16*1.1 -> 220 | T17: =S16*0.1 -> 20 | W17: JAN | X17: =X16*1.1 -> 220 | Y17: =X16*0.1 -> 20 | AA17: JAN | AB17: =AB16*1.1 -> 220 | AC17: =AB16*0.1 -> 20 | AE17: JAN | AF17: =AF16*1.1 -> 440 | AG17: =AF16*0.1 -> 40 | AI17: JAN | AJ17: =AJ16*1.1 -> 220 | AK17: =AJ16*0.1 -> 20 | AM17: JAN | AN17: =AN16*1.1 -> 220 | AO17: =AN16*0.1 -> 20 | AQ17: JAN | AR17: =AR16*1.1 -> 440 | AS17: =AR16*0.1 -> 40 | AU17: JAN | AV17: =AV16*1.1 -> 220 | AW17: =AV16*0.1 -> 20 | AY17: JAN | AZ17: =AZ16*1.1 -> 220 | BA17: =AZ16*0.1 -> 20 | BC17: JAN | BD17: =BD16*1.1 -> 5500 | BE17: =BD16*0.1 -> 500 | BG17: JAN | BH17: =BH16*1.1 -> 220 | BI17: =BH16*0.1 -> 20 | BK17: JAN | BL17: =BL16*1.1 -> 3300 | BM17: =BL16*0.1 -> 300 | BO17: JAN | BP17: =BP16*1.1 -> 1100 | BQ17: =BP16*0.1 -> 100 | BS17: JAN | BT17: =BT16*1.1 -> 2200 | BU17: =BT16*0.1 -> 200 | BW17: JAN | BX17: =BX16*1.1 -> 1100 | BY17: =BX16*0.1 -> 100 | CA17: JAN | CB17: =CB16*1.1 -> 11000 | CC17: =CB16*0.1 -> 1000 | CE17: JAN | CF17: =CF16*1.1 -> 1100 | CG17: =CF16*0.1 -> 100 | CI17: JAN | CJ17: =CJ16*1.1 -> 11000 | CK17: =CJ16*0.1 -> 1000 | CM17: JAN | CN17: =CN16*1.1 -> 1100 | CO17: =CN16*0.1 -> 100 | CQ17: JAN | CR17: =CR16*1.1 -> 4400 | CS17: =CR16*0.1 -> 400 | CU17: JAN | CV17: =CV16*1.1 -> 0 | CW17: =CV16*0.1 -> 0 | CY17: JAN | CZ17: =CZ16*1.1 -> 5060 | DA17: =CZ16*0.1 -> 460
B18: FEB | C18: =C17*1.05 -> 17325 | D18: =C17*0.05 -> 825 | F18: FEB | G18: =G17*1.05 -> 0 | H18: =G17*0.05 -> 0 | J18: FEB | K18: =K17*1.05 -> 231 | L18: =K17*0.05 -> 11 | N18: FEB | O18: =O17*1.05 -> 231 | P18: =O17*0.05 -> 11 | R18: FEB | S18: =S17*1.05 -> 231 | T18: =S17*0.05 -> 11 | W18: FEB | X18: =X17*1.05 -> 231 | Y18: =X17*0.05 -> 11 | AA18: FEB | AB18: =AB17*1.05 -> 231 | AC18: =AB17*0.05 -> 11 | AE18: FEB | AF18: =AF17*1.05 -> 462 | AG18: =AF17*0.05 -> 22 | AI18: FEB | AJ18: =AJ17*1.05 -> 231 | AK18: =AJ17*0.05 -> 11 | AM18: FEB | AN18: =AN17*1.05 -> 231 | AO18: =AN17*0.05 -> 11 | AQ18: FEB | AR18: =AR17*1.05 -> 462 | AS18: =AR17*0.05 -> 22 | AU18: FEB | AV18: =AV17*1.05 -> 231 | AW18: =AV17*0.05 -> 11 | AY18: FEB | AZ18: =AZ17*1.05 -> 231 | BA18: =AZ17*0.05 -> 11 | BC18: FEB | BD18: =BD17*1.05 -> 5775 | BE18: =BD17*0.05 -> 275 | BG18: FEB | BH18: =BH17*1.05 -> 231 | BI18: =BH17*0.05 -> 11 | BK18: FEB | BL18: =BL17*1.05 -> 3465 | BM18: =BL17*0.05 -> 165 | BO18: FEB | BP18: =BP17*1.05 -> 1155 | BQ18: =BP17*0.05 -> 55 | BS18: FEB | BT18: =BT17*1.05 -> 2310 | BU18: =BT17*0.05 -> 110 | BW18: FEB | BX18: =BX17*1.05 -> 1155 | BY18: =BX17*0.05 -> 55 | CA18: FEB | CB18: =CB17*1.05 -> 11550 | CC18: =CB17*0.05 -> 550 | CE18: FEB | CF18: =CF17*1.05 -> 1155 | CG18: =CF17*0.05 -> 55 | CI18: FEB | CJ18: =CJ17*1.05 -> 11550 | CK18: =CJ17*0.05 -> 550 | CM18: FEB | CN18: =CN17*1.05 -> 1155 | CO18: =CN17*0.05 -> 55 | CQ18: FEB | CR18: =CR17*1.05 -> 4620 | CS18: =CR17*0.05 -> 220 | CU18: FEB | CV18: =CV17*1.05 -> 0 | CW18: =CV17*0.05 -> 0 | CY18: FEB | CZ18: =CZ17*1.05 -> 5313 | DA18: =CZ17*0.05 -> 253
